Workbook
Name NativeTimeline_Date: #N/A
Name Slicer_Budget: #N/A
Name Slicer_Campaign: #N/A
Name Slicer_Hole_Type: #N/A

Sheet Dashboard
A1: Drilling to Date
A2: DD
B3: {=_xlfn.LET( _xlpm.cats, _xlfn.VSTACK( 'DDH1 RIG 38'!B5:B149, 'DDH1 RIG 38'!B5:B149, 'DDH1 RIG 41'!B5:B149, 'DDH1 RIG 41'!B5:B149 ), _xlpm.vals, _xlfn.VSTACK( 'DDH1 RIG 38'!F5:F149, 'DDH1 RIG 38'!G5:G149, 'DDH1 RIG 41'!F5:F149, 'DDH1 RIG 41'!G5:G149 ), _xlpm.mask, ISTEXT(_xlpm.vals), _xlpm.c, _xlfn._xlws.FILTER(_xlpm.cats, _xlpm.mask), _xlpm.v, _xlfn._xlws.FILTER(_xlpm.vals, _xlpm.mask), _xlpm.uC, _xlfn.UNIQUE(_xlpm.c), _xlfn.HSTACK( _xlpm.uC, _xlfn.MAP(_xlpm.uC, _xlfn.LAMBDA(_xlpm.x, COUNTA(_xlfn.UNIQUE(_xlfn._xlws.FILTER(_xlpm.v, _xlpm.c=_xlpm.x))))) ) )} -> Met | C3: 27
B4: Geotech | C4: 14
B5: A Vein DD | C5: 7
B6: Infill | C6: 5
B7: G Vein DD | C7: 4
A9: RC
B10: {=_xlfn.LET( _xlpm.cats, _xlfn.VSTACK('STR RIG 18'!B5:B149,'STR RIG 18'!B5:B149,'STR RIG 18'!B5:B149,'STR RIG 18'!B5:B149), _xlpm.vals, _xlfn.VSTACK('STR RIG 18'!E5:E149,'STR RIG 18'!F5:F149,'STR RIG 18'!G5:G149,'STR RIG 18'!H5:H149), _xlpm.mask, ISTEXT(_xlpm.vals), _xlpm.c, _xlfn._xlws.FILTER(_xlpm.cats,_xlpm.mask), _xlpm.v, _xlfn._xlws.FILTER(_xlpm.vals,_xlpm.mask), _xlpm.uC, _xlfn.UNIQUE(_xlpm.c), _xlfn.HSTACK( _xlpm.uC, _xlfn.MAP(_xlpm.uC,_xlfn.LAMBDA(_xlpm.x,COUNTA(_xlfn.UNIQUE(_xlfn._xlws.FILTER(_xlpm.v,_xlpm.c=_xlpm.x))))) ) )} -> A Vein RC | C10: 42
B11: Infill | C11: 38
B12: G Vein RC | C12: 38
D15: Actual | E15: Monthly
A16: S042 | B16: Drilling | C16: vendor | D16: 1223 | F16: Red

Sheet Pivot_Summary
A2: Rig 38
A3: Row Labels | B3: Sum of Total Costs
B4: 3780 | M4: Type | N4: Total Cost
A5: DDRD | B5: 48065.74 | M5: DDRD | N5: =GETPIVOTDATA("Total Costs",$A$3,"Hole Type","DDRD")+GETPIVOTDATA("Total Costs",$A$19,"Hole Type","DDRD") -> 117511.39
A6: GT | B6: 156449.69 | M6: GT | N6: =GETPIVOTDATA("Total Costs",$A$3,"Hole Type","GT")+GETPIVOTDATA("Total Costs",$A$19,"Hole Type","GT") -> 292723.41
A7: Index | B7: 37 | M7: MET | N7: =GETPIVOTDATA("Total Costs",$A$3,"Hole Type","MET")+GETPIVOTDATA("Total Costs",$A$19,"Hole Type","MET") -> 796476.73
A8: MET | B8: 256886.28 | M8: INF | N8: =GETPIVOTDATA("Total Costs",$A$32,"Hole Purpose","INF") -> 474557.5
A9: (blank) | B9: 0 | M9: EXT | N9: =GETPIVOTDATA("Total Costs",$A$32,"Hole Purpose","EXT") -> 208987.98
A10: Grand Total | B10: 465218.71
M11: Total | N11: =SUM(N5:N9) -> 1890257
A18: Rig 41
A19: Row Labels | B19: Sum of Total Costs
A20: DDRD | B20: 69445.65
A21: GT | B21: 136273.72
A22: Index | B22: 37
A23: MET | B23: 539590.45
A24: 45821.71 | B24: 0
A25: 45822.71 | B25: 0
A26: 45823.71 | B26: 0
A27: 45824.71 | B27: 0
A28: (blank) | B28: #VALUE!
A29: Grand Total | B29: #VALUE!
A31: Strike
A32: Row Labels | B32: Sum of Total Costs
A33: EXT | B33: 208987.98
A34: Index | B34: 28
A35: INF | B35: 474557.5
A36: (blank) | B36: 19201.02
A37: Grand Total | B37: 702774.5

Sheet Scheduler
E1: Schedule | H1: =TEXT(H2,"DDDD") -> Thursday | I1: =TEXT(I2,"DDDD") -> Friday | J1: =TEXT(J2,"DDDD") -> Saturday | K1: =TEXT(K2,"DDDD") -> Sunday | L1: =TEXT(L2,"DDDD") -> Monday | M1: =TEXT(M2,"DDDD") -> Tuesday | N1: =TEXT(N2,"DDDD") -> Wednesday | O1: =TEXT(O2,"DDDD") -> Thursday | ... FV1: =TEXT(FV2,"DDDD") -> Saturday
A2: Adequate? | B2: Planned | C2: Actual | E2: Activity Type | F2: Rig | G2: Notes | H2: 45785 | I2: 45786 | J2: 45787 | K2: 45788 | L2: 45789 | M2: 45790 | N2: 45791 | O2: 45792 | P2: 45793 | Q2: 45794 | R2: 45795 | S2: 45796 | T2: 45797 | U2: 45798 | V2: 45799 | W2: 45800 | X2: 45801 | Y2: 45802 | Z2: 45803 | AA2: 45804 | AB2: 45805 | AC2: 45806 | AD2: 45807 | AE2: 45808 | AF2: 45809 | AG2: 45810 | AH2: 45811 | AI2: 45812 | AJ2: 45813 | AK2: 45814 | AL2: 45815 | AM2: 45816 | AN2: 45817 | AO2: 45818 | AP2: 45819 | AQ2: 45820 | AR2: 45821 | AS2: 45822 | AT2: 45823 | AU2: 45824 | AV2: 45825 | AW2: 45826 | AX2: 45827 | AY2: 45828 | AZ2: 45829 | BA2: 45830 | BB2: 45831 | BC2: 45832 | BD2: 45833 | BE2: 45834 | BF2: 45835 | BG2: 45836 | BH2: 45837 | BI2: 45838 | BJ2: 45839 | BK2: 45840 | BL2: 45841 | BM2: 45842 | BN2: 45843 | BO2: 45844 | BP2: 45845 | BQ2: 45846 | BR2: 45847 | BS2: 45848 | BT2: 45849 | BU2: 45850 | BV2: 45851 | BW2: 45852 | BX2: 45853 | BY2: 45854 | BZ2: 45855 | CA2: 45856 | CB2: 45857 | CC2: 45858 | CD2: 45859 | CE2: 45860 | CF2: 45861 | CG2: 45862 | CH2: 45863 | CI2: 45864 | CJ2: 45865 | CK2: 45866 | CL2: 45867 | CM2: 45868 | CN2: 45869 | CO2: 45870 | CP2: 45871 | CQ2: 45872 | CR2: 45873 | CS2: 45874 | CT2: 45875 | CU2: 45876 | CV2: 45877 | CW2: 45878 | CX2: 45879 | CY2: 45880 | CZ2: 45881 | DA2: 45882 | DB2: 45883 | DC2: 45884 | DD2: 45885 | DE2: 45886 | DF2: 45887 | DG2: 45888 | DH2: 45889 | DI2: 45890 | DJ2: 45891 | DK2: 45892 | DL2: 45893 | DM2: 45894 | DN2: 45895 | DO2: 45896 | DP2: 45897 | DQ2: 45898 | DR2: 45899 | DS2: 45900 | DT2: 45901 | DU2: 45902 | DV2: 45903 | DW2: 45904 | DX2: 45905 | DY2: 45906 | DZ2: 45907 | EA2: 45908 | EB2: 45909 | EC2: 45910 | ED2: 45911 | EE2: 45912 | EF2: 45913 | EG2: 45914 | EH2: 45915 | EI2: 45916 | EJ2: 45917 | EK2: 45918 | EL2: 45919 | EM2: 45920 | EN2: 45921 | EO2: 45922 | EP2: 45923 | EQ2: 45924 | ER2: 45925 | ES2: 45926 | ET2: 45927 | EU2: 45928 | EV2: 45929 | EW2: 45930 | EX2: 45931 | EY2: 45932 | EZ2: 45933 | FA2: 45934 | FB2: 45935 | FC2: 45936 | FD2: 45937 | FE2: 45938 | FF2: 45939 | FG2: 45940 | FH2: 45941 | FI2: 45942 | FJ2: 45943 | FK2: 45944 | FL2: 45945 | FM2: 45946 | FN2: 45947 | FO2: 45948 | FP2: 45949 | FQ2: 45950 | FR2: 45951 | FS2: 45952 | FT2: 45953 | FU2: 45954 | FV2: 45955
A3: GENERAL EARTH WORKS | H3: Task 1 - ACCESS | O3: Task 2 - RingRoad | V3: Task 3 - Station Link | BO3: Task 5 - Test Pits | DM3: Task 7 - Rehab
G4: Survey | H4: Initial Survey | BK4: Collar Survey | CP4: Collar Survey | DY4: Collar Survey
E5: DDR1 | G5: Drilling Phase | AW5: Met | AX5: Met | AY5: Met | AZ5: Met | BA5: Met | BB5: Met | BC5: Met | BD5: Met | BE5: Met | BF5: Met | BG5: Met | BH5: Met | BI5: Met | BJ5: Met | BK5: Met | BL5: Met | BM5: Met | BN5: Met | BO5: Met | BP5: Met | BQ5: Met | BR5: Met | BS5: Met | BT5: Met | BU5: Met | BV5: Met | BW5: Met | BX5: Met | BY5: Met | BZ5: Met | CA5: Met | CB5: GeoT* | CC5: GeoT* | CD5: GeoT* | CE5: GeoT* | CF5: GeoT* | CG5: GeoT* | CH5: GeoT* | CI5: GeoT* | CJ5: GeoT* | CK5: Met | CL5: Met | CM5: Met | CN5: Met | CO5: Met | CP5: Met | CQ5: Met | CR5: Met | CS5: GT | CT5: GT | CU5: GT | CV5: GT | CW5: GT | CX5: DDRD | CY5: DDRD | CZ5: DDRD | DA5: Met | DB5: Met | DC5: Met | DD5: Met | DE5: Inf | DF5: Inf | DG5: Inf | DH5: Inf | DI5: ExtG | DJ5: ExtG | DK5: ExtG | DL5: ExtG | DM5: Inf | DN5: Inf | DO5: Inf | DP5: Inf | DQ5: Inf | DR5: Additonal Met | DS5: Additonal Met | DT5: Additonal Met | DU5: Additonal Met | DV5: Additonal Met | DW5: Additonal Met | DX5: Additonal Met | DY5: Additonal Met | DZ5: Additonal Met | EA5: Additonal Met | EB5: Additonal Met | EC5: Additonal Met | ED5: Additonal Met | EE5: Additonal Met | EF5: Additonal Met | EG5: Additonal Met | EH5: Additonal Met | EI5: Additonal Met | EJ5: Additonal Met | EK5: Additonal Met | EL5: Additonal Met | EM5: Additonal Met | EN5: Additonal Met | EO5: Additonal Met | EP5: Additonal Met | EQ5: Additonal Met | ER5: Additonal Met | ES5: Additonal Met | ET5: Additonal Met | EU5: Additonal Met | EV5: Additonal Met | EW5: Additonal Met | EX5: Additonal Met | EY5: Additonal Met | EZ5: Additonal Met | FA5: Additonal Met | FB5: Additonal Met | FC5: Additonal Met | FD5: Additonal Met | FE5: Additonal Met | FF5: Additonal Met | FG5: Additonal Met | FH5: Additonal Met | FI5: Additonal Met | FJ5: Additonal Met | FK5: Additonal Met | FL5: Additonal Met | FM5: Additonal Met | FN5: Additonal Met | FO5: Additonal Met | FP5: Additonal Met | FQ5: Additonal Met | FR5: Additonal Met
A6: =IF((C6+40)>=B6,TRUE,FALSE) -> TRUE | B6: 2045 | C6: =SUM(Y6:XFD6) -> 3260 | E6: Drilling | F6: DD PQ -> HQ | G6: Predicted | AW6: 25 | AX6: 25 | AY6: 25 | AZ6: 25 | BA6: 25 | BB6: 25 | BC6: 25 | BD6: 25 | BE6: 25 | BF6: 25 | BG6: 25 | BH6: 25 | BI6: 25 | BJ6: 25 | BK6: 25 | BL6: 25 | BM6: 25 | BN6: 25 | BO6: 25 | BP6: 25 | BQ6: 25 | BR6: 25 | BS6: 25 | BT6: 25 | BU6: 25 | BV6: 25 | BW6: 25 | BX6: 25 | BY6: 25 | BZ6: 25 | CA6: 25 | CB6: 30 | CC6: 30 | CD6: 30 | CE6: 30 | CF6: 30 | CG6: 30 | CH6: 30 | CI6: 30 | CJ6: 30 | CK6: 25 | CL6: 25 | CM6: 25 | CN6: 25 | CO6: 25 | CP6: 25 | CQ6: 25 | CR6: 25 | CS6: 30 | CT6: 30 | CU6: 30 | CV6: 30 | CW6: 30 | CX6: 30 | CY6: 30 | CZ6: 30 | DA6: 25 | DB6: 25 | DC6: 25 | DD6: 25 | DE6: 30 | DF6: 30 | DG6: 30 | DH6: 30 | DI6: 30 | DJ6: 30 | DK6: 30 | DL6: 30 | DM6: 30 | DN6: 30 | DO6: 30 | DP6: 30 | DQ6: 30 | DR6: 25 | DS6: 25 | DT6: 25 | DU6: 25 | DV6: 25 | DW6: 25 | DX6: 25 | DY6: 25 | DZ6: 25 | EA6: 25 | EB6: 25 | EC6: 15 | ED6: 15 | EE6: 15 | EF6: 15 | EG6: 25 | EH6: 25 | EI6: 25 | EJ6: 25 | EK6: 25 | EL6: 25 | EM6: 25 | EN6: 25 | EO6: 25 | EP6: 25 | EQ6: 25 | ER6: 25 | ES6: 25 | ET6: 25 | EU6: 25 | EV6: 25 | EW6: 25 | EX6: 25 | EY6: 25 | EZ6: 25 | FA6: 25 | FB6: 25 | FC6: 25 | FD6: 25 | FE6: 25 | FF6: 25 | FG6: 25 | FH6: 25 | FI6: 25 | FJ6: 25 | FK6: 25 | FL6: 25 | FM6: 25 | FN6: 25 | FO6: 25 | FP6: 25 | FQ6: 25 | FR6: 25
E7: DR41 | G7: Actual | AV7: 0 | AW7: 51.5 | AX7: 56 | AY7: 52.5 | AZ7: 21.4 | BA7: 58.6 | BB7: 30 | BC7: 32.6 | BD7: 23 | BE7: 65.1 | BF7: 43.9 | BG7: 36.1 | BH7: 45.4 | BI7: 21 | BJ7: 20.6 | BK7: 34.4 | BL7: 15.8 | BM7: 30.4 | BN7: 38.5 | BO7: =17.9+8.3 -> 26.2 | BP7: =10.4+26.4 -> 36.8 | BQ7: =5.6+27 -> 32.6 | BR7: =9.6+11.4 -> 21 | BS7: =7.9+19.6 -> 27.5 | BT7: =18+10.2 -> 28.2 | BU7: =10.8+21 -> 31.8 | BV7: =3+14.5 -> 17.5 | BW7: =12.7+24 -> 36.7 | BX7: =10.3+13.8 -> 24.1 | BY7: 33 | BZ7: =20.7+11.5 -> 32.2 | CA7: =21.8+12 -> 33.8 | CB7: =30.6+30 -> 60.6 | CC7: =30+19.4 -> 49.4 | CD7: =30.6+30 -> 60.6 | CE7: =30+19.4 -> 49.4 | CF7: =11.9+30.5 -> 42.4 | CG7: 60 | CH7: =17.6+18.5 -> 36.1 | CI7: =60 -> 60 | CJ7: =30+21.5 -> 51.5 | CK7: 39.2 | CL7: 16.6 | CM7: 22.4 | CN7: 43.9 | CO7: 48.4 | CP7: 24.6 | CQ7: 49.7 | CR7: 29.8 | CS7: 24.3 | CT7: 63.7 | CU7: 28.7 | CV7: 64.8 | CW7: 45.7 | CX7: 59.3 | CY7: 44.9 | CZ7: 44.1 | DA7: 7.2 | DB7: 44.4 | DC7: 30 | DD7: 30.8 | DE7: 66.4 | DF7: 66 | DG7: 69 | DH7: 33 | DI7: 57.5 | DJ7: 16.5 | DK7: 72.7 | DL7: 46.8 | DM7: 68 | DN7: 51 | DO7: 30 | DP7: 35.9 | DQ7: 72.7 | DR7: 21.4 | DS7: 42 | DT7: =SUM(DT6:DU6) -> 50 | DU7: =SUM(DU6:DV6) -> 50 | DV7: =SUM(DV6:DW6) -> 50 | DW7: =SUM(DW6:DX6) -> 50 | DX7: =SUM(DX6:DY6) -> 50 | DY7: =SUM(DY6:DZ6) -> 50 | DZ7: =SUM(DZ6:EA6) -> 50 | EA7: 30.4 | EB7: 32.5 | EC7: 0.5 | ED7: 33 | EE7: 13.6 | EF7: 30.6 | EG7: 27.7 | EH7: 26.7 | EI7: 15.5 | EJ7: 30 | EK7: 22.2 | EL7: 28.8 | EM7: 23.5 | EN7: 12.6 | EO7: 29.7 | EP7: 24.3 | EQ7: 24 | ER7: 29.4 | ES7: 5.9 | ET7: 12.6 | EU7: 27 | EV7: 48 | EW7: 48.4 | EX7: 31.2 | EY7: 37 | EZ7: 32.7 | FA7: 27.2 | FB7: 6.8 | FC7: 10.9 | FD7: 12 | FE7: 4.7 | FF7: 39 | FG7: 8.9 | FH7: 27 | FI7: 21 | FJ7: 21 | FK7: 22.7 | FL7: 30.1 | FM7: 0 | FN7: 46.1 | FO7: 37 | FP7: 29.7
G8: Difference | AV8: =IF(ISBLANK(AV7),"",AV7-AV6) -> 0 | AW8: =IF(ISBLANK(AW7),"",AW7-AW6) -> 26.5 | AX8: =IF(ISBLANK(AX7),"",AX7-AX6) -> 31 | AY8: =IF(ISBLANK(AY7),"",AY7-AY6) -> 27.5 | AZ8: =IF(ISBLANK(AZ7),"",AZ7-AZ6) -> -3.6 | BA8: =IF(ISBLANK(BA7),"",BA7-BA6) -> 33.6 | BB8: =IF(ISBLANK(BB7),"",BB7-BB6) -> 5 | BC8: =IF(ISBLANK(BC7),"",BC7-BC6) -> 7.6 | ... FR8: =IF(ISBLANK(FR7),"",FR7-FR6)
G9: Cumulative Difference | AV9: =IFERROR(IF(ISBLANK(AV8),"",AV8+AU9),"") -> 0 | AW9: =IFERROR(IF(ISBLANK(AW8),"",AW8+AV9),"") -> 26.5 | AX9: =IFERROR(IF(ISBLANK(AX8),"",AX8+AW9),"") -> 57.5 | AY9: =IFERROR(IF(ISBLANK(AY8),"",AY8+AX9),"") -> 85 | AZ9: =IFERROR(IF(ISBLANK(AZ8),"",AZ8+AY9),"") -> 81.4 | BA9: =IFERROR(IF(ISBLANK(BA8),"",BA8+AZ9),"") -> 115 | BB9: =IFERROR(IF(ISBLANK(BB8),"",BB8+BA9),"") -> 120 | BC9: =IFERROR(IF(ISBLANK(BC8),"",BC8+BB9),"") -> 127.6 | ... FR9: =IFERROR(IF(ISBLANK(FR8),"",FR8+FQ9),"")
G10: 7 Day rolling average | BB10: =IFERROR(AVERAGE(AV7:BB7),"") -> 38.571429 | BI10: =IFERROR(AVERAGE(BC7:BI7),"") -> 38.157143 | BP10: =IFERROR(AVERAGE(BJ7:BP7),"") -> 28.957143 | BW10: =IFERROR(AVERAGE(BQ7:BW7),"") -> 27.9 | CD10: =IFERROR(AVERAGE(BX7:CD7),"") -> 41.957143 | CK10: =IFERROR(AVERAGE(CE7:CK7),"") -> 48.371429 | CR10: =IFERROR(AVERAGE(CL7:CR7),"") -> 33.628571 | CY10: =IFERROR(AVERAGE(CS7:CY7),"") -> 47.342857 | DF10: =IFERROR(AVERAGE(CZ7:DF7),"") -> 41.271429 | DM10: =IFERROR(AVERAGE(DF7:DL7),"") -> 51.642857 | DT10: =IFERROR(AVERAGE(DN7:DT7),"") -> 43.285714 | EA10: =IFERROR(AVERAGE(DU7:EA7),"") -> 47.2 | EH10: =IFERROR(AVERAGE(EB7:EH7),"") -> 23.514286 | EO10: =IFERROR(AVERAGE(EI7:EO7),"") -> 23.185714 | EV10: =IFERROR(AVERAGE(EP7:EV7),"") -> 24.457143 | FC10: =IFERROR(AVERAGE(EW7:FC7),"") -> 27.742857 | FJ10: =IFERROR(AVERAGE(FD7:FJ7),"") -> 19.085714 | FQ10: =IFERROR(AVERAGE(FK7:FQ7),"") -> 27.6
A11: Enabling Earthwork's Task | Y11: Task 4.1 - Prelim Pad Prep | Z11: Task 4.1 - Prelim Pad Prep | AA11: Task 4.1 - Prelim Pad Prep | AK11: Task 4.1 - Prelim Pad Prep | AL11: Task 4.1 - Prelim Pad Prep | AM11: Task 4.1 - Prelim Pad Prep
A12: =IF((C12+2.5)>=B12,TRUE,FALSE) -> TRUE | B12: 13 | C12: =SUM(Y12:XFD12) -> 15 | E12: Earthworks | Y12: 2.5 | Z12: 2.5 | AA12: 2.5 | AK12: 2.5 | AL12: 2.5 | AM12: 2.5 | FB12: task 7 | FC12: task 7 | FD12: task 7 | FE12: task 7 | FF12: task 7 | FG12: task 7 | FH12: task 7 | FI12: task 7 | FJ12: task 7 | FK12: task 7 | FL12: task 7 | FM12: task 7 | FN12: task 7 | FO12: task 7 | FP12: task 7 | FQ12: task 7 | FR12: task 7 | FS12: task 7 | FT12: task 7 | FU12: task 7 | FV12: task 7
E13: DDR2 | G13: Drilling Phase | BQ13: Met | BR13: Met | BS13: Met | BT13: Met | BU13: Met | BV13: Met | BW13: Met | BX13: Met | BY13: Met | BZ13: Met | CA13: Met | CB13: Met | CC13: GeoT * | CD13: GeoT * | CE13: GeoT * | CF13: Met | CG13: Met | CH13: GeoT * | CI13: GeoT * | CJ13: GeoT * | CK13: GeoT * | CL13: GeoT * | CM13: GeoT * | CN13: GeoT * | CO13: Met | CP13: Met | CQ13: Met | CR13: Met | CS13: Met | CT13: Met | CU13: Met | CV13: ExtA | CW13: ExtA | CX13: ExtA | CY13: GT | CZ13: ExtA | DA13: ExtA | DB13: ExtA | DC13: ExtA | DD13: Inf | DE13: Inf | DF13: ExtG | DG13: ExtG | DH13: ExtG | DI13: Inf | DJ13: Inf | DK13: Inf | DL13: Inf | DM13: Inf | DN13: Inf | DO13: Inf | DP13: Inf | DQ13: Inf | DR13: Inf | DS13: Inf | DT13: Inf | DU13: Inf | DV13: Inf | DW13: Inf | DX13: Inf | DY13: Inf | DZ13: Inf | EA13: Inf | EB13: ExtA | EC13: ExtA | ED13: ExtA | EE13: ExtA | EF13: ExtA | EG13: ExtA | EH13: ExtA | EI13: ExtA | EJ13: ExtA | EK13: ExtA | EL13: ExtA | EM13: ExtG | EN13: ExtG | EO13: ExtG | EP13: ExtG | EQ13: ExtG | ER13: ExtG | ES13: ExtG | ET13: ExtG | EU13: ExtG | EV13: ExtG | EW13: ExtG
A14: =IF((C14+40)>=B14,TRUE,FALSE) -> FALSE | B14: 3421 | C14: =SUM(Y14:XFD14) -> 3135 | E14: Drilling | F14: DD HQ | G14: Predicted | BQ14: 25 | BR14: 25 | BS14: 25 | BT14: 25 | BU14: 25 | BV14: 25 | BW14: 25 | BX14: 25 | BY14: 25 | BZ14: 25 | CA14: 25 | CB14: 25 | CC14: 30 | CD14: 30 | CE14: 30 | CF14: 25 | CG14: 25 | CH14: 30 | CI14: 30 | CJ14: 30 | CK14: 30 | CL14: 30 | CM14: 30 | CN14: 30 | CO14: 25 | CP14: 25 | CQ14: 25 | CR14: 25 | CS14: 25 | CT14: 25 | CU14: 25 | CV14: 30 | CW14: 30 | CX14: 30 | CY14: 30 | CZ14: 30 | DA14: 30 | DB14: 30 | DC14: 30 | DD14: 30 | DE14: 30 | DF14: 30 | DG14: 30 | DH14: 30 | DI14: 30 | DJ14: 30 | DK14: 30 | DL14: 30 | DM14: 30 | DN14: 30 | DO14: 30 | DP14: 30 | DQ14: 30 | DR14: 30 | DS14: 30 | DT14: 30 | DU14: 30 | DV14: 30 | DW14: 30 | DX14: 30 | DY14: 30 | DZ14: 30 | EA14: 30 | EB14: 30 | EC14: 30 | ED14: 30 | EE14: 30 | EF14: 30 | EG14: 30 | EH14: 30 | EI14: 30 | EJ14: 30 | EK14: 30 | EL14: 30 | EM14: 30 | EN14: 30 | EO14: 30 | EP14: 30 | EQ14: 30 | ER14: 30 | ES14: 30 | ET14: 30 | EU14: 30 | EV14: 30 | EW14: 30 | EX14: 30 | EY14: 30 | EZ14: 30 | FA14: 30 | FB14: 30 | FC14: 30 | FD14: 30 | FE14: 30 | FF14: 30 | FG14: 30 | FH14: 30 | FI14: 30 | FJ14: 30 | FK14: 30 | FL14: 30 | FM14: 30 | FN14: 30 | FO14: 30 | FP14: 30 | FQ14: 30 | FR14: 30 | FS14: 30 | FT14: 30
E15: DR38 | G15: Actual | BQ15: =11+15.6 -> 26.6 | BR15: =7.1+30 -> 37.1 | BS15: =20.4+15.6 -> 36 | BT15: =19+16.5 -> 35.5 | BU15: =22.9+21.2 -> 44.1 | BV15: =13.2+27.3 -> 40.5 | BW15: =19.6+20.5 -> 40.1 | BX15: 60.1 | BY15: =19+21.8 -> 40.8 | BZ15: =26.2+27.7 -> 53.9 | CA15: =6+14.9 -> 20.9 | CB15: 60.7 | CC15: =8.3+17.5 -> 25.8 | CD15: =21.5+21.9 -> 43.4 | CE15: =11+16.4 -> 27.4 | CF15: =7.6+27.4 -> 35 | CG15: =29.6+16.4 -> 46 | CH15: 7.8 | CI15: 14.2 | CJ15: 21.3 | CK15: 57.4 | CL15: 29 | CM15: 24 | CN15: 20.2 | CO15: 34.5 | CP15: 45.7 | CQ15: 60 | CR15: 22.1 | CS15: 38 | CT15: 34 | CU15: 10.7 | CV15: 23 | CW15: 62.6 | CX15: 27.7 | CY15: 72 | CZ15: 22.7 | DA15: 57.2 | DB15: 46 | DC15: 59.6 | DD15: 24.5 | DE15: 71.6 | DF15: 37 | DG15: 60.5 | DH15: 48.6 | DI15: 40.6 | DJ15: 64.5 | DK15: 63.5 | DL15: 62.2 | DM15: 30.9 | DN15: 71.9 | DO15: 62.4 | DP15: 39.8 | DQ15: 66 | DR15: 22.3 | DS15: DEMOB
G16: Difference | BQ16: =IF(ISBLANK(BQ15),"",BQ15-BQ14) -> 1.6 | BR16: =IF(ISBLANK(BR15),"",BR15-CN14) -> 7.1 | BS16: =IF(ISBLANK(BS15),"",BS15-CO14) -> 11 | BT16: =IF(ISBLANK(BT15),"",BT15-CP14) -> 10.5 | BU16: =IF(ISBLANK(BU15),"",BU15-CQ14) -> 19.1 | BV16: =IF(ISBLANK(BV15),"",BV15-CS14) -> 15.5 | BW16: =IF(ISBLANK(BW15),"",BW15-CT14) -> 15.1 | BX16: =IF(ISBLANK(BX15),"",BX15-CU14) -> 35.1 | BY16: =IF(ISBLANK(BY15),"",BY15-CV14) -> 10.8 | BZ16: =IF(ISBLANK(BZ15),"",BZ15-CW14) -> 23.9 | CA16: =IF(ISBLANK(CA15),"",CA15-CX14) -> -9.1 | CB16: =IF(ISBLANK(CB15),"",CB15-CY14) -> 30.7 | CC16: =IF(ISBLANK(CC15),"",CC15-CZ14) -> -4.2 | ... EW16: =IF(ISBLANK(EW15),"",EW15-FT14)
G17: Cumulative Difference | BQ17: =IFERROR(IF(ISBLANK(BQ16),"",BQ16+BP17),"") -> 1.6 | BR17: =IFERROR(IF(ISBLANK(BR16),"",BR16+BQ17),"") -> 8.7 | BS17: =IFERROR(IF(ISBLANK(BS16),"",BS16+BR17),"") -> 19.7 | BT17: =IFERROR(IF(ISBLANK(BT16),"",BT16+BS17),"") -> 30.2 | BU17: =IFERROR(IF(ISBLANK(BU16),"",BU16+BT17),"") -> 49.3 | BV17: =IFERROR(IF(ISBLANK(BV16),"",BV16+BU17),"") -> 64.8 | BW17: =IFERROR(IF(ISBLANK(BW16),"",BW16+BV17),"") -> 79.9 | BX17: =IFERROR(IF(ISBLANK(BX16),"",BX16+BW17),"") -> 115 | ... EW17: =IFERROR(IF(ISBLANK(EW16),"",EW16+EV17),"")
BW18: =IFERROR(AVERAGE(BQ15:BW15),"") -> 37.128571 | CD18: =IFERROR(AVERAGE(BX15:CD15),"") -> 43.657143 | CK18: =IFERROR(AVERAGE(CE15:CK15),"") -> 29.871429
A19: Enabling Earthwork's Task | AA19: Task 4.1 - Prelim Pad Prep | AB19: Task 4.1 - Prelim Pad Prep | AC19: Task 4.1 - Prelim Pad Prep | AN19: Task 4.2 - Complete Pad Prep | AO19: Task 4.2 - Complete Pad Prep
A20: =IF((C20+2.5)>=B20,TRUE,FALSE) -> TRUE | B20: 29 | C20: =SUM(Y20:XFD20) -> 33 | E20: Earthworks | AA20: 2.5 | AB20: 2.5 | AC20: 2.5 | AN20: 8.5 | AO20: 8.5 | BP20: 8.5
E21: RCD1 | G21: Drilling Phase | BC21: ExtA | BD21: ExtA | BE21: ExtA | BF21: ExtA | BG21: ExtA | BH21: ExtA | BI21: ExtA | BJ21: ExtA | BK21: ExtA | BL21: ExtA | BM21: ExtA | BN21: ExtA | BO21: ExtA | BP21: ExtA | BQ21: ExtA | BR21: ExtA | BS21: ExtG | BT21: ExtG | BU21: ExtG | BV21: ExtG | BW21: ExtG | BX21: ExtG | BY21: ExtG | BZ21: ExtG | CA21: ExtG | CB21: ExtG | CC21: ExtG | CD21: ExtG | CE21: ExtG | CF21: ExtG | CG21: ExtG | CH21: ExtG | CI21: ExtG | CJ21: Inf | CK21: Inf | CL21: Inf | CM21: Inf | CN21: Inf | CO21: Inf | CP21: Inf | CQ21: Inf | CR21: Inf | CS21: Inf | CT21: Inf | CU21: Inf | CV21: Inf | CW21: Inf | CX21: Inf | CY21: Inf | CZ21: Inf | DA21: Inf | DB21: Inf | DC21: Inf | DD21: Inf | DE21: Inf | DF21: Inf | DG21: Inf | DH21: Inf | DI21: Inf | DJ21: Inf | DK21: Inf | DL21: Inf | DM21: Inf | DN21: Inf | DO21: Inf | DP21: Inf | DQ21: Inf | DR21: Inf | DS21: Inf | DT21: Inf | DU21: Inf | DV21: Inf | DW21: Inf | DX21: Inf | DY21: Inf | DZ21: Inf | EA21: Inf | EB21: Inf | EC21: Inf | ED21: Inf | EE21: Inf | EF21: Inf | EG21: Inf | EH21: Inf | EI21: Inf | EJ21: Inf | EK21: Inf | EL21: Inf | EM21: Inf | EN21: Inf | EO21: Dingo | EP21: Dingo | EQ21: Dingo | ER21: Dingo | ES21: Dingo
A22: =IF((C22+200)>=B22,TRUE,FALSE) -> #REF! | B22: =(29549.1-#REF!)/2 -> #REF! | C22: =SUM(Y22:XFD22) -> 14250 | E22: Drilling | F22: RC 1 | G22: Predicted | BC22: 150 | BD22: 150 | BE22: 150 | BF22: 150 | BG22: 150 | BH22: 150 | BI22: 150 | BJ22: 150 | BK22: 150 | BL22: 150 | BM22: 150 | BN22: 150 | BO22: 150 | BP22: 150 | BQ22: 150 | BR22: 150 | BS22: 150 | BT22: 150 | BU22: 150 | BV22: 150 | BW22: 150 | BX22: 150 | BY22: 150 | BZ22: 150 | CA22: 150 | CB22: 150 | CC22: 150 | CD22: 150 | CE22: 150 | CF22: 150 | CG22: 150 | CH22: 150 | CI22: 150 | CJ22: 150 | CK22: 150 | CL22: 150 | CM22: 150 | CN22: 150 | CO22: 150 | CP22: 150 | CQ22: 150 | CR22: 150 | CS22: 150 | CT22: 150 | CU22: 150 | CV22: 150 | CW22: 150 | CX22: 150 | CY22: 150 | CZ22: 150 | DA22: 150 | DB22: 150 | DC22: 150 | DD22: 150 | DE22: 150 | DF22: 150 | DG22: 150 | DH22: 150 | DI22: 150 | DJ22: 150 | DK22: 150 | DL22: 150 | DM22: 150 | DN22: 150 | DO22: 150 | DP22: 150 | DQ22: 150 | DR22: 150 | DS22: 150 | DT22: 150 | DU22: 150 | DV22: 150 | DW22: 150 | DX22: 150 | DY22: 150 | DZ22: 150 | EA22: 150 | EB22: 150 | EC22: 150 | ED22: 150 | EE22: 150 | EF22: 150 | EG22: 150 | EH22: 150 | EI22: 150 | EJ22: 150 | EK22: 150 | EL22: 150 | EM22: 150 | EN22: 150 | EO22: 150 | EP22: 150 | EQ22: 150 | ER22: 150 | ES22: 150
G23: Actual | BC23: 46 | BD23: 100 | BE23: 160 | BF23: 206 | BG23: 188 | BH23: 212 | BI23: 181 | BJ23: 148 | BK23: 187 | BL23: 200 | BM23: 72 | BN23: 118 | BO23: 242 | BP23: 190 | BQ23: 0 | BR23: 0 | BS23: 0 | BT23: 152 | BU23: 146 | BV23: 154 | BW23: 140 | BX23: 124 | BY23: 46 | BZ23: 150 | CA23: 200 | CB23: 216 | CC23: 284 | CD23: 212 | CE23: 202 | CF23: 176 | CG23: 0 | CH23: 0 | CI23: 194 | CJ23: 242 | CK23: 220 | CL23: 136 | CM23: 46 | CN23: 190 | CO23: 214 | CP23: 184 | CQ23: 96 | CR23: 194 | CS23: 180 | CT23: 202 | CU23: 52 | CV23: 226 | CW23: 242 | CX23: 300 | CY23: 224 | CZ23: 302 | DA23: 260 | DB23: 252 | DC23: 258 | DD23: 252 | DE23: 260 | DF23: 254 | DG23: 302 | DH23: 308 | DI23: 256 | DJ23: 280 | DK23: 210 | DL23: 258 | DM23: 220 | DN23: 300 | DO23: 302 | DP23: 238 | DQ23: 250 | DR23: 236 | DS23: 202 | DT23: 218 | DU23: 214 | DV23: 206 | DW23: 102 | DX23: 176 | DY23: 224 | DZ23: 160 | EA23: DEMOB
G24: Difference | BC24: =IF(ISBLANK(BC23),"",BC23-BC22) -> -104 | BD24: =IF(ISBLANK(BD23),"",BD23-BD22) -> -50 | BE24: =IF(ISBLANK(BE23),"",BE23-BE22) -> 10 | BF24: =IF(ISBLANK(BF23),"",BF23-BF22) -> 56 | BG24: =IF(ISBLANK(BG23),"",BG23-BG22) -> 38 | BH24: =IF(ISBLANK(BH23),"",BH23-BH22) -> 62 | BI24: =IF(ISBLANK(BI23),"",BI23-BI22) -> 31 | BJ24: =IF(ISBLANK(BJ23),"",BJ23-BJ22) -> -2 | ... ES24: =IF(ISBLANK(ES23),"",ES23-ES22)
G25: Cumulative Difference | BC25: =IFERROR(IF(ISBLANK(BC24),"",BC24+BB25),"") -> -104 | BD25: =IFERROR(IF(ISBLANK(BD24),"",BD24+BC25),"") -> -154 | BE25: =IFERROR(IF(ISBLANK(BE24),"",BE24+BD25),"") -> -144 | BF25: =IFERROR(IF(ISBLANK(BF24),"",BF24+BE25),"") -> -88 | BG25: =IFERROR(IF(ISBLANK(BG24),"",BG24+BF25),"") -> -50 | BH25: =IFERROR(IF(ISBLANK(BH24),"",BH24+BG25),"") -> 12 | BI25: =IFERROR(IF(ISBLANK(BI24),"",BI24+BH25),"") -> 43 | BJ25: =IFERROR(IF(ISBLANK(BJ24),"",BJ24+BI25),"") -> 41 | ... ES25: =IFERROR(IF(ISBLANK(ES24),"",ES24+ER25),"")
G26: 7 Day rolling average | BH26: =IFERROR(AVERAGE(BB23:BH23),"") -> 152 | BO26: =IFERROR(AVERAGE(BI23:BO23),"") -> 164 | BV26: =IFERROR(AVERAGE(BP23:BV23),"") -> 91.714286 | CC26: =IFERROR(AVERAGE(BW23:CC23),"") -> 165.71429 | CJ26: =IFERROR(AVERAGE(CD23:CJ23),"") -> 146.57143 | CQ26: =IFERROR(AVERAGE(CK23:CQ23),"") -> 155.14286 | CR26: =IFERROR(AVERAGE(CL23:CR23),"") -> 151.42857 | CY26: =IFERROR(AVERAGE(CS23:CY23),"") -> 203.71429 | DF26: =IFERROR(AVERAGE(CZ23:DF23),"") -> 262.57143 | DM26: =IFERROR(AVERAGE(DG23:DM23),"") -> 262 | DT26: =IFERROR(AVERAGE(DN23:DT23),"") -> 249.42857 | EA26: =IFERROR(AVERAGE(DU23:EA23),"") -> 180.33333 | EH26: =IFERROR(AVERAGE(EB23:EH23),"") | EO26: =IFERROR(AVERAGE(EI23:EO23),"") | EV26: =IFERROR(AVERAGE(EP23:EV23),"")
A27: Enabling Earthwork's Task | AC27: Task 4.1 - Prelim Pad Prep | AD27: Task 4.1 - Prelim Pad Prep | AE27: Task 4.1 - Prelim Pad Prep | AG27: Task 4.1 - Prelim Pad Prep | AH27: Task 4.1 - Prelim Pad Prep | AI27: Task 4.1 - Prelim Pad Prep | AJ27: Task 4.1 - Prelim Pad Prep | AK27: Task 4.1 - Prelim Pad Prep | AP27: Task 4.2 - Complete Pad Prep | AQ27: Task 4.2 - Complete Pad Prep | AR27: Task 4.2 - Complete Pad Prep | AS27: Task 4.2 - Complete Pad Prep | AT27: Task 4.2 - Complete Pad Prep | AU27: Task 4.2 - Complete Pad Prep | AV27: Task 4.2 - Complete Pad Prep | BF27: Task 4.2 - Complete Pad Prep | BG27: Task 4.2 - Complete Pad Prep | BH27: Task 4.2 - Complete Pad Prep | BI27: Task 4.2 - Complete Pad Prep | BJ27: Task 4.2 - Complete Pad Prep
A28: =IF((C28+2.5)>=B28,TRUE,FALSE) -> TRUE | B28: 116.5 | C28: =SUM(Y28:XFD28) -> 123 | E28: Earthworks | AC28: 2.5 | AD28: 2.5 | AE28: 2.5 | AG28: 2.5 | AH28: 2.5 | AI28: 2.5 | AJ28: 2.5 | AK28: 2.5 | AP28: 8.5 | AQ28: 8.5 | AR28: 8.5 | AS28: 8.5 | AT28: 8.5 | AU28: 8.5 | AV28: 8.5 | BF28: 8.5 | BG28: 8.5 | BH28: 8.5 | BI28: 8.5 | BJ28: 9.5
E29: RCD2 | G29: Drilling Phase | BI29: ExtA | BJ29: ExtA | BK29: ExtA | BL29: ExtA | BM29: ExtA | BN29: ExtA | BO29: ExtA | BP29: ExtA | BQ29: ExtA | BR29: ExtG | BS29: ExtG | BT29: ExtG | BU29: ExtG | BV29: ExtG | BW29: ExtG | BX29: ExtG | BY29: ExtG | BZ29: ExtG | CA29: ExtG | CB29: ExtG | CC29: ExtG | CD29: ExtG | CE29: ExtG | CF29: ExtG | CG29: ExtG | CH29: Inf | CI29: Inf | CJ29: Inf | CK29: Inf | CL29: Inf | CM29: Inf | CN29: Inf | CO29: Inf | CP29: Inf | CQ29: Inf | CR29: Inf | CS29: Inf | CT29: Inf | CU29: Inf | CV29: Inf | CW29: Inf | CX29: Inf | CY29: Inf | CZ29: Inf | DA29: Inf | DB29: Inf | DC29: Inf | DD29: Inf | DE29: Inf | DF29: Inf | DG29: Inf | DH29: Inf | DI29: Inf | DJ29: Inf | DK29: Inf | DL29: Inf | DM29: Inf | DN29: Inf | DO29: Inf | DP29: Inf | DQ29: Inf | DR29: Inf | DS29: Inf | DT29: Inf | DU29: Inf | DV29: Inf | DW29: Inf | DX29: Inf | DY29: Inf | DZ29: Inf | EA29: Inf | EB29: Inf | EC29: Inf | ED29: Inf | EE29: Inf | EF29: Inf | EG29: Inf | EH29: Inf | EI29: Inf | EJ29: Inf | EK29: Inf | EL29: Inf | EM29: Inf | EN29: Inf | EO29: Inf | EP29: Inf | EQ29: Inf | ER29: South | ES29: South | ET29: South | EU29: South
A30: =IF((C30+200)>=B30,TRUE,FALSE) -> #REF! | B30: =(29549.1-#REF!)/2 -> #REF! | C30: =SUM(Y30:XFD30) -> 13850 | E30: Drilling | F30: RC 2 | G30: Predicted | BI30: 150 | BJ30: 150 | BK30: 150 | BL30: 150 | BM30: 150 | BN30: 150 | BO30: 150 | BP30: 150 | BQ30: 150 | BR30: 150 | BS30: 150 | BT30: 150 | BU30: 150 | BV30: 150 | BW30: 150 | BX30: 150 | BY30: 150 | BZ30: 150 | CA30: 150 | CB30: 150 | CC30: 150 | CD30: 150 | CE30: 150 | CF30: 150 | CG30: 150 | CH30: 150 | CI30: 150 | CJ30: 150 | CK30: 150 | CL30: 150 | CM30: 150 | CN30: 150 | CO30: 150 | CP30: 150 | CQ30: 150 | CR30: 150 | CS30: 150 | CT30: 150 | CU30: 150 | CV30: 150 | CW30: 150 | CX30: 150 | CY30: 150 | CZ30: 150 | DA30: 150 | DB30: 150 | DC30: 150 | DD30: 150 | DE30: 150 | DF30: 150 | DG30: 150 | DH30: 150 | DI30: 150 | DJ30: 150 | DK30: 150 | DL30: 150 | DM30: 150 | DN30: 150 | DO30: 150 | DP30: 150 | DQ30: 150 | DR30: 150 | DS30: 150 | DT30: 150 | DU30: 150 | DV30: 150 | DW30: 150 | DX30: 150 | DY30: 150 | DZ30: 150 | EA30: 150 | EB30: 150 | EC30: 150 | ED30: 150 | EE30: 150 | EF30: 150 | EG30: 150 | EH30: 150 | EI30: 150 | EJ30: 150 | EK30: 150 | EL30: 150 | EM30: 150 | EN30: 150 | EO30: 150 | EP30: 150 | EQ30: 150 | ER30: 200 | ES30: 200 | ET30: 200 | EU30: 200
G31: Actual
G32: Difference | BI32: =IF(ISBLANK(BI31),"",BI31-BI30) | BJ32: =IF(ISBLANK(BJ31),"",BJ31-BJ30) | BK32: =IF(ISBLANK(BK31),"",BK31-BK30) | BL32: =IF(ISBLANK(BL31),"",BL31-BL30) | BM32: =IF(ISBLANK(BM31),"",BM31-BM30) | BN32: =IF(ISBLANK(BN31),"",BN31-BN30) | BO32: =IF(ISBLANK(BO31),"",BO31-BO30) | BP32: =IF(ISBLANK(BP31),"",BP31-BP30) | ... EU32: =IF(ISBLANK(EU31),"",EU31-EU30)
G33: Cumulative Difference | BI33: =IFERROR(IF(ISBLANK(BI32),"",BI32+BH33),"") | BJ33: =IFERROR(IF(ISBLANK(BJ32),"",BJ32+BI33),"") | BK33: =IFERROR(IF(ISBLANK(BK32),"",BK32+BJ33),"") | BL33: =IFERROR(IF(ISBLANK(BL32),"",BL32+BK33),"") | BM33: =IFERROR(IF(ISBLANK(BM32),"",BM32+BL33),"") | BN33: =IFERROR(IF(ISBLANK(BN32),"",BN32+BM33),"") | BO33: =IFERROR(IF(ISBLANK(BO32),"",BO32+BN33),"") | BP33: =IFERROR(IF(ISBLANK(BP32),"",BP32+BO33),"") | ... EU33: =IFERROR(IF(ISBLANK(EU32),"",EU32+ET33),"")
A35: Enabling Earthwork's Task | AE35: Task 4.1 - Prelim Pad Prep | AF35: Task 4.1 - Prelim Pad Prep | AG35: Task 4.1 - Prelim Pad Prep | AW35: Task 4.2 - Complete Pad Prep | AX35: Task 4.2 - Complete Pad Prep | AY35: Task 4.2 - Complete Pad Prep | AZ35: Task 4.2 - Complete Pad Prep | BA35: Task 4.2 - Complete Pad Prep | BB35: Task 4.2 - Complete Pad Prep | BC35: Task 4.2 - Complete Pad Prep | BD35: Task 4.2 - Complete Pad Prep | BE35: Task 4.2 - Complete Pad Prep | BK35: Task 4.2 - Complete Pad Prep | BL35: Task 4.2 - Complete Pad Prep | BM35: Task 4.2 - Complete Pad Prep | BN35: Task 4.2 - Complete Pad Prep
A36: =IF((C36+2.5)>=B36,TRUE,FALSE) -> TRUE | B36: 117.5 | C36: =SUM(Y36:XFD36) -> 118 | E36: Earthworks | AE36: 2.5 | AF36: 2.5 | AG36: 2.5 | AW36: 8.5 | AX36: 8.5 | AY36: 8.5 | AZ36: 8.5 | BA36: 8.5 | BB36: 8.5 | BC36: 8.5 | BD36: 8.5 | BE36: 8.5 | BK36: 8.5 | BL36: 8.5 | BM36: 8.5 | BN36: 8.5
E37: HYD1 | G37: Drilling Phase | BS37: Bores | BT37: Bores | BU37: Bores | BV37: Bores | BW37: Bores | BX37: Bores | BY37: Bores | BZ37: Bores | CA37: Bores | CB37: Bores | CC37: Bores | CD37: Bores | CE37: Bores | CF37: Bores | CG37: Bores | CH37: Bores | CI37: Bores | CJ37: Bores | CK37: Bores | CL37: Bores | CM37: Bores | CN37: Bores | CO37: Bores | CP37: Bores | CQ37: Bores | CR37: Bores | CS37: Bores | CT37: Bores | CU37: Bores | CV37: Bores | CW37: Bores | CX37: Bores | CY37: Bores | CZ37: Bores | DA37: Bores | DB37: Bores | DC37: Bores | DD37: Bores | DE37: Bores
E38: Rig 18 | F38: Drilling | G38: Predicted | BS38: 22 | BT38: 22 | BU38: 22 | BV38: 22 | BW38: 22 | BX38: 22 | BY38: 22 | BZ38: 22 | CA38: 22 | CB38: 22 | CC38: 22 | CD38: 22 | CE38: 22 | CF38: 22 | CG38: 22 | CH38: 22 | CI38: 22 | CJ38: 22 | CK38: 22 | CL38: 22 | CM38: 22 | CN38: 22 | CO38: 22 | CP38: 22 | CQ38: 22 | CR38: 22 | CS38: 22 | CT38: 22 | CU38: 22 | CV38: 22 | CW38: 22 | CX38: 22 | CY38: 22 | CZ38: 22 | DA38: 22 | DB38: 22 | DC38: 22 | DD38: 22 | DE38: 22
G39: Actual | BS39: 78 | BT39: 36 | BU39: 6 | BV39: 90 | BW39: 30 | BX39: 125 | BY39: 96 | BZ39: 63 | CA39: 0 | CB39: 0 | CC39: 0 | CD39: 0 | CE39: 0 | CF39: 0 | CG39: 0 | CH39: 3 | CI39: 27 | CJ39: 70 | CK39: 24 | CL39: 46 | CM39: 34 | CN39: 74 | CO39: 28 | CP39: 30 | CQ39: 18
G40: Difference | BS40: =IF(ISBLANK(BS39),"",BS39-BS38) -> 56 | BT40: =IF(ISBLANK(BT39),"",BT39-BT38) -> 14 | BU40: =IF(ISBLANK(BU39),"",BU39-BU38) -> -16 | BV40: =IF(ISBLANK(BV39),"",BV39-BV38) -> 68 | BW40: =IF(ISBLANK(BW39),"",BW39-BW38) -> 8 | BX40: =IF(ISBLANK(BX39),"",BX39-BX38) -> 103 | BY40: =IF(ISBLANK(BY39),"",BY39-BY38) -> 74 | BZ40: =IF(ISBLANK(BZ39),"",BZ39-BZ38) -> 41 | ... DE40: =IF(ISBLANK(DE39),"",DE39-DE38)
G41: Cumulative Difference | BS41: =IFERROR(IF(ISBLANK(BS40),"",BS40+BR41),"") -> 56 | BT41: =IFERROR(IF(ISBLANK(BT40),"",BT40+BS41),"") -> 70 | BU41: =IFERROR(IF(ISBLANK(BU40),"",BU40+BT41),"") -> 54 | BV41: =IFERROR(IF(ISBLANK(BV40),"",BV40+BU41),"") -> 122 | BW41: =IFERROR(IF(ISBLANK(BW40),"",BW40+BV41),"") -> 130 | BX41: =IFERROR(IF(ISBLANK(BX40),"",BX40+BW41),"") -> 233 | BY41: =IFERROR(IF(ISBLANK(BY40),"",BY40+BX41),"") -> 307 | BZ41: =IFERROR(IF(ISBLANK(BZ40),"",BZ40+BY41),"") -> 348 | ... DE41: =IFERROR(IF(ISBLANK(DE40),"",DE40+DD41),"")
G42: 7 day rolling average | BW42: =IFERROR(AVERAGE(BQ39:BW39),"") -> 48 | CD42: =IFERROR(AVERAGE(BX39:CD39),"") -> 40.571429 | CK42: =IFERROR(AVERAGE(CE39:CK39),"") -> 17.714286 | CR42: =IFERROR(AVERAGE(CL39:CR39),"") -> 38.333333 | CY42: =IFERROR(AVERAGE(CS39:CY39),"") | DF42: =IFERROR(AVERAGE(CZ39:DF39),"")
A44: =IF((C44+200)>=B44,TRUE,FALSE) -> FALSE | B44: 1934 | C44: =SUM(Y44:XFD44) -> 13 | G44: Predicted | BU44: 1 | BX44: 1 | CA44: 1 | CD44: 1 | CG44: 1 | CJ44: 1 | CM44: 1 | CP44: 1 | CS44: 1 | CV44: 1 | CY44: 1 | DB44: 1 | DE44: 1
F45: Building | G45: Actual | BT45: 1 | BU45: 0 | BV45: 0
G46: Difference | BS46: =IF(ISBLANK(BS45),"",BS45-BS44) | BT46: =IF(ISBLANK(BT45),"",BT45-BT44) -> 1 | BU46: =IF(ISBLANK(BU45),"",BU45-BU44) -> -1 | BV46: =IF(ISBLANK(BV45),"",BV45-BV44) -> 0 | BW46: =IF(ISBLANK(BW45),"",BW45-BW44) | BX46: =IF(ISBLANK(BX45),"",BX45-BX44) | BY46: =IF(ISBLANK(BY45),"",BY45-BY44) | BZ46: =IF(ISBLANK(BZ45),"",BZ45-BZ44) | ... DE46: =IF(ISBLANK(DE45),"",DE45-DE44)
G47: Cumulative Difference | BS47: =IFERROR(IF(ISBLANK(BS46),"",BS46+#REF!),"") | BT47: =IFERROR(IF(ISBLANK(BT46),"",BT46+BS47),"") | BU47: =IFERROR(IF(ISBLANK(BU46),"",BU46+BT47),"") | BV47: =IFERROR(IF(ISBLANK(BV46),"",BV46+BU47),"") | BW47: =IFERROR(IF(ISBLANK(BW46),"",BW46+BV47),"") | BX47: =IFERROR(IF(ISBLANK(BX46),"",BX46+BW47),"") | BY47: =IFERROR(IF(ISBLANK(BY46),"",BY46+BX47),"") | BZ47: =IFERROR(IF(ISBLANK(BZ46),"",BZ46+BY47),"") | CA47: =IFERROR(IF(ISBLANK(CA46),"",CA46+BZ47),"") | ... DE47: =IFERROR(IF(ISBLANK(DE46),"",DE46+DD47),"")
E49: HYD1 | G49: Drilling Phase | CD49: Bores | CE49: Bores | CF49: Bores | CG49: Bores | CH49: Bores | CI49: Bores | CJ49: Bores | CK49: Bores | CL49: Bores | CM49: Bores | CN49: Bores | CO49: Bores | CP49: Bores | CQ49: Bores | CR49: Bores | CS49: Bores | CT49: Bores | CU49: Bores | CV49: Bores | CW49: Bores | CX49: Bores | CY49: Bores | CZ49: Bores | DA49: Bores | DB49: Bores | DC49: Bores | DD49: Bores | DE49: Bores | DF49: Bores | DG49: Bores | DH49: Bores | DI49: Bores | DJ49: Bores | DK49: Bores | DL49: Bores | DM49: Bores | DN49: Bores | DO49: Bores | DP49: Bores
E50: Rig 16 | F50: Drilling | G50: Predicted | CD50: 22 | CE50: 22 | CF50: 22 | CG50: 22 | CH50: 22 | CI50: 22 | CJ50: 22 | CK50: 22 | CL50: 22 | CM50: 22 | CN50: 22 | CO50: 22 | CP50: 22 | CQ50: 22 | CR50: 22 | CS50: 22 | CT50: 22 | CU50: 22 | CV50: 22 | CW50: 22 | CX50: 22 | CY50: 22 | CZ50: 22 | DA50: 22 | DB50: 22 | DC50: 22 | DD50: 22 | DE50: 22 | DF50: 22 | DG50: 22 | DH50: 22 | DI50: 22 | DJ50: 22 | DK50: 22 | DL50: 22 | DM50: 22 | DN50: 22 | DO50: 22 | DP50: 22
G51: Actual | CD51: 0 | CE51: 40 | CF51: 0 | CG51: 19 | CH51: 17 | CI51: 0 | CJ51: 0 | CK51: 0 | CL51: 0 | CM51: 0 | CN51: 0 | CO51: 0 | CP51: 0 | CQ51: 8
G52: Difference | CD52: =IF(ISBLANK(CD51),"",CD51-CD50) -> -22 | CE52: =IF(ISBLANK(CE51),"",CE51-CE50) -> 18 | CF52: =IF(ISBLANK(CF51),"",CF51-CF50) -> -22 | CG52: =IF(ISBLANK(CG51),"",CG51-CG50) -> -3 | CH52: =IF(ISBLANK(CH51),"",CH51-CH50) -> -5 | CI52: =IF(ISBLANK(CI51),"",CI51-CI50) -> -22 | CJ52: =IF(ISBLANK(CJ51),"",CJ51-CJ50) -> -22 | CK52: =IF(ISBLANK(CK51),"",CK51-CK50) -> -22 | ... DP52: =IF(ISBLANK(DP51),"",DP51-DP50)
F53: Building | G53: Cumulative Difference | CD53: =IFERROR(IF(ISBLANK(CD52),"",CD52+BX53),"") -> -22 | CE53: =IFERROR(IF(ISBLANK(CE52),"",CE52+CD53),"") -> -4 | CF53: =IFERROR(IF(ISBLANK(CF52),"",CF52+CE53),"") -> -26 | CG53: =IFERROR(IF(ISBLANK(CG52),"",CG52+CF53),"") -> -29 | CH53: =IFERROR(IF(ISBLANK(CH52),"",CH52+CG53),"") -> -34 | CI53: =IFERROR(IF(ISBLANK(CI52),"",CI52+CH53),"") -> -56 | CJ53: =IFERROR(IF(ISBLANK(CJ52),"",CJ52+CI53),"") -> -78 | CK53: =IFERROR(IF(ISBLANK(CK52),"",CK52+CJ53),"") -> -100 | CL53: =IFERROR(IF(ISBLANK(CL52),"",CL52+CK53),"") -> -122 | ... DP53: =IFERROR(IF(ISBLANK(DP52),"",DP52+DO53),"")
A55: =IF((C55+200)>=B55,TRUE,FALSE) -> FALSE | B55: 1934 | C55: =SUM(Y55:XFD55) -> 12 | G55: Predicted | CD55: 1 | CG55: 1 | CJ55: 1 | CM55: 1 | CP55: 1 | CS55: 1 | CV55: 1 | CY55: 1 | DB55: 1 | DE55: 1 | DH55: 1 | DK55: 1
G56: Actual
G57: Difference | BY57: =IF(ISBLANK(BY56),"",BY56-BY55) | CD57: =IF(ISBLANK(CD56),"",CD56-CD55) | CE57: =IF(ISBLANK(CE56),"",CE56-CE55) | CF57: =IF(ISBLANK(CF56),"",CF56-CF55) | CG57: =IF(ISBLANK(CG56),"",CG56-CG55) | CH57: =IF(ISBLANK(CH56),"",CH56-CH55) | CI57: =IF(ISBLANK(CI56),"",CI56-CI55) | CJ57: =IF(ISBLANK(CJ56),"",CJ56-CJ55) | CK57: =IF(ISBLANK(CK56),"",CK56-CK55) | ... DK57: =IF(ISBLANK(DK56),"",DK56-DK55)
G58: Cumulative Difference | BY58: =IFERROR(IF(ISBLANK(BY57),"",BY57+BX58),"") | CD58: =IFERROR(IF(ISBLANK(CD57),"",CD57+CC58),"") | CE58: =IFERROR(IF(ISBLANK(CE57),"",CE57+CD58),"") | CF58: =IFERROR(IF(ISBLANK(CF57),"",CF57+CE58),"") | CG58: =IFERROR(IF(ISBLANK(CG57),"",CG57+CF58),"") | CH58: =IFERROR(IF(ISBLANK(CH57),"",CH57+CG58),"") | CI58: =IFERROR(IF(ISBLANK(CI57),"",CI57+CH58),"") | CJ58: =IFERROR(IF(ISBLANK(CJ57),"",CJ57+CI58),"") | CK58: =IFERROR(IF(ISBLANK(CK57),"",CK57+CJ58),"") | ... DK58: =IFERROR(IF(ISBLANK(DK57),"",DK57+DJ58),"")
A59: Enabling Earthwork's Task | BO59: Task 4.2 - Complete Pad Prep
A60: =IF((C60+2.5)>=B60,TRUE,FALSE) -> #VALUE! | B60: 7 | C60: =SUM(Y60:XFD60) -> #VALUE! | E60: Earthworks | AN60: #VALUE! | BO60: 8.5
A61: Sample Dispatch | AY61: Pick up | BF61: Pick up | BM61: Pick up | BT61: Pick up | CA61: Pick up | CH61: Pick up | CO61: Pick up | CV61: Pick up | DC61: Pick up | DJ61: Pick up | DQ61: Pick up | DX61: Pick up | EE61: Pick up | EL61: Pick up
E62: Predicted | G62: Weight | AV62: =SUM((AV6*15.3),(AV14*8.6),(AV22*2.75),(AV30*2.75)) -> 0 | AW62: =SUM((AW6*15.3),(AW14*8.6),(AW22*2.75),(AW30*2.75)) -> 382.5 | AX62: =SUM((AX6*15.3),(AX14*8.6),(AX22*2.75),(AX30*2.75)) -> 382.5 | AY62: =SUM((AY6*15.3),(AY14*8.6),(AY22*2.75),(AY30*2.75)) -> 382.5 | AZ62: =SUM((AZ6*15.3),(AZ14*8.6),(AZ22*2.75),(AZ30*2.75)) -> 382.5 | BA62: =SUM((BA6*15.3),(BA14*8.6),(BA22*2.75),(BA30*2.75)) -> 382.5 | BB62: =SUM((BB6*15.3),(BB14*8.6),(BB22*2.75),(BB30*2.75)) -> 382.5 | BC62: =SUM((BC6*15.3),(BC14*8.6),(BC22*2.75),(BC30*2.75)) -> 795 | ... BQ62: =SUM((BQ6*15.3),(BQ14*8.6),(BQ22*2.75),(BQ30*2.75)) -> 1422.5 | BR62: =SUM((BR6*15.3),(CN14*8.6),(BR22*2.75),(BR30*2.75)) -> 1465.5 | BS62: =SUM((BS6*15.3),(CO14*8.6),(BS22*2.75),(BS30*2.75)) -> 1422.5 | BT62: =SUM((BT6*15.3),(CP14*8.6),(BT22*2.75),(BT30*2.75)) -> 1422.5 | BU62: =SUM((BU6*15.3),(CQ14*8.6),(BU22*2.75),(BU30*2.75)) -> 1422.5 | BV62: =SUM((BV6*15.3),(CS14*8.6),(BV22*2.75),(BV30*2.75)) -> 1422.5 | BW62: =SUM((BW6*15.3),(CT14*8.6),(BW22*2.75),(BW30*2.75)) -> 1422.5 | BX62: =SUM((BX6*15.3),(CU14*8.6),(BX22*2.75),(BX30*2.75)) -> 1422.5 | BY62: =SUM((BY6*15.3),(CV14*8.6),(BY22*2.75),(BY30*2.75)) -> 1465.5 | BZ62: =SUM((BZ6*15.3),(CW14*8.6),(BZ22*2.75),(BZ30*2.75)) -> 1465.5 | CA62: =SUM((CA6*15.3),(CX14*8.6),(CA22*2.75),(CA30*2.75)) -> 1465.5 | CB62: =SUM((CB6*15.3),(CY14*8.6),(CB22*2.75),(CB30*2.75)) -> 1542 | CC62: =SUM((CC6*15.3),(CZ14*8.6),(CC22*2.75),(CC30*2.75)) -> 1542 | ... EW62: =SUM((EW6*15.3),(FT14*8.6),(EW22*2.75),(EW30*2.75)) -> 640.5
G63: Number of Pallets | AV63: =SUM(((AV6/4)/18),((AV14/3)/24),(AV22/350),(AV30/350)) -> 0 | AW63: =SUM(((AW6/4)/18),((AW14/3)/24),(AW22/350),(AW30/350)) -> 0.34722222 | AX63: =SUM(((AX6/4)/18),((AX14/3)/24),(AX22/350),(AX30/350)) -> 0.34722222 | AY63: =SUM(((AY6/4)/18),((AY14/3)/24),(AY22/350),(AY30/350)) -> 0.34722222 | AZ63: =SUM(((AZ6/4)/18),((AZ14/3)/24),(AZ22/350),(AZ30/350)) -> 0.34722222 | BA63: =SUM(((BA6/4)/18),((BA14/3)/24),(BA22/350),(BA30/350)) -> 0.34722222 | BB63: =SUM(((BB6/4)/18),((BB14/3)/24),(BB22/350),(BB30/350)) -> 0.34722222 | BC63: =SUM(((BC6/4)/18),((BC14/3)/24),(BC22/350),(BC30/350)) -> 0.77579365 | ... BQ63: =SUM(((BQ6/4)/18),((BQ14/3)/24),(BQ22/350),(BQ30/350)) -> 1.5515873 | BR63: =SUM(((BR6/4)/18),((CN14/3)/24),(BR22/350),(BR30/350)) -> 1.6210317 | BS63: =SUM(((BS6/4)/18),((CO14/3)/24),(BS22/350),(BS30/350)) -> 1.5515873 | BT63: =SUM(((BT6/4)/18),((CP14/3)/24),(BT22/350),(BT30/350)) -> 1.5515873 | BU63: =SUM(((BU6/4)/18),((CQ14/3)/24),(BU22/350),(BU30/350)) -> 1.5515873 | BV63: =SUM(((BV6/4)/18),((CS14/3)/24),(BV22/350),(BV30/350)) -> 1.5515873 | BW63: =SUM(((BW6/4)/18),((CT14/3)/24),(BW22/350),(BW30/350)) -> 1.5515873 | BX63: =SUM(((BX6/4)/18),((CU14/3)/24),(BX22/350),(BX30/350)) -> 1.5515873 | BY63: =SUM(((BY6/4)/18),((CV14/3)/24),(BY22/350),(BY30/350)) -> 1.6210317 | BZ63: =SUM(((BZ6/4)/18),((CW14/3)/24),(BZ22/350),(BZ30/350)) -> 1.6210317 | CA63: =SUM(((CA6/4)/18),((CX14/3)/24),(CA22/350),(CA30/350)) -> 1.6210317 | CB63: =SUM(((CB6/4)/18),((CY14/3)/24),(CB22/350),(CB30/350)) -> 1.6904762 | CC63: =SUM(((CC6/4)/18),((CZ14/3)/24),(CC22/350),(CC30/350)) -> 1.6904762 | ... EW63: =SUM(((EW6/4)/18),((FT14/3)/24),(EW22/350),(EW30/350)) -> 0.76388889
G64: Total Weight (t) | AY64: =SUM(AR62:AX62)/1000 -> 0.765 | BF64: =SUM(AY62:BE62)/1000 -> 3.915 | BM64: =SUM(BF62:BL62)/1000 -> 7.215 | BT64: =SUM(BM62:BS62)/1000 -> 9.1405 | CA64: =SUM(BT62:BZ62)/1000 -> 10.0435 | CH64: =SUM(CA62:CG62)/1000 -> 10.7175 | CO64: =SUM(CH62:CN62)/1000 -> 10.488 | CV64: =SUM(CO62:CU62)/1000 -> 10.488 | DC64: =SUM(CV62:DB62)/1000 -> 10.641 | DJ64: =SUM(DC62:DI62)/1000 -> 10.641 | DQ64: =SUM(DJ62:DP62)/1000 -> 10.794 | DX64: =SUM(DQ62:DW62)/1000 -> 10.335 | EE64: =SUM(DX62:ED62)/1000 -> 9.9525
G65: Total Pallets | AY65: =SUM(AR63:AX63) -> 0.69444444 | BF65: =SUM(AY63:BE63) -> 3.7162698 | BM65: =SUM(BF63:BL63) -> 7.1448413 | BT65: =SUM(BM63:BS63) -> 9.5416667 | CA65: =SUM(BT63:BZ63) -> 11 | CH65: =SUM(CA63:CG63) -> 11.763889 | CO65: =SUM(CH63:CN63) -> 11.555556 | CV65: =SUM(CO63:CU63) -> 11.555556 | DC65: =SUM(CV63:DB63) -> 11.694444 | DJ65: =SUM(DC63:DI63) -> 11.694444 | DQ65: =SUM(DJ63:DP63) -> 11.833333 | DX65: =SUM(DQ63:DW63) -> 11.416667 | EE65: =SUM(DX63:ED63) -> 11.069444
E66: Actual | G66: Weight | AV66: =SUM((AV7*15.3),(AV15*8.6),(AV23*2.75),(AV31*2.75)) -> 0 | AW66: =SUM((AW7*15.3),(AW15*8.6),(AW23*2.75),(AW31*2.75)) -> 787.95 | AX66: =SUM((AX7*15.3),(AX15*8.6),(AX23*2.75),(AX31*2.75)) -> 856.8 | AY66: =SUM((AY7*15.3),(AY15*8.6),(AY23*2.75),(AY31*2.75)) -> 803.25 | AZ66: =SUM((AZ7*15.3),(AZ15*8.6),(AZ23*2.75),(AZ31*2.75)) -> 327.42 | BA66: =SUM((BA7*15.3),(BA15*8.6),(BA23*2.75),(BA31*2.75)) -> 896.58 | BB66: =SUM((BB7*15.3),(BB15*8.6),(BB23*2.75),(BB31*2.75)) -> 459 | BC66: =SUM((BC7*15.3),(BC15*8.6),(BC23*2.75),(BC31*2.75)) -> 625.28 | ... CL66: =SUM((CL7*15.3),(CL15*8.6),(CL23*2.75),(CL31*2.75)) -> 877.38 | CM66: =SUM((CM7*15.3),(CN15*8.6),(CM23*2.75),(CM31*2.75)) -> 642.94 | CN66: =SUM((CN7*15.3),(#REF!*8.6),(CN23*2.75),(CN31*2.75)) -> #REF! | CO66: =SUM((CO7*15.3),(CM15*8.6),(CO23*2.75),(CO31*2.75)) -> 1535.42 | CP66: =SUM((CP7*15.3),(CP15*8.6),(CP23*2.75),(CP31*2.75)) -> 1275.4 | CQ66: =SUM((CQ7*15.3),(CQ15*8.6),(CQ23*2.75),(CQ31*2.75)) -> 1540.41 | CR66: =SUM((CR7*15.3),(CR15*8.6),(CR23*2.75),(CR31*2.75)) -> 1179.5 | CS66: =SUM((CS7*15.3),(CS15*8.6),(CS23*2.75),(CS31*2.75)) -> 1193.59 | CT66: =SUM((CT7*15.3),(CT15*8.6),(CT23*2.75),(CT31*2.75)) -> 1822.51 | CU66: =SUM((CU7*15.3),(CU15*8.6),(CU23*2.75),(CU31*2.75)) -> 674.13 | CV66: =SUM((CV7*15.3),(CV15*8.6),(CV23*2.75),(CV31*2.75)) -> 1810.74 | CW66: =SUM((CW7*15.3),(CW15*8.6),(CW23*2.75),(CW31*2.75)) -> 1903.07 | ... EW66: =SUM((EW7*15.3),(EW15*8.6),(EW23*2.75),(EW31*2.75)) -> 740.52
G67: Number of Pallets | AV67: =SUM(((AV7/4)/18),((AV15/3)/24),(AV23/350),(AV31/350)) -> 0 | AW67: =SUM(((AW7/4)/18),((AW15/3)/24),(AW23/350),(AW31/350)) -> 0.71527778 | AX67: =SUM(((AX7/4)/18),((AX15/3)/24),(AX23/350),(AX31/350)) -> 0.77777778 | AY67: =SUM(((AY7/4)/18),((AY15/3)/24),(AY23/350),(AY31/350)) -> 0.72916667 | AZ67: =SUM(((AZ7/4)/18),((AZ15/3)/24),(AZ23/350),(AZ31/350)) -> 0.29722222 | BA67: =SUM(((BA7/4)/18),((BA15/3)/24),(BA23/350),(BA31/350)) -> 0.81388889 | BB67: =SUM(((BB7/4)/18),((BB15/3)/24),(BB23/350),(BB31/350)) -> 0.41666667 | BC67: =SUM(((BC7/4)/18),((BC15/3)/24),(BC23/350),(BC31/350)) -> 0.58420635 | ... CL67: =SUM(((CL7/4)/18),((CL15/3)/24),(CL23/350),(CL31/350)) -> 1.0219048 | CM67: =SUM(((CM7/4)/18),((CN15/3)/24),(CM23/350),(CM31/350)) -> 0.72309524 | CN67: =SUM(((CN7/4)/18),((#REF!/3)/24),(CN23/350),(CN31/350)) -> #REF! | CO67: =SUM(((CO7/4)/18),((CM15/3)/24),(CO23/350),(CO31/350)) -> 1.6169841 | CP67: =SUM(((CP7/4)/18),((CP15/3)/24),(CP23/350),(CP31/350)) -> 1.5021032 | CQ67: =SUM(((CQ7/4)/18),((CQ15/3)/24),(CQ23/350),(CQ31/350)) -> 1.7978968 | CR67: =SUM(((CR7/4)/18),((CR15/3)/24),(CR23/350),(CR31/350)) -> 1.275119 | CS67: =SUM(((CS7/4)/18),((CS15/3)/24),(CS23/350),(CS31/350)) -> 1.3795635 | CT67: =SUM(((CT7/4)/18),((CT15/3)/24),(CT23/350),(CT31/350)) -> 1.9340873 | CU67: =SUM(((CU7/4)/18),((CU15/3)/24),(CU23/350),(CU31/350)) -> 0.69579365 | CV67: =SUM(((CV7/4)/18),((CV15/3)/24),(CV23/350),(CV31/350)) -> 1.8651587 | CW67: =SUM(((CW7/4)/18),((CW15/3)/24),(CW23/350),(CW31/350)) -> 2.1955952 | ... EW67: =SUM(((EW7/4)/18),((EW15/3)/24),(EW23/350),(EW31/350)) -> 0.67222222
G68: Total Weight (t) | AY68: =SUM(AR66:AX66)/1000 -> 1.64475 | BF68: =SUM(AY66:BE66)/1000 -> 5.17446
G69: Total Pallets | AY69: =SUM(AR67:AX67) -> 1.4930556 | BF69: =SUM(AY67:BE67) -> 4.807619
E70: Logged and Processed | G70: Metres RC
A71: Pad build rate | B71: Task 4.1 | C71: =37/15 -> 2.4666667 | G71: Metres PQ3
B72: Task 4.2 | C72: =300/35 -> 8.5714286 | G72: Metres HQ3
G73: Weight
G74: Number of Pallets
G75: Total Weight (t)
G76: Total Pallets
K78: Predicted | L78: Planned | AN78: * | AO78: Geotech core will need to have a special packaging protocol
I79: DD | J79: Met | K79: =SUMIF($5:$5,J79,$6:$6)+SUMIF($13:$13,J79,$14:$14) -> 1425 | L79: 2045
I80: DD | J80: GeoT * | K80: =SUMIF($5:$5,J80,$6:$6)+SUMIF($13:$13,J80,$14:$14) -> 300 | L80: 1040
I81: DD | J81: Inf | K81: =SUMIF($5:$5,J81,$6:$6)+SUMIF($13:$13,J81,$14:$14) -> 900 | L81: 1260
I82: DD | J82: ExtA | K82: =SUMIF($5:$5,J82,$6:$6)+SUMIF($13:$13,J82,$14:$14) -> 540 | L82: 540
I83: DD | J83: ExtG | K83: =SUMIF($5:$5,J83,$6:$6)+SUMIF($13:$13,J83,$14:$14) -> 540 | L83: 581
I84: RC | J84: Bores | K84: =SUMIF($37:$37,J84,$38:$38)+SUMIF($49:$49,J84,$50:$50) -> 1716 | L84: 1934 | R84: Target | S84: Meters
I85: RC | J85: Inf | K85: =SUMIF($21:$21,J85,$22:$22)+SUMIF($29:$29,J85,$30:$30) -> 17850 | L85: 17945 | R85: Met Drilling (DFS) | S85: 2045
I86: RC | J86: ExtA | K86: =SUMIF($21:$21,J86,$22:$22)+SUMIF($29:$29,J86,$30:$30) -> 3750 | L86: 3645
I87: RC | J87: ExtG | K87: =SUMIF($21:$21,J87,$22:$22)+SUMIF($29:$29,J87,$30:$30) -> 4950 | L87: 4495.1
I88: RC | J88: Dingo | K88: =SUMIF($21:$21,J88,$22:$22)+SUMIF($29:$29,J88,$30:$30) -> 750 | L88: 630
I89: RC | J89: South | K89: =SUMIF($21:$21,J89,$22:$22)+SUMIF($29:$29,J89,$30:$30) -> 800 | L89: 900
R90: Infill Drilling | S90: 19205
R91: Dingo Vein 1st Pass | S91: 630
R92: Southern Extension Exploration | S92: 900
DW100: 218
DW101: 214
DW102: 206
BS103: 0 | DW103: 102
BS104: 40 | DW104: 176
BS105: 0 | DW105: 224
BS106: 19 | DW106: 160
BS107: 17
BS108: 0
BS109: 0
BS110: 0
BS111: 0
BS112: 0
...

Sheet Pivot_Rig38
A9: RIG38
A10: Row Labels | B10: Sum of Completed Holes | C10: Sum of Total Length PQ | D10: Sum of Total Length HQ | E10: Sum of Charged Drilling Cost | F10: Sum of Active Hours total Cost | G10: Sum of Standby & Inactive Total Cost | H10: Sum of Tool Hire Cost | I10: Sum of Total Activity Hours Cost | J10: Sum of ***Insert Total Consumable Costs*** | K10: Sum of Total Costs
C11: 0 | D11: 0 | E11: 0 | F11: 0 | G11: 3780 | H11: 0 | I11: 3780 | K11: 3780
A12: DDRD | B12: 1 | C12: 0 | D12: 84.6 | E12: 13623 | F12: 6900 | G12: 45.625 | H12: 1500 | I12: 12750 | J12: 7504.06 | K12: 35767.06
A13: GT | B13: 7 | C13: 10.1 | D13: 333.9 | E13: 67505 | F13: 29440 | G13: 12871 | H13: 7425 | I13: 44650 | J13: 10934.64 | K13: 130514.64
A14: MET | B14: 9 | C14: 749 | D14: 2.3 | E14: 143015 | F14: 54280 | G14: 7471.5 | H14: 12200 | I14: 63910 | J14: 37761.28 | K14: 256886.28
A15: (blank) | C15: 0 | D15: 0 | E15: 0 | F15: 0 | G15: 0 | H15: 0 | I15: 0 | K15: 0
A16: Grand Total | B16: 17 | C16: 759.1 | D16: 420.8 | E16: 224143 | F16: 90620 | G16: 24168.125 | H16: 21125 | I16: 125090 | J16: 56199.98 | K16: 426947.98
A17: Row Labels | B17: Sum of Planned Holes | C17: Sum of Planned Metres
A18: A-Vein Resource Extension | B18: 47 | C18: 4185
A19: RD | B19: 47 | C19: 4185
A20: DD | B20: 5 | C20: 450
A21: RC | B21: 42 | C21: 3735
A22: DFS Met Sample collection (24 no. Holes, 2,045m) | B22: 24 | C22: 2045
A23: MET | B23: 24 | C23: 2045
A24: DD | B24: 24 | C24: 2045
A25: Dingo Vein Exploration | B25: 7 | C25: 630
A26: EXP | B26: 7 | C26: 630
A27: RC | B27: 7 | C27: 630
A28: Geotechnical drilling (12 no. HQ Holes, 1040m) | B28: 12 | C28: 1040
A29: GT | B29: 12 | C29: 1040
... A41: RC | B41: 10 | C41: 900
A42: (blank)
A43: Grand Total | B43: 307 | C43: 33601

Sheet DDH1 RIG 38_Data
A1: RIG 38 | G1: Rate | H1: 130 | I1: Hole 1 | K1: 175 | N1: 135 | O1: Hole 2 | Q1: 175 | T1: 135 | Z1: 175 | AA1: 155 | AB1: 420 | AE1: 460 | AF1: 460 | AH1: 360 | AI1: 360
E2: Hole 1 | F2: Hole 2 | I2: PQ3 | L2: HQ3 | O2: PQ3 | R2: HQ3 | Y2: Slow Pen rate Normalised | AK2: 0 | AL2: 0
A3: Hole Type | B3: Completion | C3: Date | D3: Shift | E3: Hole ID | F3: Hole ID2 | G3: Personel (incl driller) | H3: Accom Cost | I3: Depth From | J3: Depth To | K3: Length | L3: Depth From3 | M3: Depth To4 | N3: Length5 | O3: Depth From6 | P3: Depth To7 | Q3: Length8 | R3: Depth From9 | S3: Depth To10 | T3: Length11 | U3: Total Length PQ | V3: Total Length HQ | W3: Total Length | X3: Drilling Cost | Y3: Charged Drilling Cost | Z3: PQ Ori Tool | AA3: HQ Ori Tool | AB3: Gyro Tool | AC3: Tool ID | AD3: Tool Hire Cost | AE3: Drill Time | AF3: Active hours (Other than drilling) | AG3: Active Hours total Cost | AH3: Inactive Hours (Other than client standby) | AI3: Standby Total Hours | AJ3: Standby & Inactive Total Cost | AK3: Uncharged Hours | AL3: Maintenance | AM3: Total Daily Hours | AN3: Total Activity Hours Cost | AO3: ***Insert Total Consumable Costs*** | AP3: Total Consumables Cost (-accom) | AQ3: Total Costs | AR3: Plod Cost (Comparison) | AS3: Cummulative Cost | AT3: Month | AU3: Day | AV3: Shift Shorthand
A4: =IFERROR(IF(FIND("MET",E4),"MET",IF(FIND("GT",E4),"GT",)),"") | C4: =45843.21 -> 45843.21 | D4: DS 5am | H4: =IF(ISBLANK(G4),"",G4*$H$1) | K4: =IF(ISBLANK(I4),"",J4-I4) | N4: =IF(ISBLANK(L4),,M4-L4) -> 0 | Q4: =IF(ISBLANK(O4),,P4-O4) -> 0 | T4: =IF(ISBLANK(R4),,S4-R4) -> 0 | U4: =SUM(K4,Q4) -> 0 | V4: =SUM(N4,T4) -> 0 | W4: =IFERROR(K4+N4+Q4+T4,"") | X4: =IFERROR((K4*$K$1)+(N4*$N$1)+(Q4*$Q$1)+(T4*$T$1),"") | Y4: =IF(E4<>"",IF(X4<(AE4*$AE$1),(AE4*$AE$1),X4),"") | AA4: 1 | AB4: 1 | AE4: 0 | AF4: 0 | AG4: =Table3[[#This Row],[Active hours (Other than drilling)]]*$AF$1 -> 0 | AH4: 3.5 | AJ4: {=SUM(Table3[[#This Row],[Inactive Hours (Other than client standby)]:[Standby Total Hours]]*$AI$1)} -> 1260 | AK4: 8.5 | AM4: =IF(ISBLANK(AE4),"",SUM(AE4:AF4,AH4:AI4,AK4:AL4)) -> 12 | AN4: =(AF4*$AF$1)+(AH4*$AH$1)+(AI4*$AI$1) -> 1260 | AQ4: =SUM(Y4,AN4,AP4,H4)+AD4 -> 1260 | AS4: =SUM($AQ4:AQ$6) -> 3780 | AT4: =_xlfn.TEXTJOIN(,TRUE,"0",MONTH(C4)) -> 07 | AU4: =DAY(C4) -> 5 | AV4: =LEFT(D4,1) -> D
A5: =IFERROR(IF(FIND("MET",E5),"MET",IF(FIND("GT",E5),"GT",)),"") | C5: =45843 -> 45843 | D5: NS 5pm | H5: =IF(ISBLANK(G5),"",G5*$H$1) | K5: =IF(ISBLANK(I5),"",J5-I5) | N5: =IF(ISBLANK(L5),,M5-L5) -> 0 | Q5: =IF(ISBLANK(O5),,P5-O5) -> 0 | T5: =IF(ISBLANK(R5),,S5-R5) -> 0 | U5: =SUM(K5,Q5) -> 0 | V5: =SUM(N5,T5) -> 0 | W5: =IFERROR(K5+N5+Q5+T5,"") | X5: =IFERROR((K5*$K$1)+(N5*$N$1)+(Q5*$Q$1)+(T5*$T$1),"") | Y5: =IF(E5<>"",IF(X5<(AE5*$AE$1),(AE5*$AE$1),X5),"") | AE5: 0 | AF5: 0 | AG5: =Table3[[#This Row],[Active hours (Other than drilling)]]*$AF$1 -> 0 | AH5: 3.5 | AJ5: {=SUM(Table3[[#This Row],[Inactive Hours (Other than client standby)]:[Standby Total Hours]]*$AI$1)} -> 1260 | AK5: 7.5 | AM5: =IF(ISBLANK(AE5),"",SUM(AE5:AF5,AH5:AI5,AK5:AL5)) -> 11 | AN5: =(AF5*$AF$1)+(AH5*$AH$1)+(AI5*$AI$1) -> 1260 | AQ5: =SUM(Y5,AN5,AP5,H5)+AD5 -> 1260 | AS5: =SUM($AQ5:AQ$6) -> 2520 | AT5: =_xlfn.TEXTJOIN(,TRUE,"0",MONTH(C5)) -> 07 | AU5: =DAY(C5) -> 5 | AV5: =LEFT(D5,1) -> N
A6: =IFERROR(IF(FIND("MET",E6),"MET",IF(FIND("GT",E6),"GT",)),"") | C6: =45843.21+1 -> 45844.21 | D6: DS 5am | H6: =IF(ISBLANK(G6),"",G6*$H$1) | K6: =IF(ISBLANK(I6),"",J6-I6) | N6: =IF(ISBLANK(L6),,M6-L6) -> 0 | Q6: =IF(ISBLANK(O6),,P6-O6) -> 0 | T6: =IF(ISBLANK(R6),,S6-R6) -> 0 | U6: =SUM(K6,Q6) -> 0 | V6: =SUM(N6,T6) -> 0 | W6: =IFERROR(K6+N6+Q6+T6,"") | X6: =IFERROR((K6*$K$1)+(N6*$N$1)+(Q6*$Q$1)+(T6*$T$1),"") | Y6: =IF(E6<>"",IF(X6<(AE6*$AE$1),(AE6*$AE$1),X6),"") | AA6: 1 | AB6: 1 | AE6: 0 | AF6: 0 | AG6: =Table3[[#This Row],[Active hours (Other than drilling)]]*$AF$1 -> 0 | AH6: 3.5 | AJ6: {=SUM(Table3[[#This Row],[Inactive Hours (Other than client standby)]:[Standby Total Hours]]*$AI$1)} -> 1260 | AK6: 8.5 | AM6: =IF(ISBLANK(AE6),"",SUM(AE6:AF6,AH6:AI6,AK6:AL6)) -> 12 | AN6: =(AF6*$AF$1)+(AH6*$AH$1)+(AI6*$AI$1) -> 1260 | AQ6: =SUM(Y6,AN6,AP6,H6)+AD6 -> 1260 | AR6: 1260 | AS6: =SUM($AQ$6:AQ6) -> 1260 | AT6: =_xlfn.TEXTJOIN(,TRUE,"0",MONTH(C6)) -> 07 | AU6: =DAY(C6) -> 6 | AV6: =LEFT(D6,1) -> D
A7: =IFERROR(IF(FIND("MET",E7),"MET",IF(FIND("GT",E7),"GT",)),"") | C7: =45843.71+1 -> 45844.71 | D7: NS 5pm | H7: =IF(ISBLANK(G7),"",G7*$H$1) | K7: =IF(ISBLANK(I7),"",J7-I7) | N7: =IF(ISBLANK(L7),,M7-L7) -> 0 | Q7: =IF(ISBLANK(O7),,P7-O7) -> 0 | T7: =IF(ISBLANK(R7),,S7-R7) -> 0 | U7: =SUM(K7,Q7) -> 0 | V7: =SUM(N7,T7) -> 0 | W7: =IFERROR(K7+N7+Q7+T7,"") | X7: =IFERROR((K7*$K$1)+(N7*$N$1)+(Q7*$Q$1)+(T7*$T$1),"") | Y7: =IF(E7<>"",IF(X7<(AE7*$AE$1),(AE7*$AE$1),X7),"") | AG7: =Table3[[#This Row],[Active hours (Other than drilling)]]*$AF$1 -> 0 | AJ7: {=SUM(Table3[[#This Row],[Inactive Hours (Other than client standby)]:[Standby Total Hours]]*$AI$1)} -> 0 | AM7: =IF(ISBLANK(AE7),"",SUM(AE7:AF7,AH7:AI7,AK7:AL7)) | AN7: =(AF7*$AF$1)+(AH7*$AH$1)+(AI7*$AI$1) -> 0 | AQ7: =SUM(Y7,AN7,AP7,H7)+AD7 -> 0 | AR7: 0 | AS7: =SUM($AQ$6:AQ7) -> 1260 | AT7: =_xlfn.TEXTJOIN(,TRUE,"0",MONTH(C7)) -> 07 | AU7: =DAY(C7) -> 6 | AV7: =LEFT(D7,1) -> N
A8: MET | C8: =C6+1 -> 45845.21 | D8: DS 5am | E8: SF25_DMET023 | G8: 6 | H8: =IF(ISBLANK(G8),"",G8*$H$1) -> 780 | I8: 0 | J8: 0 | K8: =IF(ISBLANK(I8),"",J8-I8) -> 0 | N8: =IF(ISBLANK(L8),,M8-L8) -> 0 | Q8: =IF(ISBLANK(O8),,P8-O8) -> 0 | T8: =IF(ISBLANK(R8),,S8-R8) -> 0 | U8: =SUM(K8,Q8) -> 0 | V8: =SUM(N8,T8) -> 0 | W8: =IFERROR(K8+N8+Q8+T8,"") -> 0 | X8: =IFERROR((K8*$K$1)+(N8*$N$1)+(Q8*$Q$1)+(T8*$T$1),"") -> 0 | Y8: =IF(E8<>"",IF(X8<(AE8*$AE$1),(AE8*$AE$1),X8),"") -> 0 | AA8: 1 | AB8: 1 | AC8: 13170 | AD8: =SUMPRODUCT(Z8:AB8,$Z$1:$AB$1) -> 575 | AE8: 0 | AF8: 8.25 | AG8: =Table3[[#This Row],[Active hours (Other than drilling)]]*$AF$1 -> 3795 | AH8: 2 | AJ8: {=SUM(Table3[[#This Row],[Inactive Hours (Other than client standby)]:[Standby Total Hours]]*$AI$1)} -> 720 | AK8: 1.75 | AM8: =IF(ISBLANK(AE8),"",SUM(AE8:AF8,AH8:AI8,AK8:AL8)) -> 12 | AN8: =(AF8*$AF$1)+(AH8*$AH$1)+(AI8*$AI$1) -> 4515 | AO8: 1541 | AP8: 761 | AQ8: =SUM(Y8,AN8,AP8,H8)+AD8 -> 6631 | AR8: 6631 | AS8: =SUM($AQ$6:AQ8) -> 7891 | AT8: =_xlfn.TEXTJOIN(,TRUE,"0",MONTH(C8)) -> 07 | AU8: =DAY(C8) -> 7 | AV8: =LEFT(D8,1) -> D
C9: =C7+1 -> 45845.71 | D9: NS 5pm | H9: =IF(ISBLANK(G9),"",G9*$H$1) | K9: =IF(ISBLANK(I9),"",J9-I9) | N9: =IF(ISBLANK(L9),,M9-L9) -> 0 | Q9: =IF(ISBLANK(O9),,P9-O9) -> 0 | T9: =IF(ISBLANK(R9),,S9-R9) -> 0 | U9: =SUM(K9,Q9) -> 0 | V9: =SUM(N9,T9) -> 0 | W9: =IFERROR(K9+N9+Q9+T9,"") | X9: =IFERROR((K9*$K$1)+(N9*$N$1)+(Q9*$Q$1)+(T9*$T$1),"") | Y9: =IF(E9<>"",IF(X9<(AE9*$AE$1),(AE9*$AE$1),X9),"") | AD9: =SUMPRODUCT(Z9:AB9,$Z$1:$AB$1) -> 0 | AG9: =Table3[[#This Row],[Active hours (Other than drilling)]]*$AF$1 -> 0 | AJ9: {=SUM(Table3[[#This Row],[Inactive Hours (Other than client standby)]:[Standby Total Hours]]*$AI$1)} -> 0 | AM9: =IF(ISBLANK(AE9),"",SUM(AE9:AF9,AH9:AI9,AK9:AL9)) | AN9: =(AF9*$AF$1)+(AH9*$AH$1)+(AI9*$AI$1) -> 0 | AQ9: =SUM(Y9,AN9,AP9,H9)+AD9 -> 0 | AR9: 0 | AS9: =SUM($AQ$6:AQ9) -> 7891 | AT9: =_xlfn.TEXTJOIN(,TRUE,"0",MONTH(C9)) -> 07 | AU9: =DAY(C9) -> 7 | AV9: =LEFT(D9,1) -> N
A10: MET | C10: =C8+1 -> 45846.21 | D10: DS 5am | E10: SF25_DMET023 | G10: 3 | H10: =IF(ISBLANK(G10),"",G10*$H$1) -> 390 | I10: 0 | J10: 11 | K10: =IF(ISBLANK(I10),"",J10-I10) -> 11 | N10: =IF(ISBLANK(L10),,M10-L10) -> 0 | Q10: =IF(ISBLANK(O10),,P10-O10) -> 0 | T10: =IF(ISBLANK(R10),,S10-R10) -> 0 | U10: =SUM(K10,Q10) -> 11 | V10: =SUM(N10,T10) -> 0 | W10: =IFERROR(K10+N10+Q10+T10,"") -> 11 | X10: =IFERROR((K10*$K$1)+(N10*$N$1)+(Q10*$Q$1)+(T10*$T$1),"") -> 1925 | Y10: =IF(E10<>"",IF(X10<(AE10*$AE$1),(AE10*$AE$1),X10),"") -> 1955 | AA10: 1 | AB10: 1 | AC10: 13170 | AD10: =SUMPRODUCT(Z10:AB10,$Z$1:$AB$1) -> 575 | AE10: 4.25 | AF10: 7 | AG10: =Table3[[#This Row],[Active hours (Other than drilling)]]*$AF$1 -> 3220 | AH10: 0.75 | AJ10: {=SUM(Table3[[#This Row],[Inactive Hours (Other than client standby)]:[Standby Total Hours]]*$AI$1)} -> 270 | AM10: =IF(ISBLANK(AE10),"",SUM(AE10:AF10,AH10:AI10,AK10:AL10)) -> 12 | AN10: =(AF10*$AF$1)+(AH10*$AH$1)+(AI10*$AI$1) -> 3490 | AO10: 1076.34 | AP10: =1076.34-390 -> 686.34 | AQ10: =SUM(Y10,AN10,AP10,H10)+AD10 -> 7096.34 | AR10: 7096.34 | AS10: =SUM($AQ$6:AQ10) -> 14987.34 | AT10: =_xlfn.TEXTJOIN(,TRUE,"0",MONTH(C10)) -> 07 | AU10: =DAY(C10) -> 8 | AV10: =LEFT(D10,1) -> D
A11: MET | C11: =C9+1 -> 45846.71 | D11: NS 5pm | E11: SF25_DMET023 | G11: 3 | H11: =IF(ISBLANK(G11),"",G11*$H$1) -> 390 | I11: 11 | J11: 26.6 | K11: =IF(ISBLANK(I11),"",J11-I11) -> 15.6 | N11: =IF(ISBLANK(L11),,M11-L11) -> 0 | Q11: =IF(ISBLANK(O11),,P11-O11) -> 0 | T11: =IF(ISBLANK(R11),,S11-R11) -> 0 | U11: =SUM(K11,Q11) -> 15.6 | V11: =SUM(N11,T11) -> 0 | W11: =IFERROR(K11+N11+Q11+T11,"") -> 15.6 | X11: =IFERROR((K11*$K$1)+(N11*$N$1)+(Q11*$Q$1)+(T11*$T$1),"") -> 2730 | Y11: =IF(E11<>"",IF(X11<(AE11*$AE$1),(AE11*$AE$1),X11),"") -> 3335 | AD11: =SUMPRODUCT(Z11:AB11,$Z$1:$AB$1) -> 0 | AE11: 7.25 | AF11: 1.5 | AG11: =Table3[[#This Row],[Active hours (Other than drilling)]]*$AF$1 -> 690 | AH11: 0.25 | AJ11: {=SUM(Table3[[#This Row],[Inactive Hours (Other than client standby)]:[Standby Total Hours]]*$AI$1)} -> 90 | AK11: 3 | AM11: =IF(ISBLANK(AE11),"",SUM(AE11:AF11,AH11:AI11,AK11:AL11)) -> 12 | AN11: =(AF11*$AF$1)+(AH11*$AH$1)+(AI11*$AI$1) -> 780 | AO11: 507.93 | AP11: 117.93 | AQ11: =SUM(Y11,AN11,AP11,H11)+AD11 -> 4622.93 | AR11: 4622.93 | AS11: =SUM($AQ$6:AQ11) -> 19610.27 | AT11: =_xlfn.TEXTJOIN(,TRUE,"0",MONTH(C11)) -> 07 | AU11: =DAY(C11) -> 8 | AV11: =LEFT(D11,1) -> N
A12: MET | C12: =C10+1 -> 45847.21 | D12: DS 5am | E12: SF25_DMET023 | G12: 3 | H12: =IF(ISBLANK(G12),"",G12*$H$1) -> 390 | I12: 26.6 | J12: 33.7 | K12: =IF(ISBLANK(I12),"",J12-I12) -> 7.1 | N12: =IF(ISBLANK(L12),,M12-L12) -> 0 | Q12: =IF(ISBLANK(O12),,P12-O12) -> 0 | T12: =IF(ISBLANK(R12),,S12-R12) -> 0 | U12: =SUM(K12,Q12) -> 7.1 | V12: =SUM(N12,T12) -> 0 | W12: =IFERROR(K12+N12+Q12+T12,"") -> 7.1 | X12: =IFERROR((K12*$K$1)+(N12*$N$1)+(Q12*$Q$1)+(T12*$T$1),"") -> 1242.5 | Y12: =IF(E12<>"",IF(X12<(AE12*$AE$1),(AE12*$AE$1),X12),"") -> 1380 | AA12: 1 | AB12: 1 | AC12: 13170 | AD12: =SUMPRODUCT(Z12:AB12,$Z$1:$AB$1) -> 575 | AE12: 3 | AF12: 0.25 | AG12: =Table3[[#This Row],[Active hours (Other than drilling)]]*$AF$1 -> 115 | AH12: 0.25 | AJ12: {=SUM(Table3[[#This Row],[Inactive Hours (Other than client standby)]:[Standby Total Hours]]*$AI$1)} -> 90 | AK12: 8.5 | AM12: =IF(ISBLANK(AE12),"",SUM(AE12:AF12,AH12:AI12,AK12:AL12)) -> 12 | AN12: =(AF12*$AF$1)+(AH12*$AH$1)+(AI12*$AI$1) -> 205 | AO12: 390 | AP12: 0 | AQ12: =SUM(Y12,AN12,AP12,H12)+AD12 -> 2550 | AR12: 2550 | AS12: =SUM($AQ$6:AQ12) -> 22160.27 | AT12: =_xlfn.TEXTJOIN(,TRUE,"0",MONTH(C12)) -> 07 | AU12: =DAY(C12) -> 9 | AV12: =LEFT(D12,1) -> D
A13: MET | C13: =C11+1 -> 45847.71 | D13: NS 5pm | E13: SF25_DMET023 | G13: 3 | H13: =IF(ISBLANK(G13),"",G13*$H$1) -> 390 | I13: 33.7 | J13: 63.7 | K13: =IF(ISBLANK(I13),"",J13-I13) -> 30 | N13: =IF(ISBLANK(L13),,M13-L13) -> 0 | Q13: =IF(ISBLANK(O13),,P13-O13) -> 0 | T13: =IF(ISBLANK(R13),,S13-R13) -> 0 | U13: =SUM(K13,Q13) -> 30 | V13: =SUM(N13,T13) -> 0 | W13: =IFERROR(K13+N13+Q13+T13,"") -> 30 | X13: =IFERROR((K13*$K$1)+(N13*$N$1)+(Q13*$Q$1)+(T13*$T$1),"") -> 5250 | Y13: =IF(E13<>"",IF(X13<(AE13*$AE$1),(AE13*$AE$1),X13),"") -> 5250 | AD13: =SUMPRODUCT(Z13:AB13,$Z$1:$AB$1) -> 0 | AE13: 10.75 | AF13: 0.75 | AG13: =Table3[[#This Row],[Active hours (Other than drilling)]]*$AF$1 -> 345 | AH13: 0.5 | AJ13: {=SUM(Table3[[#This Row],[Inactive Hours (Other than client standby)]:[Standby Total Hours]]*$AI$1)} -> 180 | AM13: =IF(ISBLANK(AE13),"",SUM(AE13:AF13,AH13:AI13,AK13:AL13)) -> 12 | AN13: =(AF13*$AF$1)+(AH13*$AH$1)+(AI13*$AI$1) -> 525 | AO13: 507.93 | AP13: 117.93 | AQ13: =SUM(Y13,AN13,AP13,H13)+AD13 -> 6282.93 | AR13: 6282.93 | AS13: =SUM($AQ$6:AQ13) -> 28443.2 | AT13: =_xlfn.TEXTJOIN(,TRUE,"0",MONTH(C13)) -> 07 | AU13: =DAY(C13) -> 9 | AV13: =LEFT(D13,1) -> N
A14: MET | C14: =C12+1 -> 45848.21 | D14: DS 5am | E14: SF25_DMET023 | G14: 3 | H14: =IF(ISBLANK(G14),"",G14*$H$1) -> 390 | I14: 63.7 | J14: 84.1 | K14: =IF(ISBLANK(I14),"",J14-I14) -> 20.4 | N14: =IF(ISBLANK(L14),,M14-L14) -> 0 | Q14: =IF(ISBLANK(O14),,P14-O14) -> 0 | T14: =IF(ISBLANK(R14),,S14-R14) -> 0 | U14: =SUM(K14,Q14) -> 20.4 | V14: =SUM(N14,T14) -> 0 | W14: =IFERROR(K14+N14+Q14+T14,"") -> 20.4 | X14: =IFERROR((K14*$K$1)+(N14*$N$1)+(Q14*$Q$1)+(T14*$T$1),"") -> 3570 | Y14: =IF(E14<>"",IF(X14<(AE14*$AE$1),(AE14*$AE$1),X14),"") -> 5060 | AA14: 1 | AB14: 1 | AC14: 13170 | AD14: =SUMPRODUCT(Z14:AB14,$Z$1:$AB$1) -> 575 | AE14: 11 | AF14: 0.5 | AG14: =Table3[[#This Row],[Active hours (Other than drilling)]]*$AF$1 -> 230 | AH14: 0.5 | AJ14: {=SUM(Table3[[#This Row],[Inactive Hours (Other than client standby)]:[Standby Total Hours]]*$AI$1)} -> 180 | AM14: =IF(ISBLANK(AE14),"",SUM(AE14:AF14,AH14:AI14,AK14:AL14)) -> 12 | AN14: =(AF14*$AF$1)+(AH14*$AH$1)+(AI14*$AI$1) -> 410 | AO14: 817.99 | AP14: =817.99-390 -> 427.99 | AQ14: =SUM(Y14,AN14,AP14,H14)+AD14 -> 6862.99 | AR14: 6862.99 | AS14: =SUM($AQ$6:AQ14) -> 35306.19 | AT14: =_xlfn.TEXTJOIN(,TRUE,"0",MONTH(C14)) -> 07 | AU14: =DAY(C14) -> 10 | AV14: =LEFT(D14,1) -> D
A15: MET | C15: =C13+1 -> 45848.71 | D15: NS 5pm | E15: SF25_DMET023 | G15: 3 | H15: =IF(ISBLANK(G15),"",G15*$H$1) -> 390 | I15: 84.1 | J15: 99.7 | K15: =IF(ISBLANK(I15),"",J15-I15) -> 15.6 | N15: =IF(ISBLANK(L15),,M15-L15) -> 0 | Q15: =IF(ISBLANK(O15),,P15-O15) -> 0 | T15: =IF(ISBLANK(R15),,S15-R15) -> 0 | U15: =SUM(K15,Q15) -> 15.6 | V15: =SUM(N15,T15) -> 0 | W15: =IFERROR(K15+N15+Q15+T15,"") -> 15.6 | X15: =IFERROR((K15*$K$1)+(N15*$N$1)+(Q15*$Q$1)+(T15*$T$1),"") -> 2730 | Y15: =IF(E15<>"",IF(X15<(AE15*$AE$1),(AE15*$AE$1),X15),"") -> 3105 | AD15: =SUMPRODUCT(Z15:AB15,$Z$1:$AB$1) -> 0 | AE15: 6.75 | AF15: 4.75 | AG15: =Table3[[#This Row],[Active hours (Other than drilling)]]*$AF$1 -> 2185 | AH15: 0.5 | AJ15: {=SUM(Table3[[#This Row],[Inactive Hours (Other than client standby)]:[Standby Total Hours]]*$AI$1)} -> 180 | AM15: =IF(ISBLANK(AE15),"",SUM(AE15:AF15,AH15:AI15,AK15:AL15)) -> 12 | AN15: =(AF15*$AF$1)+(AH15*$AH$1)+(AI15*$AI$1) -> 2365 | AO15: 1166.68 | AP15: =1166.68-390 -> 776.68 | AQ15: =SUM(Y15,AN15,AP15,H15)+AD15 -> 6636.68 | AR15: 6636.68 | AS15: =SUM($AQ$6:AQ15) -> 41942.87 | AT15: =_xlfn.TEXTJOIN(,TRUE,"0",MONTH(C15)) -> 07 | AU15: =DAY(C15) -> 10 | AV15: =LEFT(D15,1) -> N
A16: MET | B16: 1 | C16: =C14+1 -> 45849.21 | D16: DS 5am | E16: SF25_DMET023 | G16: 3 | H16: =IF(ISBLANK(G16),"",G16*$H$1) -> 390 | I16: 99.7 | J16: 118.7 | K16: =IF(ISBLANK(I16),"",J16-I16) -> 19 | N16: =IF(ISBLANK(L16),,M16-L16) -> 0 | Q16: =IF(ISBLANK(O16),,P16-O16) -> 0 | T16: =IF(ISBLANK(R16),,S16-R16) -> 0 | U16: =SUM(K16,Q16) -> 19 | V16: =SUM(N16,T16) -> 0 | W16: =IFERROR(K16+N16+Q16+T16,"") -> 19 | X16: =IFERROR((K16*$K$1)+(N16*$N$1)+(Q16*$Q$1)+(T16*$T$1),"") -> 3325 | Y16: =IF(E16<>"",IF(X16<(AE16*$AE$1),(AE16*$AE$1),X16),"") -> 3910 | AA16: 1 | AB16: 1 | AC16: 13170 | AD16: =SUMPRODUCT(Z16:AB16,$Z$1:$AB$1) -> 575 | AE16: 8.5 | AF16: 3 | AG16: =Table3[[#This Row],[Active hours (Other than drilling)]]*$AF$1 -> 1380 | AH16: 0.5 | AJ16: {=SUM(Table3[[#This Row],[Inactive Hours (Other than client standby)]:[Standby Total Hours]]*$AI$1)} -> 180 | AM16: =IF(ISBLANK(AE16),"",SUM(AE16:AF16,AH16:AI16,AK16:AL16)) -> 12 | AN16: =(AF16*$AF$1)+(AH16*$AH$1)+(AI16*$AI$1) -> 1560 | AO16: 390 | AQ16: =SUM(Y16,AN16,AP16,H16)+AD16 -> 6435 | AR16: 6435 | AS16: =SUM($AQ$6:AQ16) -> 48377.87 | AT16: =_xlfn.TEXTJOIN(,TRUE,"0",MONTH(C16)) -> 07 | AU16: =DAY(C16) -> 11 | AV16: =LEFT(D16,1) -> D
A17: MET | C17: =C15+1 -> 45849.71 | D17: NS 5pm | E17: SF25_DMET022 | G17: 3 | H17: =IF(ISBLANK(G17),"",G17*$H$1) -> 390 | I17: 0 | J17: 16.5 | K17: =IF(ISBLANK(I17),"",J17-I17) -> 16.5 | N17: =IF(ISBLANK(L17),,M17-L17) -> 0 | Q17: =IF(ISBLANK(O17),,P17-O17) -> 0 | T17: =IF(ISBLANK(R17),,S17-R17) -> 0 | U17: =SUM(K17,Q17) -> 16.5 | V17: =SUM(N17,T17) -> 0 | W17: =IFERROR(K17+N17+Q17+T17,"") -> 16.5 | X17: =IFERROR((K17*$K$1)+(N17*$N$1)+(Q17*$Q$1)+(T17*$T$1),"") -> 2887.5 | Y17: =IF(E17<>"",IF(X17<(AE17*$AE$1),(AE17*$AE$1),X17),"") -> 3335 | AD17: =SUMPRODUCT(Z17:AB17,$Z$1:$AB$1) -> 0 | AE17: 7.25 | AF17: 4.25 | AG17: =Table3[[#This Row],[Active hours (Other than drilling)]]*$AF$1 -> 1955 | AH17: 0.5 | AJ17: {=SUM(Table3[[#This Row],[Inactive Hours (Other than client standby)]:[Standby Total Hours]]*$AI$1)} -> 180 | AM17: =IF(ISBLANK(AE17),"",SUM(AE17:AF17,AH17:AI17,AK17:AL17)) -> 12 | AN17: =(AF17*$AF$1)+(AH17*$AH$1)+(AI17*$AI$1) -> 2135 | AO17: 786.12 | AP17: =786.12-390 -> 396.12 | AQ17: =SUM(Y17,AN17,AP17,H17)+AD17 -> 6256.12 | AR17: 6256.12 | AS17: =SUM($AQ$6:AQ17) -> 54633.99 | AT17: =_xlfn.TEXTJOIN(,TRUE,"0",MONTH(C17)) -> 07 | AU17: =DAY(C17) -> 11 | AV17: =LEFT(D17,1) -> N
A18: MET | C18: =C16+1 -> 45850.21 | D18: DS 5am | E18: SF25_DMET022 | G18: 3 | H18: =IF(ISBLANK(G18),"",G18*$H$1) -> 390 | I18: 16.5 | J18: 39.4 | K18: =IF(ISBLANK(I18),"",J18-I18) -> 22.9 | N18: =IF(ISBLANK(L18),,M18-L18) -> 0 | Q18: =IF(ISBLANK(O18),,P18-O18) -> 0 | T18: =IF(ISBLANK(R18),,S18-R18) -> 0 | U18: =SUM(K18,Q18) -> 22.9 | V18: =SUM(N18,T18) -> 0 | W18: =IFERROR(K18+N18+Q18+T18,"") -> 22.9 | X18: =IFERROR((K18*$K$1)+(N18*$N$1)+(Q18*$Q$1)+(T18*$T$1),"") -> 4007.5 | Y18: =IF(E18<>"",IF(X18<(AE18*$AE$1),(AE18*$AE$1),X18),"") -> 4945 | AA18: 1 | AB18: 1 | AC18: 13170 | AD18: =SUMPRODUCT(Z18:AB18,$Z$1:$AB$1) -> 575 | AE18: 10.75 | AF18: 0.25 | AG18: =Table3[[#This Row],[Active hours (Other than drilling)]]*$AF$1 -> 115 | AH18: 0.5 | AJ18: {=SUM(Table3[[#This Row],[Inactive Hours (Other than client standby)]:[Standby Total Hours]]*$AI$1)} -> 180 | AK18: 0.5 | AM18: =IF(ISBLANK(AE18),"",SUM(AE18:AF18,AH18:AI18,AK18:AL18)) -> 12 | AN18: =(AF18*$AF$1)+(AH18*$AH$1)+(AI18*$AI$1) -> 295 | AO18: 541.79 | AP18: 151.79 | AQ18: =SUM(Y18,AN18,AP18,H18)+AD18 -> 6356.79 | AR18: 6356.79 | AS18: =SUM($AQ$6:AQ18) -> 60990.78 | AT18: =_xlfn.TEXTJOIN(,TRUE,"0",MONTH(C18)) -> 07 | AU18: =DAY(C18) -> 12 | AV18: =LEFT(D18,1) -> D
A19: MET | C19: =C17+1 -> 45850.71 | D19: NS 5pm | E19: SF25_DMET022 | G19: 3 | H19: =IF(ISBLANK(G19),"",G19*$H$1) -> 390 | I19: 39.4 | J19: 60.6 | K19: =IF(ISBLANK(I19),"",J19-I19) -> 21.2 | N19: =IF(ISBLANK(L19),,M19-L19) -> 0 | Q19: =IF(ISBLANK(O19),,P19-O19) -> 0 | T19: =IF(ISBLANK(R19),,S19-R19) -> 0 | U19: =SUM(K19,Q19) -> 21.2 | V19: =SUM(N19,T19) -> 0 | W19: =IFERROR(K19+N19+Q19+T19,"") -> 21.2 | X19: =IFERROR((K19*$K$1)+(N19*$N$1)+(Q19*$Q$1)+(T19*$T$1),"") -> 3710 | Y19: =IF(E19<>"",IF(X19<(AE19*$AE$1),(AE19*$AE$1),X19),"") -> 3910 | AD19: =SUMPRODUCT(Z19:AB19,$Z$1:$AB$1) -> 0 | AE19: 8.5 | AF19: 2.5 | AG19: =Table3[[#This Row],[Active hours (Other than drilling)]]*$AF$1 -> 1150 | AH19: 0.5 | AJ19: {=SUM(Table3[[#This Row],[Inactive Hours (Other than client standby)]:[Standby Total Hours]]*$AI$1)} -> 180 | AK19: 0.5 | AM19: =IF(ISBLANK(AE19),"",SUM(AE19:AF19,AH19:AI19,AK19:AL19)) -> 12 | AN19: =(AF19*$AF$1)+(AH19*$AH$1)+(AI19*$AI$1) -> 1330 | AO19: 507.93 | AP19: 117.93 | AQ19: =SUM(Y19,AN19,AP19,H19)+AD19 -> 5747.93 | AR19: 5747.93 | AS19: =SUM($AQ$6:AQ19) -> 66738.71 | AT19: =_xlfn.TEXTJOIN(,TRUE,"0",MONTH(C19)) -> 07 | AU19: =DAY(C19) -> 12 | AV19: =LEFT(D19,1) -> N
A20: MET | C20: =C18+1 -> 45851.21 | D20: DS 5am | E20: SF25_DMET022 | G20: 3 | H20: =IF(ISBLANK(G20),"",G20*$H$1) -> 390 | I20: 60.6 | J20: 73.8 | K20: =IF(ISBLANK(I20),"",J20-I20) -> 13.2 | N20: =IF(ISBLANK(L20),,M20-L20) -> 0 | Q20: =IF(ISBLANK(O20),,P20-O20) -> 0 | T20: =IF(ISBLANK(R20),,S20-R20) -> 0 | U20: =SUM(K20,Q20) -> 13.2 | V20: =SUM(N20,T20) -> 0 | W20: =IFERROR(K20+N20+Q20+T20,"") -> 13.2 | X20: =IFERROR((K20*$K$1)+(N20*$N$1)+(Q20*$Q$1)+(T20*$T$1),"") -> 2310 | Y20: =IF(E20<>"",IF(X20<(AE20*$AE$1),(AE20*$AE$1),X20),"") -> 4025 | AA20: 1 | AB20: 1 | AC20: 13170 | AD20: =SUMPRODUCT(Z20:AB20,$Z$1:$AB$1) -> 575 | AE20: 8.75 | AF20: 2.75 | AG20: =Table3[[#This Row],[Active hours (Other than drilling)]]*$AF$1 -> 1265 | AH20: 0.5 | AJ20: {=SUM(Table3[[#This Row],[Inactive Hours (Other than client standby)]:[Standby Total Hours]]*$AI$1)} -> 180 | AM20: =IF(ISBLANK(AE20),"",SUM(AE20:AF20,AH20:AI20,AK20:AL20)) -> 12 | AN20: =(AF20*$AF$1)+(AH20*$AH$1)+(AI20*$AI$1) -> 1445 | AO20: 443.23 | AP20: 53.23 | AQ20: =SUM(Y20,AN20,AP20,H20)+AD20 -> 6488.23 | AR20: 6488.23 | AS20: =SUM($AQ$6:AQ20) -> 73226.94 | AT20: =_xlfn.TEXTJOIN(,TRUE,"0",MONTH(C20)) -> 07 | AU20: =DAY(C20) -> 13 | AV20: =LEFT(D20,1) -> D
A21: MET | C21: =C19+1 -> 45851.71 | D21: NS 5pm | E21: SF25_DMET022 | G21: 3 | H21: =IF(ISBLANK(G21),"",G21*$H$1) -> 390 | I21: 73.8 | J21: 101.1 | K21: =IF(ISBLANK(I21),"",J21-I21) -> 27.3 | N21: =IF(ISBLANK(L21),,M21-L21) -> 0 | Q21: =IF(ISBLANK(O21),,P21-O21) -> 0 | T21: =IF(ISBLANK(R21),,S21-R21) -> 0 | U21: =SUM(K21,Q21) -> 27.3 | V21: =SUM(N21,T21) -> 0 | W21: =IFERROR(K21+N21+Q21+T21,"") -> 27.3 | X21: =IFERROR((K21*$K$1)+(N21*$N$1)+(Q21*$Q$1)+(T21*$T$1),"") -> 4777.5 | Y21: =IF(E21<>"",IF(X21<(AE21*$AE$1),(AE21*$AE$1),X21),"") -> 5060 | AD21: =SUMPRODUCT(Z21:AB21,$Z$1:$AB$1) -> 0 | AE21: 11 | AF21: 0.5 | AG21: =Table3[[#This Row],[Active hours (Other than drilling)]]*$AF$1 -> 230 | AH21: 0.5 | AJ21: {=SUM(Table3[[#This Row],[Inactive Hours (Other than client standby)]:[Standby Total Hours]]*$AI$1)} -> 180 | AM21: =IF(ISBLANK(AE21),"",SUM(AE21:AF21,AH21:AI21,AK21:AL21)) -> 12 | AN21: =(AF21*$AF$1)+(AH21*$AH$1)+(AI21*$AI$1) -> 410 | AO21: 507.93 | AP21: 117.93 | AQ21: =SUM(Y21,AN21,AP21,H21)+AD21 -> 5977.93 | AR21: 5977.93 | AS21: =SUM($AQ$6:AQ21) -> 79204.87 | AT21: =_xlfn.TEXTJOIN(,TRUE,"0",MONTH(C21)) -> 07 | AU21: =DAY(C21) -> 13 | AV21: =LEFT(D21,1) -> N
A22: MET | B22: 1 | C22: =C20+1 -> 45852.21 | D22: DS 5am | E22: SF25_DMET022 | G22: 3 | H22: =IF(ISBLANK(G22),"",G22*$H$1) -> 390 | I22: 101.1 | J22: 120.7 | K22: =IF(ISBLANK(I22),"",J22-I22) -> 19.6 | N22: =IF(ISBLANK(L22),,M22-L22) -> 0 | Q22: =IF(ISBLANK(O22),,P22-O22) -> 0 | T22: =IF(ISBLANK(R22),,S22-R22) -> 0 | U22: =SUM(K22,Q22) -> 19.6 | V22: =SUM(N22,T22) -> 0 | W22: =IFERROR(K22+N22+Q22+T22,"") -> 19.6 | X22: =IFERROR((K22*$K$1)+(N22*$N$1)+(Q22*$Q$1)+(T22*$T$1),"") -> 3430 | Y22: =IF(E22<>"",IF(X22<(AE22*$AE$1),(AE22*$AE$1),X22),"") -> 3680 | AA22: 1 | AB22: 1 | AC22: 13170 | AD22: =SUMPRODUCT(Z22:AB22,$Z$1:$AB$1) -> 575 | AE22: 8 | AF22: 3.5 | AG22: =Table3[[#This Row],[Active hours (Other than drilling)]]*$AF$1 -> 1610 | AH22: 0.5 | AJ22: {=SUM(Table3[[#This Row],[Inactive Hours (Other than client standby)]:[Standby Total Hours]]*$AI$1)} -> 180 | AM22: =IF(ISBLANK(AE22),"",SUM(AE22:AF22,AH22:AI22,AK22:AL22)) -> 12 | AN22: =(AF22*$AF$1)+(AH22*$AH$1)+(AI22*$AI$1) -> 1790 | AO22: 390 | AQ22: =SUM(Y22,AN22,AP22,H22)+AD22 -> 6435 | AR22: 6435 | AS22: =SUM($AQ$6:AQ22) -> 85639.87 | AT22: =_xlfn.TEXTJOIN(,TRUE,"0",MONTH(C22)) -> 07 | AU22: =DAY(C22) -> 14 | AV22: =LEFT(D22,1) -> D
A23: MET | C23: =C21+1 -> 45852.71 | D23: NS 5pm | E23: SF25_DMET021 | G23: 3 | H23: =IF(ISBLANK(G23),"",G23*$H$1) -> 390 | I23: 0 | J23: 20.5 | K23: =IF(ISBLANK(I23),"",J23-I23) -> 20.5 | N23: =IF(ISBLANK(L23),,M23-L23) -> 0 | Q23: =IF(ISBLANK(O23),,P23-O23) -> 0 | T23: =IF(ISBLANK(R23),,S23-R23) -> 0 | U23: =SUM(K23,Q23) -> 20.5 | V23: =SUM(N23,T23) -> 0 | W23: =IFERROR(K23+N23+Q23+T23,"") -> 20.5 | X23: =IFERROR((K23*$K$1)+(N23*$N$1)+(Q23*$Q$1)+(T23*$T$1),"") -> 3587.5 | Y23: =IF(E23<>"",IF(X23<(AE23*$AE$1),(AE23*$AE$1),X23),"") -> 3795 | AD23: =SUMPRODUCT(Z23:AB23,$Z$1:$AB$1) -> 0 | AE23: 8.25 | AF23: 3.25 | AG23: =Table3[[#This Row],[Active hours (Other than drilling)]]*$AF$1 -> 1495 | AH23: 0.5 | AJ23: {=SUM(Table3[[#This Row],[Inactive Hours (Other than client standby)]:[Standby Total Hours]]*$AI$1)} -> 180 | AM23: =IF(ISBLANK(AE23),"",SUM(AE23:AF23,AH23:AI23,AK23:AL23)) -> 12 | AN23: =(AF23*$AF$1)+(AH23*$AH$1)+(AI23*$AI$1) -> 1675 | AO23: 625.86 | AP23: 235.86 | AQ23: =SUM(Y23,AN23,AP23,H23)+AD23 -> 6095.86 | AR23: 6095.86 | AS23: =SUM($AQ$6:AQ23) -> 91735.73 | AT23: =_xlfn.TEXTJOIN(,TRUE,"0",MONTH(C23)) -> 07 | AU23: =DAY(C23) -> 14 | AV23: =LEFT(D23,1) -> N
A24: MET | C24: =C22+1 -> 45853.21 | D24: DS 5am | E24: SF25_DMET021 | G24: 3 | H24: =IF(ISBLANK(G24),"",G24*$H$1) -> 390 | I24: 20.5 | J24: 50.5 | K24: =IF(ISBLANK(I24),"",J24-I24) -> 30 | N24: =IF(ISBLANK(L24),,M24-L24) -> 0 | Q24: =IF(ISBLANK(O24),,P24-O24) -> 0 | T24: =IF(ISBLANK(R24),,S24-R24) -> 0 | U24: =SUM(K24,Q24) -> 30 | V24: =SUM(N24,T24) -> 0 | W24: =IFERROR(K24+N24+Q24+T24,"") -> 30 | X24: =IFERROR((K24*$K$1)+(N24*$N$1)+(Q24*$Q$1)+(T24*$T$1),"") -> 5250 | Y24: =IF(E24<>"",IF(X24<(AE24*$AE$1),(AE24*$AE$1),X24),"") -> 5250 | AA24: 1 | AB24: 1 | AC24: 13170 | AD24: =SUMPRODUCT(Z24:AB24,$Z$1:$AB$1) -> 575 | AE24: 10.5 | AF24: 1 | AG24: =Table3[[#This Row],[Active hours (Other than drilling)]]*$AF$1 -> 460 | AH24: 0.5 | AJ24: {=SUM(Table3[[#This Row],[Inactive Hours (Other than client standby)]:[Standby Total Hours]]*$AI$1)} -> 180 | AM24: =IF(ISBLANK(AE24),"",SUM(AE24:AF24,AH24:AI24,AK24:AL24)) -> 12 | AN24: =(AF24*$AF$1)+(AH24*$AH$1)+(AI24*$AI$1) -> 640 | AO24: 1269.56 | AP24: 879.56 | AQ24: =SUM(Y24,AN24,AP24,H24)+AD24 -> 7734.56 | AR24: 7734.56 | AS24: =SUM($AQ$6:AQ24) -> 99470.29 | AT24: =_xlfn.TEXTJOIN(,TRUE,"0",MONTH(C24)) -> 07 | AU24: =DAY(C24) -> 15 | AV24: =LEFT(D24,1) -> D
A25: MET | C25: =C23+1 -> 45853.71 | D25: NS 5pm | E25: SF25_DMET021 | G25: 3 | H25: =IF(ISBLANK(G25),"",G25*$H$1) -> 390 | I25: 50.5 | J25: 80.6 | K25: =IF(ISBLANK(I25),"",J25-I25) -> 30.1 | N25: =IF(ISBLANK(L25),,M25-L25) -> 0 | Q25: =IF(ISBLANK(O25),,P25-O25) -> 0 | T25: =IF(ISBLANK(R25),,S25-R25) -> 0 | U25: =SUM(K25,Q25) -> 30.1 | V25: =SUM(N25,T25) -> 0 | W25: =IFERROR(K25+N25+Q25+T25,"") -> 30.1 | X25: =IFERROR((K25*$K$1)+(N25*$N$1)+(Q25*$Q$1)+(T25*$T$1),"") -> 5267.5 | Y25: =IF(E25<>"",IF(X25<(AE25*$AE$1),(AE25*$AE$1),X25),"") -> 5267.5 | AD25: =SUMPRODUCT(Z25:AB25,$Z$1:$AB$1) -> 0 | AE25: 10.25 | AF25: 1.25 | AG25: =Table3[[#This Row],[Active hours (Other than drilling)]]*$AF$1 -> 575 | AH25: 0.5 | AJ25: {=SUM(Table3[[#This Row],[Inactive Hours (Other than client standby)]:[Standby Total Hours]]*$AI$1)} -> 180 | AM25: =IF(ISBLANK(AE25),"",SUM(AE25:AF25,AH25:AI25,AK25:AL25)) -> 12 | AN25: =(AF25*$AF$1)+(AH25*$AH$1)+(AI25*$AI$1) -> 755 | AO25: 626.49 | AP25: 236.49 | AQ25: =SUM(Y25,AN25,AP25,H25)+AD25 -> 6648.99 | AR25: 6648.99 | AS25: =SUM($AQ$6:AQ25) -> 106119.28 | AT25: =_xlfn.TEXTJOIN(,TRUE,"0",MONTH(C25)) -> 07 | AU25: =DAY(C25) -> 15 | AV25: =LEFT(D25,1) -> N
A26: MET | B26: 1 | C26: =C24+1 -> 45854.21 | D26: DS 5am | E26: SF25_DMET021 | F26: SF25_DMET020 | G26: 3 | H26: =IF(ISBLANK(G26),"",G26*$H$1) -> 390 | I26: 80.6 | J26: 90.6 | K26: =IF(ISBLANK(I26),"",J26-I26) -> 10 | N26: =IF(ISBLANK(L26),,M26-L26) -> 0 | O26: 0 | P26: 9 | Q26: =IF(ISBLANK(O26),,P26-O26) -> 9 | T26: =IF(ISBLANK(R26),,S26-R26) -> 0 | U26: =SUM(K26,Q26) -> 19 | V26: =SUM(N26,T26) -> 0 | W26: =IFERROR(K26+N26+Q26+T26,"") -> 19 | X26: =IFERROR((K26*$K$1)+(N26*$N$1)+(Q26*$Q$1)+(T26*$T$1),"") -> 3325 | Y26: =IF(E26<>"",IF(X26<(AE26*$AE$1),(AE26*$AE$1),X26),"") -> 3325 | AA26: 1 | AB26: 1 | AC26: 13170 | AD26: =SUMPRODUCT(Z26:AB26,$Z$1:$AB$1) -> 575 | AE26: 6.5 | AF26: 4.5 | AG26: =Table3[[#This Row],[Active hours (Other than drilling)]]*$AF$1 -> 2070 | AH26: 1 | AJ26: {=SUM(Table3[[#This Row],[Inactive Hours (Other than client standby)]:[Standby Total Hours]]*$AI$1)} -> 360 | AM26: =IF(ISBLANK(AE26),"",SUM(AE26:AF26,AH26:AI26,AK26:AL26)) -> 12 | AN26: =(AF26*$AF$1)+(AH26*$AH$1)+(AI26*$AI$1) -> 2430 | AO26: 390 | AQ26: =SUM(Y26,AN26,AP26,H26)+AD26 -> 6720 | AR26: 6720 | AS26: =SUM($AQ$6:AQ26) -> 112839.28 | AT26: =_xlfn.TEXTJOIN(,TRUE,"0",MONTH(C26)) -> 07 | AU26: =DAY(C26) -> 16 | AV26: =LEFT(D26,1) -> D
A27: MET | C27: =C25+1 -> 45854.71 | D27: NS 5pm | E27: SF25_DMET020 | G27: 3 | H27: =IF(ISBLANK(G27),"",G27*$H$1) -> 390 | I27: 9 | J27: 30.8 | K27: =IF(ISBLANK(I27),"",J27-I27) -> 21.8 | N27: =IF(ISBLANK(L27),,M27-L27) -> 0 | Q27: =IF(ISBLANK(O27),,P27-O27) -> 0 | T27: =IF(ISBLANK(R27),,S27-R27) -> 0 | U27: =SUM(K27,Q27) -> 21.8 | V27: =SUM(N27,T27) -> 0 | W27: =IFERROR(K27+N27+Q27+T27,"") -> 21.8 | X27: =IFERROR((K27*$K$1)+(N27*$N$1)+(Q27*$Q$1)+(T27*$T$1),"") -> 3815 | Y27: =IF(E27<>"",IF(X27<(AE27*$AE$1),(AE27*$AE$1),X27),"") -> 4025 | AD27: =SUMPRODUCT(Z27:AB27,$Z$1:$AB$1) -> 0 | AE27: 8.75 | AF27: 2.75 | AG27: =Table3[[#This Row],[Active hours (Other than drilling)]]*$AF$1 -> 1265 | AH27: 0.5 | AJ27: {=SUM(Table3[[#This Row],[Inactive Hours (Other than client standby)]:[Standby Total Hours]]*$AI$1)} -> 180 | AM27: =IF(ISBLANK(AE27),"",SUM(AE27:AF27,AH27:AI27,AK27:AL27)) -> 12 | AN27: =(AF27*$AF$1)+(AH27*$AH$1)+(AI27*$AI$1) -> 1445 | AO27: 786.12 | AP27: 396.12 | AQ27: =SUM(Y27,AN27,AP27,H27)+AD27 -> 6256.12 | AR27: 6256.12 | AS27: =SUM($AQ$6:AQ27) -> 119095.4 | AT27: =_xlfn.TEXTJOIN(,TRUE,"0",MONTH(C27)) -> 07 | AU27: =DAY(C27) -> 16 | AV27: =LEFT(D27,1) -> N
A28: MET | C28: =C26+1 -> 45855.21 | D28: DS 5am | E28: SF25_DMET020 | G28: 3 | H28: =IF(ISBLANK(G28),"",G28*$H$1) -> 390 | I28: 30.8 | J28: 57 | K28: =IF(ISBLANK(I28),"",J28-I28) -> 26.2 | N28: =IF(ISBLANK(L28),,M28-L28) -> 0 | Q28: =IF(ISBLANK(O28),,P28-O28) -> 0 | T28: =IF(ISBLANK(R28),,S28-R28) -> 0 | U28: =SUM(K28,Q28) -> 26.2 | V28: =SUM(N28,T28) -> 0 | W28: =IFERROR(K28+N28+Q28+T28,"") -> 26.2 | X28: =IFERROR((K28*$K$1)+(N28*$N$1)+(Q28*$Q$1)+(T28*$T$1),"") -> 4585 | Y28: =IF(E28<>"",IF(X28<(AE28*$AE$1),(AE28*$AE$1),X28),"") -> 4715 | AA28: 1 | AB28: 1 | AC28: 13170 | AD28: =SUMPRODUCT(Z28:AB28,$Z$1:$AB$1) -> 575 | AE28: 10.25 | AF28: 1.25 | AG28: =Table3[[#This Row],[Active hours (Other than drilling)]]*$AF$1 -> 575 | AH28: 0.5 | AJ28: {=SUM(Table3[[#This Row],[Inactive Hours (Other than client standby)]:[Standby Total Hours]]*$AI$1)} -> 180 | AM28: =IF(ISBLANK(AE28),"",SUM(AE28:AF28,AH28:AI28,AK28:AL28)) -> 12 | AN28: =(AF28*$AF$1)+(AH28*$AH$1)+(AI28*$AI$1) -> 755 | AO28: 390 | AQ28: =SUM(Y28,AN28,AP28,H28)+AD28 -> 6435 | AR28: 6435 | AS28: =SUM($AQ$6:AQ28) -> 125530.4 | AT28: =_xlfn.TEXTJOIN(,TRUE,"0",MONTH(C28)) -> 07 | AU28: =DAY(C28) -> 17 | AV28: =LEFT(D28,1) -> D
A29: MET | C29: =C27+1 -> 45855.71 | D29: NS 5pm | E29: SF25_DMET020 | G29: 3 | H29: =IF(ISBLANK(G29),"",G29*$H$1) -> 390 | I29: 57 | J29: 84.7 | K29: =IF(ISBLANK(I29),"",J29-I29) -> 27.7 | N29: =IF(ISBLANK(L29),,M29-L29) -> 0 | Q29: =IF(ISBLANK(O29),,P29-O29) -> 0 | T29: =IF(ISBLANK(R29),,S29-R29) -> 0 | U29: =SUM(K29,Q29) -> 27.7 | V29: =SUM(N29,T29) -> 0 | W29: =IFERROR(K29+N29+Q29+T29,"") -> 27.7 | X29: =IFERROR((K29*$K$1)+(N29*$N$1)+(Q29*$Q$1)+(T29*$T$1),"") -> 4847.5 | Y29: =IF(E29<>"",IF(X29<(AE29*$AE$1),(AE29*$AE$1),X29),"") -> 4847.5 | AD29: =SUMPRODUCT(Z29:AB29,$Z$1:$AB$1) -> 0 | AE29: 10 | AF29: 1.5 | AG29: =Table3[[#This Row],[Active hours (Other than drilling)]]*$AF$1 -> 690 | AH29: 0.5 | AJ29: {=SUM(Table3[[#This Row],[Inactive Hours (Other than client standby)]:[Standby Total Hours]]*$AI$1)} -> 180 | AM29: =IF(ISBLANK(AE29),"",SUM(AE29:AF29,AH29:AI29,AK29:AL29)) -> 12 | AN29: =(AF29*$AF$1)+(AH29*$AH$1)+(AI29*$AI$1) -> 870 | AO29: 507.93 | AP29: 117.93 | AQ29: =SUM(Y29,AN29,AP29,H29)+AD29 -> 6225.43 | AR29: 6225.43 | AS29: =SUM($AQ$6:AQ29) -> 131755.83 | AT29: =_xlfn.TEXTJOIN(,TRUE,"0",MONTH(C29)) -> 07 | AU29: =DAY(C29) -> 17 | AV29: =LEFT(D29,1) -> N
A30: MET | B30: 1 | C30: =C28+1 -> 45856.21 | D30: DS 5am | E30: SF25_DMET020 | G30: 3 | H30: =IF(ISBLANK(G30),"",G30*$H$1) -> 390 | I30: 84.7 | J30: 90.7 | K30: =IF(ISBLANK(I30),"",J30-I30) -> 6 | N30: =IF(ISBLANK(L30),,M30-L30) -> 0 | Q30: =IF(ISBLANK(O30),,P30-O30) -> 0 | T30: =IF(ISBLANK(R30),,S30-R30) -> 0 | U30: =SUM(K30,Q30) -> 6 | V30: =SUM(N30,T30) -> 0 | W30: =IFERROR(K30+N30+Q30+T30,"") -> 6 | X30: =IFERROR((K30*$K$1)+(N30*$N$1)+(Q30*$Q$1)+(T30*$T$1),"") -> 1050 | Y30: =IF(E30<>"",IF(X30<(AE30*$AE$1),(AE30*$AE$1),X30),"") -> 1610 | AA30: 1 | AB30: 1 | AC30: 13170 | AD30: =SUMPRODUCT(Z30:AB30,$Z$1:$AB$1) -> 575 | AE30: 3.5 | AF30: 7.5 | AG30: =Table3[[#This Row],[Active hours (Other than drilling)]]*$AF$1 -> 3450 | AH30: 1 | AJ30: {=SUM(Table3[[#This Row],[Inactive Hours (Other than client standby)]:[Standby Total Hours]]*$AI$1)} -> 360 | AM30: =IF(ISBLANK(AE30),"",SUM(AE30:AF30,AH30:AI30,AK30:AL30)) -> 12 | AN30: =(AF30*$AF$1)+(AH30*$AH$1)+(AI30*$AI$1) -> 3810 | AO30: 390 | AQ30: =SUM(Y30,AN30,AP30,H30)+AD30 -> 6385 | AR30: 6385 | AS30: =SUM($AQ$6:AQ30) -> 138140.83 | AT30: =_xlfn.TEXTJOIN(,TRUE,"0",MONTH(C30)) -> 07 | AU30: =DAY(C30) -> 18 | AV30: =LEFT(D30,1) -> D
A31: MET | C31: =C29+1 -> 45856.71 | D31: NS 5pm | E31: SF25_DMET010 | G31: 3 | H31: =IF(ISBLANK(G31),"",G31*$H$1) -> 390 | I31: 0 | J31: 14.9 | K31: =IF(ISBLANK(I31),"",J31-I31) -> 14.9 | N31: =IF(ISBLANK(L31),,M31-L31) -> 0 | Q31: =IF(ISBLANK(O31),,P31-O31) -> 0 | T31: =IF(ISBLANK(R31),,S31-R31) -> 0 | U31: =SUM(K31,Q31) -> 14.9 | V31: =SUM(N31,T31) -> 0 | W31: =IFERROR(K31+N31+Q31+T31,"") -> 14.9 | X31: =IFERROR((K31*$K$1)+(N31*$N$1)+(Q31*$Q$1)+(T31*$T$1),"") -> 2607.5 | Y31: =IF(E31<>"",IF(X31<(AE31*$AE$1),(AE31*$AE$1),X31),"") -> 2607.5 | AD31: =SUMPRODUCT(Z31:AB31,$Z$1:$AB$1) -> 0 | AE31: 5.25 | AF31: 3.75 | AG31: =Table3[[#This Row],[Active hours (Other than drilling)]]*$AF$1 -> 1725 | AH31: 0.5 | AI31: 2.5 | AJ31: {=SUM(Table3[[#This Row],[Inactive Hours (Other than client standby)]:[Standby Total Hours]]*$AI$1)} -> 1080 | AM31: =IF(ISBLANK(AE31),"",SUM(AE31:AF31,AH31:AI31,AK31:AL31)) -> 12 | AN31: =(AF31*$AF$1)+(AH31*$AH$1)+(AI31*$AI$1) -> 2805 | AO31: 904.05 | AP31: 514.05 | AQ31: =SUM(Y31,AN31,AP31,H31)+AD31 -> 6316.55 | AR31: 6316.55 | AS31: =SUM($AQ$6:AQ31) -> 144457.38 | AT31: =_xlfn.TEXTJOIN(,TRUE,"0",MONTH(C31)) -> 07 | AU31: =DAY(C31) -> 18 | AV31: =LEFT(D31,1) -> N
A32: MET | C32: =C30+1 -> 45857.21 | D32: DS 5am | E32: SF25_DMET010 | G32: 3 | H32: =IF(ISBLANK(G32),"",G32*$H$1) -> 390 | I32: 14.9 | J32: 45.6 | K32: =IF(ISBLANK(I32),"",J32-I32) -> 30.7 | N32: =IF(ISBLANK(L32),,M32-L32) -> 0 | Q32: =IF(ISBLANK(O32),,P32-O32) -> 0 | T32: =IF(ISBLANK(R32),,S32-R32) -> 0 | U32: =SUM(K32,Q32) -> 30.7 | V32: =SUM(N32,T32) -> 0 | W32: =IFERROR(K32+N32+Q32+T32,"") -> 30.7 | X32: =IFERROR((K32*$K$1)+(N32*$N$1)+(Q32*$Q$1)+(T32*$T$1),"") -> 5372.5 | Y32: =IF(E32<>"",IF(X32<(AE32*$AE$1),(AE32*$AE$1),X32),"") -> 5372.5 | AA32: 1 | AB32: 1 | AC32: 13170 | AD32: =SUMPRODUCT(Z32:AB32,$Z$1:$AB$1) -> 575 | AE32: 10.75 | AF32: 0.75 | AG32: =Table3[[#This Row],[Active hours (Other than drilling)]]*$AF$1 -> 345 | AH32: 0.5 | AJ32: {=SUM(Table3[[#This Row],[Inactive Hours (Other than client standby)]:[Standby Total Hours]]*$AI$1)} -> 180 | AM32: =IF(ISBLANK(AE32),"",SUM(AE32:AF32,AH32:AI32,AK32:AL32)) -> 12 | AN32: =(AF32*$AF$1)+(AH32*$AH$1)+(AI32*$AI$1) -> 525 | AO32: 390 | AQ32: =SUM(Y32,AN32,AP32,H32)+AD32 -> 6862.5 | AR32: 6862.5 | AS32: =SUM($AQ$6:AQ32) -> 151319.88 | AT32: =_xlfn.TEXTJOIN(,TRUE,"0",MONTH(C32)) -> 07 | AU32: =DAY(C32) -> 19 | AV32: =LEFT(D32,1) -> D
A33: MET | C33: =C31+1 -> 45857.71 | D33: NS 5pm | E33: SF25_DMET010 | G33: 3 | H33: =IF(ISBLANK(G33),"",G33*$H$1) -> 390 | I33: 45.6 | J33: 75.6 | K33: =IF(ISBLANK(I33),"",J33-I33) -> 30 | N33: =IF(ISBLANK(L33),,M33-L33) -> 0 | Q33: =IF(ISBLANK(O33),,P33-O33) -> 0 | T33: =IF(ISBLANK(R33),,S33-R33) -> 0 | U33: =SUM(K33,Q33) -> 30 | V33: =SUM(N33,T33) -> 0 | W33: =IFERROR(K33+N33+Q33+T33,"") -> 30 | X33: =IFERROR((K33*$K$1)+(N33*$N$1)+(Q33*$Q$1)+(T33*$T$1),"") -> 5250 | Y33: =IF(E33<>"",IF(X33<(AE33*$AE$1),(AE33*$AE$1),X33),"") -> 5250 | AD33: =SUMPRODUCT(Z33:AB33,$Z$1:$AB$1) -> 0 | AE33: 10.5 | AF33: 1 | AG33: =Table3[[#This Row],[Active hours (Other than drilling)]]*$AF$1 -> 460 | AH33: 0.5 | AJ33: {=SUM(Table3[[#This Row],[Inactive Hours (Other than client standby)]:[Standby Total Hours]]*$AI$1)} -> 180 | AM33: =IF(ISBLANK(AE33),"",SUM(AE33:AF33,AH33:AI33,AK33:AL33)) -> 12 | AN33: =(AF33*$AF$1)+(AH33*$AH$1)+(AI33*$AI$1) -> 640 | AO33: 507.93 | AP33: 117.93 | AQ33: =SUM(Y33,AN33,AP33,H33)+AD33 -> 6397.93 | AR33: 6397.93 | AS33: =SUM($AQ$6:AQ33) -> 157717.81 | AT33: =_xlfn.TEXTJOIN(,TRUE,"0",MONTH(C33)) -> 07 | AU33: =DAY(C33) -> 19 | AV33: =LEFT(D33,1) -> N
A34: MET | B34: 1 | C34: =C32+1 -> 45858.21 | D34: DS 5am | E34: SF25_DMET010 | F34: SF25_DDGT012 | G34: 3 | H34: =IF(ISBLANK(G34),"",G34*$H$1) -> 390 | I34: 75.6 | J34: 81.6 | K34: =IF(ISBLANK(I34),"",J34-I34) -> 6 | L34: 0 | M34: 2.3 | N34: =IF(ISBLANK(L34),,M34-L34) -> 2.3 | Q34: =IF(ISBLANK(O34),,P34-O34) -> 0 | T34: =IF(ISBLANK(R34),,S34-R34) -> 0 | U34: =SUM(K34,Q34) -> 6 | V34: =SUM(N34,T34) -> 2.3 | W34: =IFERROR(K34+N34+Q34+T34,"") -> 8.3 | X34: =IFERROR((K34*$K$1)+(N34*$N$1)+(Q34*$Q$1)+(T34*$T$1),"") -> 1360.5 | Y34: =IF(E34<>"",IF(X34<(AE34*$AE$1),(AE34*$AE$1),X34),"") -> 1495 | AA34: 1 | AB34: 1 | AC34: 13170 | AD34: =SUMPRODUCT(Z34:AB34,$Z$1:$AB$1) -> 575 | AE34: 3.25 | AF34: 7.75 | AG34: =Table3[[#This Row],[Active hours (Other than drilling)]]*$AF$1 -> 3565 | AH34: 0.5 | AJ34: {=SUM(Table3[[#This Row],[Inactive Hours (Other than client standby)]:[Standby Total Hours]]*$AI$1)} -> 180 | AK34: 0.5 | AM34: =IF(ISBLANK(AE34),"",SUM(AE34:AF34,AH34:AI34,AK34:AL34)) -> 12 | AN34: =(AF34*$AF$1)+(AH34*$AH$1)+(AI34*$AI$1) -> 3745 | AO34: 390 | AQ34: =SUM(Y34,AN34,AP34,H34)+AD34 -> 6205 | AR34: 6205 | AS34: =SUM($AQ$6:AQ34) -> 163922.81 | AT34: =_xlfn.TEXTJOIN(,TRUE,"0",MONTH(C34)) -> 07 | AU34: =DAY(C34) -> 20 | AV34: =LEFT(D34,1) -> D
A35: GT | C35: =C33+1 -> 45858.71 | D35: NS 5pm | E35: SF25_DDGT012 | G35: 3 | H35: =IF(ISBLANK(G35),"",G35*$H$1) -> 390 | K35: 0 | L35: 2.3 | M35: 19.8 | N35: =IF(ISBLANK(L35),,M35-L35) -> 17.5 | Q35: =IF(ISBLANK(O35),,P35-O35) -> 0 | T35: =IF(ISBLANK(R35),,S35-R35) -> 0 | U35: =SUM(K35,Q35) -> 0 | V35: =SUM(N35,T35) -> 17.5 | W35: =IFERROR(K35+N35+Q35+T35,"") -> 17.5 | X35: =IFERROR((K35*$K$1)+(N35*$N$1)+(Q35*$Q$1)+(T35*$T$1),"") -> 2362.5 | Y35: =IF(E35<>"",IF(X35<(AE35*$AE$1),(AE35*$AE$1),X35),"") -> 3335 | AD35: =SUMPRODUCT(Z35:AB35,$Z$1:$AB$1) -> 0 | AE35: 7.25 | AF35: 3.75 | AG35: =Table3[[#This Row],[Active hours (Other than drilling)]]*$AF$1 -> 1725 | AH35: 0.5 | AJ35: {=SUM(Table3[[#This Row],[Inactive Hours (Other than client standby)]:[Standby Total Hours]]*$AI$1)} -> 180 | AK35: 0.5 | AM35: =IF(ISBLANK(AE35),"",SUM(AE35:AF35,AH35:AI35,AK35:AL35)) -> 12 | AN35: =(AF35*$AF$1)+(AH35*$AH$1)+(AI35*$AI$1) -> 1905 | AO35: 904.05 | AP35: 514.05 | AQ35: =SUM(Y35,AN35,AP35,H35)+AD35 -> 6144.05 | AR35: 6144.05 | AS35: =SUM($AQ$6:AQ35) -> 170066.86 | AT35: =_xlfn.TEXTJOIN(,TRUE,"0",MONTH(C35)) -> 07 | AU35: =DAY(C35) -> 20 | AV35: =LEFT(D35,1) -> N
A36: GT | C36: =C34+1 -> 45859.21 | D36: DS 5am | E36: SF25_DDGT012 | G36: 3 | H36: =IF(ISBLANK(G36),"",G36*$H$1) -> 390 | K36: 0 | L36: 19.8 | M36: 41.3 | N36: =IF(ISBLANK(L36),,M36-L36) -> 21.5 | Q36: =IF(ISBLANK(O36),,P36-O36) -> 0 | T36: =IF(ISBLANK(R36),,S36-R36) -> 0 | U36: =SUM(K36,Q36) -> 0 | V36: =SUM(N36,T36) -> 21.5 | W36: 21.5 | X36: =IFERROR((K36*$K$1)+(N36*$N$1)+(Q36*$Q$1)+(T36*$T$1),"") -> 2902.5 | Y36: =IF(E36<>"",IF(X36<(AE36*$AE$1),(AE36*$AE$1),X36),"") -> 4945 | AA36: 1 | AB36: 1 | AC36: 13170 | AD36: =SUMPRODUCT(Z36:AB36,$Z$1:$AB$1) -> 575 | AE36: 10.75 | AF36: 0.75 | AG36: =Table3[[#This Row],[Active hours (Other than drilling)]]*$AF$1 -> 345 | AH36: 0.5 | AJ36: {=SUM(Table3[[#This Row],[Inactive Hours (Other than client standby)]:[Standby Total Hours]]*$AI$1)} -> 180 | AM36: =IF(ISBLANK(AE36),"",SUM(AE36:AF36,AH36:AI36,AK36:AL36)) -> 12 | AN36: =(AF36*$AF$1)+(AH36*$AH$1)+(AI36*$AI$1) -> 525 | AO36: 541.79 | AP36: 151.79 | AQ36: =SUM(Y36,AN36,AP36,H36)+AD36 -> 6586.79 | AR36: 6586.79 | AS36: =SUM($AQ$6:AQ36) -> 176653.65 | AT36: =_xlfn.TEXTJOIN(,TRUE,"0",MONTH(C36)) -> 07 | AU36: =DAY(C36) -> 21 | AV36: =LEFT(D36,1) -> D
A37: GT | C37: =C35+1 -> 45859.71 | D37: NS 5pm | E37: SF25_DDGT012 | G37: 3 | H37: =IF(ISBLANK(G37),"",G37*$H$1) -> 390 | K37: =IF(ISBLANK(I37),0,J37-I37) -> 0 | L37: 41.3 | M37: 63.2 | N37: =IF(ISBLANK(L37),,M37-L37) -> 21.9 | Q37: =IF(ISBLANK(O37),,P37-O37) -> 0 | T37: =IF(ISBLANK(R37),,S37-R37) -> 0 | U37: =SUM(K37,Q37) -> 0 | V37: =SUM(N37,T37) -> 21.9 | W37: =IFERROR(K37+N37+Q37+T37,"") -> 21.9 | X37: =IFERROR((K37*$K$1)+(N37*$N$1)+(Q37*$Q$1)+(T37*$T$1),"") -> 2956.5 | Y37: =IF(E37<>"",IF(X37<(AE37*$AE$1),(AE37*$AE$1),X37),"") -> 4945 | AD37: =SUMPRODUCT(Z37:AB37,$Z$1:$AB$1) -> 0 | AE37: 10.75 | AF37: 0.75 | AG37: =Table3[[#This Row],[Active hours (Other than drilling)]]*$AF$1 -> 345 | AH37: 0.5 | AJ37: {=SUM(Table3[[#This Row],[Inactive Hours (Other than client standby)]:[Standby Total Hours]]*$AI$1)} -> 180 | AM37: =IF(ISBLANK(AE37),"",SUM(AE37:AF37,AH37:AI37,AK37:AL37)) -> 12 | AN37: =(AF37*$AF$1)+(AH37*$AH$1)+(AI37*$AI$1) -> 525 | AO37: 507.93 | AP37: 117.93 | AQ37: =SUM(Y37,AN37,AP37,H37)+AD37 -> 5977.93 | AR37: 5977.93 | AS37: =SUM($AQ$6:AQ37) -> 182631.58 | AT37: =_xlfn.TEXTJOIN(,TRUE,"0",MONTH(C37)) -> 07 | AU37: =DAY(C37) -> 21 | AV37: =LEFT(D37,1) -> N
A38: GT | B38: 1 | C38: =C36+1 -> 45860.21 | D38: DS 5am | E38: SF25_DDGT012 | F38: SF25_DMET024 | G38: 3 | H38: =IF(ISBLANK(G38),"",G38*$H$1) -> 390 | I38: 0 | J38: 3.7 | K38: =IF(ISBLANK(I38),0,J38-I38) -> 3.7 | L38: 63.2 | M38: 70.5 | N38: =IF(ISBLANK(L38),,M38-L38) -> 7.3 | Q38: =IF(ISBLANK(O38),,P38-O38) -> 0 | T38: =IF(ISBLANK(R38),,S38-R38) -> 0 | U38: =SUM(K38,Q38) -> 3.7 | V38: =SUM(N38,T38) -> 7.3 | W38: =IFERROR(K38+N38+Q38+T38,"") -> 11 | X38: =IFERROR((K38*$K$1)+(N38*$N$1)+(Q38*$Q$1)+(T38*$T$1),"") -> 1633 | Y38: =IF(E38<>"",IF(X38<(AE38*$AE$1),(AE38*$AE$1),X38),"") -> 2875 | AA38: 1 | AB38: 1 | AC38: 13170 | AD38: =SUMPRODUCT(Z38:AB38,$Z$1:$AB$1) -> 575 | AE38: 6.25 | AF38: 5.25 | AG38: =Table3[[#This Row],[Active hours (Other than drilling)]]*$AF$1 -> 2415 | AH38: 0.5 | AJ38: {=SUM(Table3[[#This Row],[Inactive Hours (Other than client standby)]:[Standby Total Hours]]*$AI$1)} -> 180 | AM38: =IF(ISBLANK(AE38),"",SUM(AE38:AF38,AH38:AI38,AK38:AL38)) -> 12 | AN38: =(AF38*$AF$1)+(AH38*$AH$1)+(AI38*$AI$1) -> 2595 | AO38: 390 | AQ38: =SUM(Y38,AN38,AP38,H38)+AD38 -> 6435 | AR38: 6435 | AS38: =SUM($AQ$6:AQ38) -> 189066.58 | AT38: =_xlfn.TEXTJOIN(,TRUE,"0",MONTH(C38)) -> 07 | AU38: =DAY(C38) -> 22 | AV38: =LEFT(D38,1) -> D
A39: =IFERROR(IF(FIND("MET",E39),"MET",IF(FIND("GT",E39),"GT",)),"") -> MET | C39: =C37+1 -> 45860.71 | D39: NS 5pm | E39: SF25_DMET024 | G39: 3 | H39: =IF(ISBLANK(G39),"",G39*$H$1) -> 390 | I39: 3.7 | J39: 20.1 | K39: =IF(ISBLANK(I39),0,J39-I39) -> 16.4 | N39: =IF(ISBLANK(L39),,M39-L39) -> 0 | Q39: =IF(ISBLANK(O39),,P39-O39) -> 0 | T39: =IF(ISBLANK(R39),,S39-R39) -> 0 | U39: =SUM(K39,Q39) -> 16.4 | V39: =SUM(N39,T39) -> 0 | W39: =IFERROR(K39+N39+Q39+T39,"") -> 16.4 | X39: =IFERROR((K39*$K$1)+(N39*$N$1)+(Q39*$Q$1)+(T39*$T$1),"") -> 2870 | Y39: =IF(E39<>"",IF(X39<(AE39*$AE$1),(AE39*$AE$1),X39),"") -> 2870 | AD39: =SUMPRODUCT(Z39:AB39,$Z$1:$AB$1) -> 0 | AE39: 5.75 | AF39: 2.75 | AG39: =Table3[[#This Row],[Active hours (Other than drilling)]]*$AF$1 -> 1265 | AH39: 0.5 | AJ39: {=SUM(Table3[[#This Row],[Inactive Hours (Other than client standby)]:[Standby Total Hours]]*$AI$1)} -> 180 | AK39: 3 | AM39: =IF(ISBLANK(AE39),"",SUM(AE39:AF39,AH39:AI39,AK39:AL39)) -> 12 | AN39: =(AF39*$AF$1)+(AH39*$AH$1)+(AI39*$AI$1) -> 1445 | AO39: 904.05 | AP39: 514.05 | AQ39: =SUM(Y39,AN39,AP39,H39)+AD39 -> 5219.05 | AR39: 5219.05 | AS39: =SUM($AQ$6:AQ39) -> 194285.63 | AT39: =_xlfn.TEXTJOIN(,TRUE,"0",MONTH(C39)) -> 07 | AU39: =DAY(C39) -> 22 | AV39: =LEFT(D39,1) -> N
A40: =IFERROR(IF(FIND("MET",E40),"MET",IF(FIND("GT",E40),"GT",)),"") -> MET | C40: =C38+1 -> 45861.21 | D40: DS 5am | E40: SF25_DMET024 | G40: 3 | H40: =IF(ISBLANK(G40),"",G40*$H$1) -> 390 | I40: 20.1 | J40: 27.7 | K40: =IF(ISBLANK(I40),0,J40-I40) -> 7.6 | N40: =IF(ISBLANK(L40),,M40-L40) -> 0 | Q40: =IF(ISBLANK(O40),,P40-O40) -> 0 | T40: =IF(ISBLANK(R40),,S40-R40) -> 0 | U40: =SUM(K40,Q40) -> 7.6 | V40: =SUM(N40,T40) -> 0 | W40: =IFERROR(K40+N40+Q40+T40,"") -> 7.6 | X40: =IFERROR((K40*$K$1)+(N40*$N$1)+(Q40*$Q$1)+(T40*$T$1),"") -> 1330 | Y40: =IF(E40<>"",IF(X40<(AE40*$AE$1),(AE40*$AE$1),X40),"") -> 1610 | AA40: 1 | AB40: 1 | AC40: 13170 | AD40: =SUMPRODUCT(Z40:AB40,$Z$1:$AB$1) -> 575 | AE40: 3.5 | AF40: 0.75 | AG40: =Table3[[#This Row],[Active hours (Other than drilling)]]*$AF$1 -> 345 | AH40: 0.5 | AJ40: {=SUM(Table3[[#This Row],[Inactive Hours (Other than client standby)]:[Standby Total Hours]]*$AI$1)} -> 180 | AK40: 7.25 | AM40: =IF(ISBLANK(AE40),"",SUM(AE40:AF40,AH40:AI40,AK40:AL40)) -> 12 | AN40: =(AF40*$AF$1)+(AH40*$AH$1)+(AI40*$AI$1) -> 525 | AO40: 390 | AQ40: =SUM(Y40,AN40,AP40,H40)+AD40 -> 3100 | AR40: 3100 | AS40: =SUM($AQ$6:AQ40) -> 197385.63 | AT40: =_xlfn.TEXTJOIN(,TRUE,"0",MONTH(C40)) -> 07 | AU40: =DAY(C40) -> 23 | AV40: =LEFT(D40,1) -> D
A41: =IFERROR(IF(FIND("MET",E41),"MET",IF(FIND("GT",E41),"GT",)),"") -> MET | C41: =C39+1 -> 45861.71 | D41: NS 5pm | E41: SF25_DMET024 | G41: 3 | H41: =IF(ISBLANK(G41),"",G41*$H$1) -> 390 | I41: 27.7 | J41: 55.1 | K41: =IF(ISBLANK(I41),0,J41-I41) -> 27.4 | N41: =IF(ISBLANK(L41),,M41-L41) -> 0 | Q41: =IF(ISBLANK(O41),,P41-O41) -> 0 | T41: =IF(ISBLANK(R41),,S41-R41) -> 0 | U41: =SUM(K41,Q41) -> 27.4 | V41: =SUM(N41,T41) -> 0 | W41: =IFERROR(K41+N41+Q41+T41,"") -> 27.4 | X41: =IFERROR((K41*$K$1)+(N41*$N$1)+(Q41*$Q$1)+(T41*$T$1),"") -> 4795 | Y41: =IF(E41<>"",IF(X41<(AE41*$AE$1),(AE41*$AE$1),X41),"") -> 4830 | AD41: =SUMPRODUCT(Z41:AB41,$Z$1:$AB$1) -> 0 | AE41: 10.5 | AF41: 1 | AG41: =Table3[[#This Row],[Active hours (Other than drilling)]]*$AF$1 -> 460 | AH41: 0.5 | AJ41: {=SUM(Table3[[#This Row],[Inactive Hours (Other than client standby)]:[Standby Total Hours]]*$AI$1)} -> 180 | AM41: =IF(ISBLANK(AE41),"",SUM(AE41:AF41,AH41:AI41,AK41:AL41)) -> 12 | AN41: =(AF41*$AF$1)+(AH41*$AH$1)+(AI41*$AI$1) -> 640 | AO41: 390 | AQ41: =SUM(Y41,AN41,AP41,H41)+AD41 -> 5860 | AR41: 5860 | AS41: =SUM($AQ$6:AQ41) -> 203245.63 | AT41: =_xlfn.TEXTJOIN(,TRUE,"0",MONTH(C41)) -> 07 | AU41: =DAY(C41) -> 23 | AV41: =LEFT(D41,1) -> N
A42: =IFERROR(IF(FIND("MET",E42),"MET",IF(FIND("GT",E42),"GT",)),"") -> MET | C42: =C40+1 -> 45862.21 | D42: DS 5am | E42: SF25_DMET024 | G42: 3 | H42: =IF(ISBLANK(G42),"",G42*$H$1) -> 390 | I42: 55.1 | J42: 84.7 | K42: =IF(ISBLANK(I42),0,J42-I42) -> 29.6 | N42: =IF(ISBLANK(L42),,M42-L42) -> 0 | Q42: =IF(ISBLANK(O42),,P42-O42) -> 0 | T42: =IF(ISBLANK(R42),,S42-R42) -> 0 | U42: =SUM(K42,Q42) -> 29.6 | V42: =SUM(N42,T42) -> 0 | W42: =IFERROR(K42+N42+Q42+T42,"") -> 29.6 | X42: =IFERROR((K42*$K$1)+(N42*$N$1)+(Q42*$Q$1)+(T42*$T$1),"") -> 5180 | Y42: =IF(E42<>"",IF(X42<(AE42*$AE$1),(AE42*$AE$1),X42),"") -> 5180 | AA42: 1 | AB42: 1 | AC42: 13170 | AD42: =SUMPRODUCT(Z42:AB42,$Z$1:$AB$1) -> 575 | AE42: 10.5 | AF42: 1 | AG42: =Table3[[#This Row],[Active hours (Other than drilling)]]*$AF$1 -> 460 | AH42: 0.5 | AJ42: {=SUM(Table3[[#This Row],[Inactive Hours (Other than client standby)]:[Standby Total Hours]]*$AI$1)} -> 180 | AM42: =IF(ISBLANK(AE42),"",SUM(AE42:AF42,AH42:AI42,AK42:AL42)) -> 12 | AN42: =(AF42*$AF$1)+(AH42*$AH$1)+(AI42*$AI$1) -> 640 | AO42: 646.06 | AP42: 256.06 | AQ42: =SUM(Y42,AN42,AP42,H42)+AD42 -> 7041.06 | AR42: 7041.06 | AS42: =SUM($AQ$6:AQ42) -> 210286.69 | AT42: =_xlfn.TEXTJOIN(,TRUE,"0",MONTH(C42)) -> 07 | AU42: =DAY(C42) -> 24 | AV42: =LEFT(D42,1) -> D
A43: =IFERROR(IF(FIND("MET",E43),"MET",IF(FIND("GT",E43),"GT",)),"") -> MET | B43: 1 | C43: =C41+1 -> 45862.71 | D43: NS 5pm | E43: SF25_DMET024 | G43: 3 | H43: =IF(ISBLANK(G43),"",G43*$H$1) -> 390 | I43: 84.7 | J43: 101.1 | K43: =IF(ISBLANK(I43),0,J43-I43) -> 16.4 | N43: =IF(ISBLANK(L43),,M43-L43) -> 0 | Q43: =IF(ISBLANK(O43),,P43-O43) -> 0 | T43: =IF(ISBLANK(R43),,S43-R43) -> 0 | U43: =SUM(K43,Q43) -> 16.4 | V43: =SUM(N43,T43) -> 0 | W43: =IFERROR(K43+N43+Q43+T43,"") -> 16.4 | X43: =IFERROR((K43*$K$1)+(N43*$N$1)+(Q43*$Q$1)+(T43*$T$1),"") -> 2870 | Y43: =IF(E43<>"",IF(X43<(AE43*$AE$1),(AE43*$AE$1),X43),"") -> 3335 | AD43: =SUMPRODUCT(Z43:AB43,$Z$1:$AB$1) -> 0 | AE43: 7.25 | AF43: 4.25 | AG43: =Table3[[#This Row],[Active hours (Other than drilling)]]*$AF$1 -> 1955 | AH43: 0.5 | AJ43: {=SUM(Table3[[#This Row],[Inactive Hours (Other than client standby)]:[Standby Total Hours]]*$AI$1)} -> 180 | AM43: =IF(ISBLANK(AE43),"",SUM(AE43:AF43,AH43:AI43,AK43:AL43)) -> 12 | AN43: =(AF43*$AF$1)+(AH43*$AH$1)+(AI43*$AI$1) -> 2135 | AO43: 390 | AQ43: =SUM(Y43,AN43,AP43,H43)+AD43 -> 5860 | AR43: 5860 | AS43: =SUM($AQ$6:AQ43) -> 216146.69 | AT43: =_xlfn.TEXTJOIN(,TRUE,"0",MONTH(C43)) -> 07 | AU43: =DAY(C43) -> 24 | AV43: =LEFT(D43,1) -> N
A44: GT | C44: =C42+1 -> 45863.21 | D44: DS 5am | E44: SF25_DDGT006 | G44: 3 | H44: =IF(ISBLANK(G44),"",G44*$H$1) -> 390 | K44: =IF(ISBLANK(I44),0,J44-I44) -> 0 | N44: =IF(ISBLANK(L44),,M44-L44) -> 0 | Q44: =IF(ISBLANK(O44),,P44-O44) -> 0 | T44: =IF(ISBLANK(R44),,S44-R44) -> 0 | U44: =SUM(K44,Q44) -> 0 | V44: =SUM(N44,T44) -> 0 | W44: =IFERROR(K44+N44+Q44+T44,"") -> 0 | X44: =IFERROR((K44*$K$1)+(N44*$N$1)+(Q44*$Q$1)+(T44*$T$1),"") -> 0 | Y44: =IF(E44<>"",IF(X44<(AE44*$AE$1),(AE44*$AE$1),X44),"") -> 0 | AA44: 1 | AB44: 1 | AC44: 13170 | AD44: =SUMPRODUCT(Z44:AB44,$Z$1:$AB$1) -> 575 | AE44: 0 | AF44: 7.5 | AG44: =Table3[[#This Row],[Active hours (Other than drilling)]]*$AF$1 -> 3450 | AH44: 4.5 | AJ44: {=SUM(Table3[[#This Row],[Inactive Hours (Other than client standby)]:[Standby Total Hours]]*$AI$1)} -> 1620 | AM44: =IF(ISBLANK(AE44),"",SUM(AE44:AF44,AH44:AI44,AK44:AL44)) -> 12 | AN44: =(AF44*$AF$1)+(AH44*$AH$1)+(AI44*$AI$1) -> 5070 | AO44: 646.06 | AP44: 256.06 | AQ44: =SUM(Y44,AN44,AP44,H44)+AD44 -> 6291.06 | AR44: 6291.06 | AS44: =SUM($AQ$6:AQ44) -> 222437.75 | AT44: =_xlfn.TEXTJOIN(,TRUE,"0",MONTH(C44)) -> 07 | AU44: =DAY(C44) -> 25 | AV44: =LEFT(D44,1) -> D
A45: GT | C45: =C43+1 -> 45863.71 | D45: NS 5pm | E45: SF25_DDGT006 | G45: 3 | H45: =IF(ISBLANK(G45),"",G45*$H$1) -> 390 | K45: =IF(ISBLANK(I45),0,J45-I45) -> 0 | L45: 6 | M45: 13.8 | N45: =IF(ISBLANK(L45),,M45-L45) -> 7.8 | Q45: =IF(ISBLANK(O45),,P45-O45) -> 0 | T45: =IF(ISBLANK(R45),,S45-R45) -> 0 | U45: =SUM(K45,Q45) -> 0 | V45: =SUM(N45,T45) -> 7.8 | W45: =IFERROR(K45+N45+Q45+T45,"") -> 7.8 | X45: =IFERROR((K45*$K$1)+(N45*$N$1)+(Q45*$Q$1)+(T45*$T$1),"") -> 1053 | Y45: =IF(E45<>"",IF(X45<(AE45*$AE$1),(AE45*$AE$1),X45),"") -> 1840 | AD45: =SUMPRODUCT(Z45:AB45,$Z$1:$AB$1) -> 0 | AE45: 4 | AF45: 3 | AG45: =Table3[[#This Row],[Active hours (Other than drilling)]]*$AF$1 -> 1380 | AH45: 5 | AJ45: {=SUM(Table3[[#This Row],[Inactive Hours (Other than client standby)]:[Standby Total Hours]]*$AI$1)} -> 1800 | AM45: =IF(ISBLANK(AE45),"",SUM(AE45:AF45,AH45:AI45,AK45:AL45)) -> 12 | AN45: =(AF45*$AF$1)+(AH45*$AH$1)+(AI45*$AI$1) -> 3180 | AO45: 390 | AQ45: =SUM(Y45,AN45,AP45,H45)+AD45 -> 5410 | AR45: 5410 | AS45: =SUM($AQ$6:AQ45) -> 227847.75 | AT45: =_xlfn.TEXTJOIN(,TRUE,"0",MONTH(C45)) -> 07 | AU45: =DAY(C45) -> 25 | AV45: =LEFT(D45,1) -> N
A46: GT | B46: 1 | C46: =C44+1 -> 45864.21 | D46: DS 5am | E46: SF25_DDGT006 | F46: SF25_DDGT005 | G46: 3 | H46: =IF(ISBLANK(G46),"",G46*$H$1) -> 390 | K46: =IF(ISBLANK(I46),0,J46-I46) -> 0 | L46: 13.8 | M46: 15 | N46: =IF(ISBLANK(L46),,M46-L46) -> 1.2 | Q46: =IF(ISBLANK(O46),,P46-O46) -> 0 | R46: 0 | S46: 2 | T46: =IF(ISBLANK(R46),,S46-R46) -> 2 | U46: =SUM(K46,Q46) -> 0 | V46: =SUM(N46,T46) -> 3.2 | W46: =IFERROR(K46+N46+Q46+T46,"") -> 3.2 | X46: =IFERROR((K46*$K$1)+(N46*$N$1)+(Q46*$Q$1)+(T46*$T$1),"") -> 432 | Y46: =IF(E46<>"",IF(X46<(AE46*$AE$1),(AE46*$AE$1),X46),"") -> 1265 | AA46: 1 | AB46: 1 | AC46: 13170 | AD46: =SUMPRODUCT(Z46:AB46,$Z$1:$AB$1) -> 575 | AE46: 2.75 | AF46: 6.75 | AG46: =Table3[[#This Row],[Active hours (Other than drilling)]]*$AF$1 -> 3105 | AH46: 2.5 | AJ46: {=SUM(Table3[[#This Row],[Inactive Hours (Other than client standby)]:[Standby Total Hours]]*$AI$1)} -> 900 | AM46: =IF(ISBLANK(AE46),"",SUM(AE46:AF46,AH46:AI46,AK46:AL46)) -> 12 | AN46: =(AF46*$AF$1)+(AH46*$AH$1)+(AI46*$AI$1) -> 4005 | AO46: 390 | AQ46: =SUM(Y46,AN46,AP46,H46)+AD46 -> 6235 | AR46: 6235 | AS46: =SUM($AQ$6:AQ46) -> 234082.75 | AT46: =_xlfn.TEXTJOIN(,TRUE,"0",MONTH(C46)) -> 07 | AU46: =DAY(C46) -> 26 | AV46: =LEFT(D46,1) -> D
A47: GT | B47: 1 | C47: =C45+1 -> 45864.71 | D47: NS 5pm | E47: SF25_DDGT005 | G47: 3 | H47: =IF(ISBLANK(G47),"",G47*$H$1) -> 390 | K47: =IF(ISBLANK(I47),0,J47-I47) -> 0 | L47: 2 | M47: 15 | N47: =IF(ISBLANK(L47),,M47-L47) -> 13 | Q47: =IF(ISBLANK(O47),,P47-O47) -> 0 | T47: =IF(ISBLANK(R47),,S47-R47) -> 0 | U47: =SUM(K47,Q47) -> 0 | V47: =SUM(N47,T47) -> 13 | W47: =IFERROR(K47+N47+Q47+T47,"") -> 13 | X47: =IFERROR((K47*$K$1)+(N47*$N$1)+(Q47*$Q$1)+(T47*$T$1),"") -> 1755 | Y47: =IF(E47<>"",IF(X47<(AE47*$AE$1),(AE47*$AE$1),X47),"") -> 2300 | AD47: =SUMPRODUCT(Z47:AB47,$Z$1:$AB$1) -> 0 | AE47: 5 | AF47: 2.5 | AG47: =Table3[[#This Row],[Active hours (Other than drilling)]]*$AF$1 -> 1150 | AH47: 4.5 | AJ47: {=SUM(Table3[[#This Row],[Inactive Hours (Other than client standby)]:[Standby Total Hours]]*$AI$1)} -> 1620 | AM47: =IF(ISBLANK(AE47),"",SUM(AE47:AF47,AH47:AI47,AK47:AL47)) -> 12 | AN47: =(AF47*$AF$1)+(AH47*$AH$1)+(AI47*$AI$1) -> 2770 | AO47: 390 | AQ47: =SUM(Y47,AN47,AP47,H47)+AD47 -> 5460 | AR47: 5460 | AS47: =SUM($AQ$6:AQ47) -> 239542.75 | AT47: =_xlfn.TEXTJOIN(,TRUE,"0",MONTH(C47)) -> 07 | AU47: =DAY(C47) -> 26 | AV47: =LEFT(D47,1) -> N
A48: GT | C48: =C46+1 -> 45865.21 | D48: DS 5am | E48: SF25_DDGT011 | G48: 3 | H48: =IF(ISBLANK(G48),"",G48*$H$1) -> 390 | K48: =IF(ISBLANK(I48),0,J48-I48) -> 0 | N48: =IF(ISBLANK(L48),,M48-L48) -> 0 | Q48: =IF(ISBLANK(O48),,P48-O48) -> 0 | T48: =IF(ISBLANK(R48),,S48-R48) -> 0 | U48: =SUM(K48,Q48) -> 0 | V48: =SUM(N48,T48) -> 0 | W48: =IFERROR(K48+N48+Q48+T48,"") -> 0 | X48: =IFERROR((K48*$K$1)+(N48*$N$1)+(Q48*$Q$1)+(T48*$T$1),"") -> 0 | Y48: =IF(E48<>"",IF(X48<(AE48*$AE$1),(AE48*$AE$1),X48),"") -> 0 | AA48: 1 | AB48: 1 | AC48: 13170 | AD48: =SUMPRODUCT(Z48:AB48,$Z$1:$AB$1) -> 575 | AE48: 0 | AF48: 6 | AG48: =Table3[[#This Row],[Active hours (Other than drilling)]]*$AF$1 -> 2760 | AH48: 0.5 | AI48: 5 | AJ48: {=SUM(Table3[[#This Row],[Inactive Hours (Other than client standby)]:[Standby Total Hours]]*$AI$1)} -> 1980 | AK48: 0.5 | AM48: =IF(ISBLANK(AE48),"",SUM(AE48:AF48,AH48:AI48,AK48:AL48)) -> 12 | AN48: =(AF48*$AF$1)+(AH48*$AH$1)+(AI48*$AI$1) -> 4740 | AO48: 390 | AQ48: =SUM(Y48,AN48,AP48,H48)+AD48 -> 5705 | AR48: 5705 | AS48: =SUM($AQ$6:AQ48) -> 245247.75 | AT48: =_xlfn.TEXTJOIN(,TRUE,"0",MONTH(C48)) -> 07 | AU48: =DAY(C48) -> 27 | AV48: =LEFT(D48,1) -> D
A49: GT | C49: =C47+1 -> 45865.71 | D49: NS 5pm | E49: SF25_DDGT011 | G49: 3 | H49: =IF(ISBLANK(G49),"",G49*$H$1) -> 390 | K49: =IF(ISBLANK(I49),0,J49-I49) -> 0 | L49: 0 | M49: 21.3 | N49: =IF(ISBLANK(L49),,M49-L49) -> 21.3 | Q49: =IF(ISBLANK(O49),,P49-O49) -> 0 | T49: =IF(ISBLANK(R49),,S49-R49) -> 0 | U49: =SUM(K49,Q49) -> 0 | V49: =SUM(N49,T49) -> 21.3 | W49: =IFERROR(K49+N49+Q49+T49,"") -> 21.3 | X49: =IFERROR((K49*$K$1)+(N49*$N$1)+(Q49*$Q$1)+(T49*$T$1),"") -> 2875.5 | Y49: =IF(E49<>"",IF(X49<(AE49*$AE$1),(AE49*$AE$1),X49),"") -> 3335 | AD49: =SUMPRODUCT(Z49:AB49,$Z$1:$AB$1) -> 0 | AE49: 7.25 | AF49: 3.75 | AG49: =Table3[[#This Row],[Active hours (Other than drilling)]]*$AF$1 -> 1725 | AH49: 0.5 | AJ49: {=SUM(Table3[[#This Row],[Inactive Hours (Other than client standby)]:[Standby Total Hours]]*$AI$1)} -> 180 | AK49: 0.5 | AM49: =IF(ISBLANK(AE49),"",SUM(AE49:AF49,AH49:AI49,AK49:AL49)) -> 12 | AN49: =(AF49*$AF$1)+(AH49*$AH$1)+(AI49*$AI$1) -> 1905 | AO49: =AP49+H49 -> 1076.61 | AP49: 686.61 | AQ49: =SUM(Y49,AN49,AP49,H49)+AD49 -> 6316.61 | AR49: 6316.61 | AS49: =SUM($AQ$6:AQ49) -> 251564.36 | AT49: =_xlfn.TEXTJOIN(,TRUE,"0",MONTH(C49)) -> 07 | AU49: =DAY(C49) -> 27 | AV49: =LEFT(D49,1) -> N
A50: GT | C50: =C48+1 -> 45866.21 | D50: DS 5am | E50: SF25_DDGT011 | G50: 3 | H50: =IF(ISBLANK(G50),"",G50*$H$1) -> 390 | K50: =IF(ISBLANK(I50),0,J50-I50) -> 0 | L50: 21.3 | M50: 51.7 | N50: =IF(ISBLANK(L50),,M50-L50) -> 30.4 | Q50: =IF(ISBLANK(O50),,P50-O50) -> 0 | T50: =IF(ISBLANK(R50),,S50-R50) -> 0 | U50: =SUM(K50,Q50) -> 0 | V50: =SUM(N50,T50) -> 30.4 | W50: =IFERROR(K50+N50+Q50+T50,"") -> 30.4 | X50: =IFERROR((K50*$K$1)+(N50*$N$1)+(Q50*$Q$1)+(T50*$T$1),"") -> 4104 | Y50: =IF(E50<>"",IF(X50<(AE50*$AE$1),(AE50*$AE$1),X50),"") -> 5060 | AA50: 1 | AB50: 1 | AC50: 13170 | AD50: =SUMPRODUCT(Z50:AB50,$Z$1:$AB$1) -> 575 | AE50: 11 | AF50: 0.5 | AG50: =Table3[[#This Row],[Active hours (Other than drilling)]]*$AF$1 -> 230 | AH50: 0.5 | AJ50: {=SUM(Table3[[#This Row],[Inactive Hours (Other than client standby)]:[Standby Total Hours]]*$AI$1)} -> 180 | AM50: =IF(ISBLANK(AE50),"",SUM(AE50:AF50,AH50:AI50,AK50:AL50)) -> 12 | AN50: =(AF50*$AF$1)+(AH50*$AH$1)+(AI50*$AI$1) -> 410 | AO50: =AP50+H50 -> 390 | AQ50: =SUM(Y50,AN50,AP50,H50)+AD50 -> 6435 | AR50: 6435 | AS50: =SUM($AQ$6:AQ50) -> 257999.36 | AT50: =_xlfn.TEXTJOIN(,TRUE,"0",MONTH(C50)) -> 07 | AU50: =DAY(C50) -> 28 | AV50: =LEFT(D50,1) -> D
A51: GT | C51: =C49+1 -> 45866.71 | D51: NS 5pm | E51: SF25_DDGT011 | G51: 3 | H51: =IF(ISBLANK(G51),"",G51*$H$1) -> 390 | K51: =IF(ISBLANK(I51),0,J51-I51) -> 0 | L51: 51.7 | M51: 78.7 | N51: =IF(ISBLANK(L51),,M51-L51) -> 27 | Q51: =IF(ISBLANK(O51),,P51-O51) -> 0 | T51: =IF(ISBLANK(R51),,S51-R51) -> 0 | U51: =SUM(K51,Q51) -> 0 | V51: =SUM(N51,T51) -> 27 | W51: =IFERROR(K51+N51+Q51+T51,"") -> 27 | X51: =IFERROR((K51*$K$1)+(N51*$N$1)+(Q51*$Q$1)+(T51*$T$1),"") -> 3645 | Y51: =IF(E51<>"",IF(X51<(AE51*$AE$1),(AE51*$AE$1),X51),"") -> 4945 | AD51: =SUMPRODUCT(Z51:AB51,$Z$1:$AB$1) -> 0 | AE51: 10.75 | AF51: 0.25 | AG51: =Table3[[#This Row],[Active hours (Other than drilling)]]*$AF$1 -> 115 | AH51: 0.5 | AJ51: {=SUM(Table3[[#This Row],[Inactive Hours (Other than client standby)]:[Standby Total Hours]]*$AI$1)} -> 180 | AL51: 0.5 | AM51: =IF(ISBLANK(AE51),"",SUM(AE51:AF51,AH51:AI51,AK51:AL51)) -> 12 | AN51: =(AF51*$AF$1)+(AH51*$AH$1)+(AI51*$AI$1) -> 295 | AO51: =AP51+H51 -> 390 | AQ51: =SUM(Y51,AN51,AP51,H51)+AD51 -> 5630 | AR51: 5630 | AS51: =SUM($AQ$6:AQ51) -> 263629.36 | AT51: =_xlfn.TEXTJOIN(,TRUE,"0",MONTH(C51)) -> 07 | AU51: =DAY(C51) -> 28 | AV51: =LEFT(D51,1) -> N
A52: GT | C52: =C50+1 -> 45867.21 | D52: DS 5am | E52: SF25_DDGT011 | G52: 3 | H52: =IF(ISBLANK(G52),"",G52*$H$1) -> 390 | K52: =IF(ISBLANK(I52),0,J52-I52) -> 0 | L52: 78.7 | M52: 92.7 | N52: =IF(ISBLANK(L52),,M52-L52) -> 14 | Q52: =IF(ISBLANK(O52),,P52-O52) -> 0 | T52: =IF(ISBLANK(R52),,S52-R52) -> 0 | U52: =SUM(K52,Q52) -> 0 | V52: =SUM(N52,T52) -> 14 | W52: =IFERROR(K52+N52+Q52+T52,"") -> 14 | X52: =IFERROR((K52*$K$1)+(N52*$N$1)+(Q52*$Q$1)+(T52*$T$1),"") -> 1890 | Y52: =IF(E52<>"",IF(X52<(AE52*$AE$1),(AE52*$AE$1),X52),"") -> 2645 | AA52: 1 | AB52: 1 | AC52: 13170 | AD52: =SUMPRODUCT(Z52:AB52,$Z$1:$AB$1) -> 575 | AE52: 5.75 | AF52: 0.25 | AG52: =Table3[[#This Row],[Active hours (Other than drilling)]]*$AF$1 -> 115 | AH52: 0.5 | AJ52: {=SUM(Table3[[#This Row],[Inactive Hours (Other than client standby)]:[Standby Total Hours]]*$AI$1)} -> 180 | AL52: 5.5 | AM52: =IF(ISBLANK(AE52),"",SUM(AE52:AF52,AH52:AI52,AK52:AL52)) -> 12 | AN52: =(AF52*$AF$1)+(AH52*$AH$1)+(AI52*$AI$1) -> 295 | AO52: =AP52+H52 -> 390 | AQ52: =SUM(Y52,AN52,AP52,H52)+AD52 -> 3905 | AR52: 3905 | AS52: =SUM($AQ$6:AQ52) -> 267534.36 | AT52: =_xlfn.TEXTJOIN(,TRUE,"0",MONTH(C52)) -> 07 | AU52: =DAY(C52) -> 29 | AV52: =LEFT(D52,1) -> D
A53: GT | C53: =C51+1 -> 45867.71 | D53: NS 5pm | E53: SF25_DDGT011 | G53: 3 | H53: =IF(ISBLANK(G53),"",G53*$H$1) -> 390 | K53: =IF(ISBLANK(I53),0,J53-I53) -> 0 | L53: 92.7 | M53: 107.7 | N53: =IF(ISBLANK(L53),,M53-L53) -> 15 | Q53: =IF(ISBLANK(O53),,P53-O53) -> 0 | T53: =IF(ISBLANK(R53),,S53-R53) -> 0 | U53: =SUM(K53,Q53) -> 0 | V53: =SUM(N53,T53) -> 15 | W53: =IFERROR(K53+N53+Q53+T53,"") -> 15 | X53: =IFERROR((K53*$K$1)+(N53*$N$1)+(Q53*$Q$1)+(T53*$T$1),"") -> 2025 | Y53: =IF(E53<>"",IF(X53<(AE53*$AE$1),(AE53*$AE$1),X53),"") -> 3680 | AD53: =SUMPRODUCT(Z53:AB53,$Z$1:$AB$1) -> 0 | AE53: 8 | AF53: 0.5 | AG53: =Table3[[#This Row],[Active hours (Other than drilling)]]*$AF$1 -> 230 | AH53: 0.5 | AJ53: {=SUM(Table3[[#This Row],[Inactive Hours (Other than client standby)]:[Standby Total Hours]]*$AI$1)} -> 180 | AL53: 3 | AM53: =IF(ISBLANK(AE53),"",SUM(AE53:AF53,AH53:AI53,AK53:AL53)) -> 12 | AN53: =(AF53*$AF$1)+(AH53*$AH$1)+(AI53*$AI$1) -> 410 | AO53: =AP53+H53 -> 527.5 | AP53: 137.5 | AQ53: =SUM(Y53,AN53,AP53,H53)+AD53 -> 4617.5 | AR53: 4617.5 | AS53: =SUM($AQ$6:AQ53) -> 272151.86 | AT53: =_xlfn.TEXTJOIN(,TRUE,"0",MONTH(C53)) -> 07 | AU53: =DAY(C53) -> 29 | AV53: =LEFT(D53,1) -> N
A54: GT | B54: 1 | C54: =C52+1 -> 45868.21 | D54: DS 5am | E54: SF25_DDGT011 | G54: 3 | H54: =IF(ISBLANK(G54),"",G54*$H$1) -> 390 | K54: =IF(ISBLANK(I54),0,J54-I54) -> 0 | L54: 107.7 | M54: 130 | N54: =IF(ISBLANK(L54),,M54-L54) -> 22.3 | Q54: =IF(ISBLANK(O54),,P54-O54) -> 0 | T54: =IF(ISBLANK(R54),,S54-R54) -> 0 | U54: =SUM(K54,Q54) -> 0 | V54: =SUM(N54,T54) -> 22.3 | W54: =IFERROR(K54+N54+Q54+T54,"") -> 22.3 | X54: =IFERROR((K54*$K$1)+(N54*$N$1)+(Q54*$Q$1)+(T54*$T$1),"") -> 3010.5 | Y54: =IF(E54<>"",IF(X54<(AE54*$AE$1),(AE54*$AE$1),X54),"") -> 4370 | AA54: 1 | AB54: 1 | AC54: 13170 | AD54: =SUMPRODUCT(Z54:AB54,$Z$1:$AB$1) -> 575 | AE54: 9.5 | AF54: 1.5 | AG54: =Table3[[#This Row],[Active hours (Other than drilling)]]*$AF$1 -> 690 | AH54: 1 | AJ54: {=SUM(Table3[[#This Row],[Inactive Hours (Other than client standby)]:[Standby Total Hours]]*$AI$1)} -> 360 | AM54: =IF(ISBLANK(AE54),"",SUM(AE54:AF54,AH54:AI54,AK54:AL54)) -> 12 | AN54: =(AF54*$AF$1)+(AH54*$AH$1)+(AI54*$AI$1) -> 1050 | AO54: =AP54+H54 -> 390 | AQ54: =SUM(Y54,AN54,AP54,H54)+AD54 -> 6385 | AR54: 6385 | AS54: =SUM($AQ$6:AQ54) -> 278536.86 | AT54: =_xlfn.TEXTJOIN(,TRUE,"0",MONTH(C54)) -> 07 | AU54: =DAY(C54) -> 30 | AV54: =LEFT(D54,1) -> D
A55: GT | B55: 1 | C55: =C53+1 -> 45868.71 | D55: NS 5pm | E55: SF25_DDGT011 | F55: SF25_DDGT002 | G55: 3 | H55: =IF(ISBLANK(G55),"",G55*$H$1) -> 390 | K55: =IF(ISBLANK(I55),0,J55-I55) -> 0 | L55: 0 | M55: 1.7 | N55: =IF(ISBLANK(L55),,M55-L55) -> 1.7 | Q55: =IF(ISBLANK(O55),,P55-O55) -> 0 | T55: =IF(ISBLANK(R55),,S55-R55) -> 0 | U55: =SUM(K55,Q55) -> 0 | V55: =SUM(N55,T55) -> 1.7 | W55: =IFERROR(K55+N55+Q55+T55,"") -> 1.7 | X55: =IFERROR((K55*$K$1)+(N55*$N$1)+(Q55*$Q$1)+(T55*$T$1),"") -> 229.5 | Y55: =IF(E55<>"",IF(X55<(AE55*$AE$1),(AE55*$AE$1),X55),"") -> 345 | AD55: =SUMPRODUCT(Z55:AB55,$Z$1:$AB$1) -> 0 | AE55: 0.75 | AF55: 6.5 | AG55: =Table3[[#This Row],[Active hours (Other than drilling)]]*$AF$1 -> 2990 | AH55: 4.75 | AJ55: {=SUM(Table3[[#This Row],[Inactive Hours (Other than client standby)]:[Standby Total Hours]]*$AI$1)} -> 1710 | AM55: =IF(ISBLANK(AE55),"",SUM(AE55:AF55,AH55:AI55,AK55:AL55)) -> 12 | AN55: =(AF55*$AF$1)+(AH55*$AH$1)+(AI55*$AI$1) -> 4700 | AO55: =AP55+H55 -> 390 | AQ55: =SUM(Y55,AN55,AP55,H55)+AD55 -> 5435 | AR55: 5435 | AS55: =SUM($AQ$6:AQ55) -> 283971.86 | AT55: =_xlfn.TEXTJOIN(,TRUE,"0",MONTH(C55)) -> 07 | AU55: =DAY(C55) -> 30 | AV55: =LEFT(D55,1) -> N
A56: GT | B56: 1 | C56: =C54+1 -> 45869.21 | D56: DS 5am | E56: SF25_DDGT006 | G56: 3 | H56: =IF(ISBLANK(G56),"",G56*$H$1) -> 390 | I56: 0 | J56: 6.4 | K56: =IF(ISBLANK(I56),0,J56-I56) -> 6.4 | N56: =IF(ISBLANK(L56),,M56-L56) -> 0 | Q56: =IF(ISBLANK(O56),,P56-O56) -> 0 | T56: =IF(ISBLANK(R56),,S56-R56) -> 0 | U56: =SUM(K56,Q56) -> 6.4 | V56: =SUM(N56,T56) -> 0 | W56: =IFERROR(K56+N56+Q56+T56,"") -> 6.4 | X56: =IFERROR((K56*$K$1)+(N56*$N$1)+(Q56*$Q$1)+(T56*$T$1),"") -> 1120 | Y56: =IF(E56<>"",IF(X56<(AE56*$AE$1),(AE56*$AE$1),X56),"") -> 1840 | AA56: 1 | AB56: 1 | AC56: 13170 | AD56: =SUMPRODUCT(Z56:AB56,$Z$1:$AB$1) -> 575 | AE56: 4 | AF56: 4.5 | AG56: =Table3[[#This Row],[Active hours (Other than drilling)]]*$AF$1 -> 2070 | AH56: 3.5 | AJ56: {=SUM(Table3[[#This Row],[Inactive Hours (Other than client standby)]:[Standby Total Hours]]*$AI$1)} -> 1260 | AM56: =IF(ISBLANK(AE56),"",SUM(AE56:AF56,AH56:AI56,AK56:AL56)) -> 12 | AN56: =(AF56*$AF$1)+(AH56*$AH$1)+(AI56*$AI$1) -> 3330 | AO56: =AP56+H56 -> 390 | AQ56: =SUM(Y56,AN56,AP56,H56)+AD56 -> 6135 | AR56: 6135 | AS56: =SUM($AQ$6:AQ56) -> 290106.86 | AT56: =_xlfn.TEXTJOIN(,TRUE,"0",MONTH(C56)) -> 07 | AU56: =DAY(C56) -> 31 | AV56: =LEFT(D56,1) -> D
A57: =IFERROR(IF(FIND("MET",E57),"MET",IF(FIND("GT",E57),"GT",)),"") -> MET | C57: =C55+1 -> 45869.71 | D57: NS 5pm | E57: SF25_DMET018 | G57: 3 | H57: =IF(ISBLANK(G57),"",G57*$H$1) -> 390 | I57: 1.2 | J57: 15.5 | K57: =IF(ISBLANK(I57),0,J57-I57) -> 14.3 | N57: =IF(ISBLANK(L57),,M57-L57) -> 0 | Q57: =IF(ISBLANK(O57),,P57-O57) -> 0 | T57: =IF(ISBLANK(R57),,S57-R57) -> 0 | U57: =SUM(K57,Q57) -> 14.3 | V57: =SUM(N57,T57) -> 0 | W57: =IFERROR(K57+N57+Q57+T57,"") -> 14.3 | X57: =IFERROR((K57*$K$1)+(N57*$N$1)+(Q57*$Q$1)+(T57*$T$1),"") -> 2502.5 | Y57: =IF(E57<>"",IF(X57<(AE57*$AE$1),(AE57*$AE$1),X57),"") -> 4255 | AD57: =SUMPRODUCT(Z57:AB57,$Z$1:$AB$1) -> 0 | AE57: 9.25 | AF57: 2.25 | AG57: =Table3[[#This Row],[Active hours (Other than drilling)]]*$AF$1 -> 1035 | AH57: 0.5 | AJ57: {=SUM(Table3[[#This Row],[Inactive Hours (Other than client standby)]:[Standby Total Hours]]*$AI$1)} -> 180 | AM57: =IF(ISBLANK(AE57),"",SUM(AE57:AF57,AH57:AI57,AK57:AL57)) -> 12 | AN57: =(AF57*$AF$1)+(AH57*$AH$1)+(AI57*$AI$1) -> 1215 | AO57: =14376.12 -> 14376.12 | AP57: =AO57-H57 -> 13986.12 | AQ57: =SUM(Y57,AN57,AP57,H57)+AD57 -> 19846.12 | AR57: 19846.12 | AS57: =SUM($AQ$6:AQ57) -> 309952.98 | AT57: =_xlfn.TEXTJOIN(,TRUE,"0",MONTH(C57)) -> 07 | AU57: =DAY(C57) -> 31 | AV57: =LEFT(D57,1) -> N
A58: =IFERROR(IF(FIND("MET",E58),"MET",IF(FIND("GT",E58),"GT",)),"") -> MET | C58: =C56+1 -> 45870.21 | D58: DS 5am | E58: SF25_DMET018 | G58: 3 | H58: =IF(ISBLANK(G58),"",G58*$H$1) -> 390 | I58: 15.5 | J58: 45.5 | K58: =IF(ISBLANK(I58),0,J58-I58) -> 30 | N58: =IF(ISBLANK(L58),,M58-L58) -> 0 | Q58: =IF(ISBLANK(O58),,P58-O58) -> 0 | T58: =IF(ISBLANK(R58),,S58-R58) -> 0 | U58: =SUM(K58,Q58) -> 30 | V58: =SUM(N58,T58) -> 0 | W58: =IFERROR(K58+N58+Q58+T58,"") -> 30 | X58: =IFERROR((K58*$K$1)+(N58*$N$1)+(Q58*$Q$1)+(T58*$T$1),"") -> 5250 | Y58: =IF(E58<>"",IF(X58<(AE58*$AE$1),(AE58*$AE$1),X58),"") -> 5250 | Z58: 1 | AA58: 1 | AB58: 1 | AC58: 13170 | AD58: =SUMPRODUCT(Z58:AB58,$Z$1:$AB$1) -> 750 | AE58: 11 | AF58: 0.5 | AG58: =Table3[[#This Row],[Active hours (Other than drilling)]]*$AF$1 -> 230 | AH58: 0.5 | AJ58: {=SUM(Table3[[#This Row],[Inactive Hours (Other than client standby)]:[Standby Total Hours]]*$AI55)} -> 0 | AM58: =IF(ISBLANK(AE58),"",SUM(AE58:AF58,AH58:AI58,AK58:AL58)) -> 12 | AN58: =(AF58*$AF$1)+(AH58*$AH$1)+(AI58*$AI$1) -> 410 | AO58: =AP58+H58 -> 390 | AQ58: =SUM(Y58,AN58,AP58,H58)+AD58 -> 6800 | AR58: 6800 | AS58: =SUM($AQ$6:AQ58) -> 316752.98 | AT58: =_xlfn.TEXTJOIN(,TRUE,"0",MONTH(C58)) -> 08 | AU58: =DAY(C58) -> 1 | AV58: =LEFT(D58,1) -> D
A59: =IFERROR(IF(FIND("MET",E59),"MET",IF(FIND("GT",E59),"GT",)),"") -> MET | B59: 1 | C59: =C57+1 -> 45870.71 | D59: NS 5pm | E59: SF25_DMET018 | G59: 3 | H59: =IF(ISBLANK(G59),"",G59*$H$1) -> 390 | I59: 45.5 | J59: 50 | K59: =IF(ISBLANK(I59),0,J59-I59) -> 4.5 | N59: =IF(ISBLANK(L59),,M59-L59) -> 0 | Q59: =IF(ISBLANK(O59),,P59-O59) -> 0 | T59: =IF(ISBLANK(R59),,S59-R59) -> 0 | U59: =SUM(K59,Q59) -> 4.5 | V59: =SUM(N59,T59) -> 0 | W59: =IFERROR(K59+N59+Q59+T59,"") -> 4.5 | X59: =IFERROR((K59*$K$1)+(N59*$N$1)+(Q59*$Q$1)+(T59*$T$1),"") -> 787.5 | Y59: =IF(E59<>"",IF(X59<(AE59*$AE$1),(AE59*$AE$1),X59),"") -> 920 | AD59: =SUMPRODUCT(Z59:AB59,$Z$1:$AB$1) -> 0 | AE59: 2 | AF59: 9.5 | AG59: =Table3[[#This Row],[Active hours (Other than drilling)]]*$AF$1 -> 4370 | AH59: 0.5 | AJ59: {=SUM(Table3[[#This Row],[Inactive Hours (Other than client standby)]:[Standby Total Hours]]*$AI56)} -> 0 | AM59: =IF(ISBLANK(AE59),"",SUM(AE59:AF59,AH59:AI59,AK59:AL59)) -> 12 | AN59: =(AF59*$AF$1)+(AH59*$AH$1)+(AI59*$AI$1) -> 4550 | AO59: =AP59+H59 -> 390 | AQ59: =SUM(Y59,AN59,AP59,H59)+AD59 -> 5860 | AR59: 5860 | AS59: =SUM($AQ$6:AQ59) -> 322612.98 | AT59: =_xlfn.TEXTJOIN(,TRUE,"0",MONTH(C59)) -> 08 | AU59: =DAY(C59) -> 1 | AV59: =LEFT(D59,1) -> N
A60: GT | C60: =C58+1 -> 45871.21 | D60: DS 5am | E60: SF25_DDGT010 | G60: 3 | H60: =IF(ISBLANK(G60),"",G60*$H$1) -> 390 | K60: =IF(ISBLANK(I60),0,J60-I60) -> 0 | L60: 0 | M60: 15.7 | N60: =IF(ISBLANK(L60),,M60-L60) -> 15.7 | Q60: =IF(ISBLANK(O60),,P60-O60) -> 0 | T60: =IF(ISBLANK(R60),,S60-R60) -> 0 | U60: =SUM(K60,Q60) -> 0 | V60: =SUM(N60,T60) -> 15.7 | W60: =IFERROR(K60+N60+Q60+T60,"") -> 15.7 | X60: =IFERROR((K60*$K$1)+(N60*$N$1)+(Q60*$Q$1)+(T60*$T$1),"") -> 2119.5 | Y60: =IF(E60<>"",IF(X60<(AE60*$AE$1),(AE60*$AE$1),X60),"") -> 2990 | Z60: 1 | AA60: 1 | AB60: 1 | AC60: 13170 | AD60: =SUMPRODUCT(Z60:AB60,$Z$1:$AB$1) -> 750 | AE60: 6.5 | AF60: 2 | AG60: =Table3[[#This Row],[Active hours (Other than drilling)]]*$AF$1 -> 920 | AH60: 1.5 | AI60: 2 | AJ60: {=SUM(Table3[[#This Row],[Inactive Hours (Other than client standby)]:[Standby Total Hours]]*$AI57)} -> 0 | AM60: =IF(ISBLANK(AE60),"",SUM(AE60:AF60,AH60:AI60,AK60:AL60)) -> 12 | AN60: =(AF60*$AF$1)+(AH60*$AH$1)+(AI60*$AI$1) -> 2180 | AO60: 880.7 | AP60: =AO60-H60 -> 490.7 | AQ60: =SUM(Y60,AN60,AP60,H60)+AD60 -> 6800.7 | AR60: 6800.7 | AS60: =SUM($AQ$6:AQ60) -> 329413.68 | AT60: =_xlfn.TEXTJOIN(,TRUE,"0",MONTH(C60)) -> 08 | AU60: =DAY(C60) -> 2 | AV60: =LEFT(D60,1) -> D
A61: GT | C61: =C59+1 -> 45871.71 | D61: NS 5pm | E61: SF25_DDGT010 | G61: 3 | H61: =IF(ISBLANK(G61),"",G61*$H$1) -> 390 | K61: =IF(ISBLANK(I61),0,J61-I61) -> 0 | L61: 15.7 | M61: 45.7 | N61: =IF(ISBLANK(L61),,M61-L61) -> 30 | Q61: =IF(ISBLANK(O61),,P61-O61) -> 0 | T61: =IF(ISBLANK(R61),,S61-R61) -> 0 | U61: =SUM(K61,Q61) -> 0 | V61: =SUM(N61,T61) -> 30 | W61: =IFERROR(K61+N61+Q61+T61,"") -> 30 | X61: =IFERROR((K61*$K$1)+(N61*$N$1)+(Q61*$Q$1)+(T61*$T$1),"") -> 4050 | Y61: =IF(E61<>"",IF(X61<(AE61*$AE$1),(AE61*$AE$1),X61),"") -> 4945 | AD61: =SUMPRODUCT(Z61:AB61,$Z$1:$AB$1) -> 0 | AE61: 10.75 | AF61: 0.75 | AG61: =Table3[[#This Row],[Active hours (Other than drilling)]]*$AF$1 -> 345 | AH61: 0.5 | AJ61: {=SUM(Table3[[#This Row],[Inactive Hours (Other than client standby)]:[Standby Total Hours]]*$AI58)} -> 0 | AM61: =IF(ISBLANK(AE61),"",SUM(AE61:AF61,AH61:AI61,AK61:AL61)) -> 12 | AN61: =(AF61*$AF$1)+(AH61*$AH$1)+(AI61*$AI$1) -> 525 | AO61: 390 | AP61: =AO61-H61 -> 0 | AQ61: =SUM(Y61,AN61,AP61,H61)+AD61 -> 5860 | AR61: 5860 | AS61: =SUM($AQ$6:AQ61) -> 335273.68 | AT61: =_xlfn.TEXTJOIN(,TRUE,"0",MONTH(C61)) -> 08 | AU61: =DAY(C61) -> 2 | AV61: =LEFT(D61,1) -> N
A62: GT | C62: =C60+1 -> 45872.21 | D62: DS 5am | E62: SF25_DDGT010 | G62: 3 | H62: =IF(ISBLANK(G62),"",G62*$H$1) -> 390 | K62: =IF(ISBLANK(I62),0,J62-I62) -> 0 | L62: 45.7 | M62: 75.5 | N62: =IF(ISBLANK(L62),,M62-L62) -> 29.8 | Q62: =IF(ISBLANK(O62),,P62-O62) -> 0 | T62: =IF(ISBLANK(R62),,S62-R62) -> 0 | U62: =SUM(K62,Q62) -> 0 | V62: =SUM(N62,T62) -> 29.8 | W62: =IFERROR(K62+N62+Q62+T62,"") -> 29.8 | X62: =IFERROR((K62*$K$1)+(N62*$N$1)+(Q62*$Q$1)+(T62*$T$1),"") -> 4023 | Y62: =IF(E62<>"",IF(X62<(AE62*$AE$1),(AE62*$AE$1),X62),"") -> 5060 | Z62: 1 | AA62: 1 | AB62: 1 | AC62: 13170 | AD62: =SUMPRODUCT(Z62:AB62,$Z$1:$AB$1) -> 750 | AE62: 11 | AF62: 0.5 | AG62: =Table3[[#This Row],[Active hours (Other than drilling)]]*$AF$1 -> 230 | AH62: 0.5 | AJ62: {=SUM(Table3[[#This Row],[Inactive Hours (Other than client standby)]:[Standby Total Hours]]*$AI59)} -> 0 | AM62: =IF(ISBLANK(AE62),"",SUM(AE62:AF62,AH62:AI62,AK62:AL62)) -> 12 | AN62: =(AF62*$AF$1)+(AH62*$AH$1)+(AI62*$AI$1) -> 410 | AO62: 390 | AP62: =AO62-H62 -> 0 | AQ62: =SUM(Y62,AN62,AP62,H62)+AD62 -> 6610 | AR62: 6610 | AS62: =SUM($AQ$6:AQ62) -> 341883.68 | AT62: =_xlfn.TEXTJOIN(,TRUE,"0",MONTH(C62)) -> 08 | AU62: =DAY(C62) -> 3 | AV62: =LEFT(D62,1) -> D
A63: GT | C63: =C61+1 -> 45872.71 | D63: NS 5pm | E63: SF25_DDGT010 | G63: 3 | H63: =IF(ISBLANK(G63),"",G63*$H$1) -> 390 | K63: =IF(ISBLANK(I63),0,J63-I63) -> 0 | L63: 75.5 | M63: 105.7 | N63: =IF(ISBLANK(L63),,M63-L63) -> 30.2 | Q63: =IF(ISBLANK(O63),,P63-O63) -> 0 | T63: =IF(ISBLANK(R63),,S63-R63) -> 0 | U63: =SUM(K63,Q63) -> 0 | V63: =SUM(N63,T63) -> 30.2 | W63: =IFERROR(K63+N63+Q63+T63,"") -> 30.2 | X63: =IFERROR((K63*$K$1)+(N63*$N$1)+(Q63*$Q$1)+(T63*$T$1),"") -> 4077 | Y63: =IF(E63<>"",IF(X63<(AE63*$AE$1),(AE63*$AE$1),X63),"") -> 4945 | AD63: =SUMPRODUCT(Z63:AB63,$Z$1:$AB$1) -> 0 | AE63: 10.75 | AF63: 0.25 | AG63: =Table3[[#This Row],[Active hours (Other than drilling)]]*$AF$1 -> 115 | AH63: 0.5 | AJ63: {=SUM(Table3[[#This Row],[Inactive Hours (Other than client standby)]:[Standby Total Hours]]*$AI60)} -> 1 | AK63: 0.5 | AM63: =IF(ISBLANK(AE63),"",SUM(AE63:AF63,AH63:AI63,AK63:AL63)) -> 12 | AN63: =(AF63*$AF$1)+(AH63*$AH$1)+(AI63*$AI$1) -> 295 | AO63: 390 | AP63: =AO63-H63 -> 0 | AQ63: =SUM(Y63,AN63,AP63,H63)+AD63 -> 5630 | AR63: 5630 | AS63: =SUM($AQ$6:AQ63) -> 347513.68 | AT63: =_xlfn.TEXTJOIN(,TRUE,"0",MONTH(C63)) -> 08 | AU63: =DAY(C63) -> 3 | AV63: =LEFT(D63,1) -> N
A64: GT | B64: 1 | C64: =C62+1 -> 45873.21 | D64: DS 5am | E64: SF25_DDGT010 | F64: SF25_DMET017 | G64: 3 | H64: =IF(ISBLANK(G64),"",G64*$H$1) -> 390 | K64: =IF(ISBLANK(I64),0,J64-I64) -> 0 | L64: 105.7 | M64: 110 | N64: =IF(ISBLANK(L64),,M64-L64) -> 4.3 | O64: 0 | P64: 0 | Q64: =IF(ISBLANK(O64),,P64-O64) -> 0 | T64: =IF(ISBLANK(R64),,S64-R64) -> 0 | U64: =SUM(K64,Q64) -> 0 | V64: =SUM(N64,T64) -> 4.3 | W64: =IFERROR(K64+N64+Q64+T64,"") -> 4.3 | X64: =IFERROR((K64*$K$1)+(N64*$N$1)+(Q64*$Q$1)+(T64*$T$1),"") -> 580.5 | Y64: =IF(E64<>"",IF(X64<(AE64*$AE$1),(AE64*$AE$1),X64),"") -> 1840 | Z64: 1 | AA64: 1 | AB64: 1 | AC64: 13170 | AD64: =SUMPRODUCT(Z64:AB64,$Z$1:$AB$1) -> 750 | AE64: 4 | AF64: 6.5 | AG64: =Table3[[#This Row],[Active hours (Other than drilling)]]*$AF$1 -> 2990 | AH64: 0.5 | AI64: 1 | AJ64: {=SUM(Table3[[#This Row],[Inactive Hours (Other than client standby)]:[Standby Total Hours]]*$AI61)} -> 0 | AM64: =IF(ISBLANK(AE64),"",SUM(AE64:AF64,AH64:AI64,AK64:AL64)) -> 12 | AN64: =(AF64*$AF$1)+(AH64*$AH$1)+(AI64*$AI$1) -> 3530 | AO64: 390 | AP64: =AO64-H64 -> 0 | AQ64: =SUM(Y64,AN64,AP64,H64)+AD64 -> 6510 | AR64: 6510 | AS64: =SUM($AQ$6:AQ64) -> 354023.68 | AT64: =_xlfn.TEXTJOIN(,TRUE,"0",MONTH(C64)) -> 08 | AU64: =DAY(C64) -> 4 | AV64: =LEFT(D64,1) -> D
A65: MET | C65: =C63+1 -> 45873.71 | D65: NS 5pm | E65: SF25_DMET017 | G65: 3 | H65: =IF(ISBLANK(G65),"",G65*$H$1) -> 390 | I65: 0 | J65: 17.8 | K65: =IF(ISBLANK(I65),0,J65-I65) -> 17.8 | N65: =IF(ISBLANK(L65),,M65-L65) -> 0 | Q65: =IF(ISBLANK(O65),,P65-O65) -> 0 | T65: =IF(ISBLANK(R65),,S65-R65) -> 0 | U65: =SUM(K65,Q65) -> 17.8 | V65: =SUM(N65,T65) -> 0 | W65: =IFERROR(K65+N65+Q65+T65,"") -> 17.8 | X65: =IFERROR((K65*$K$1)+(N65*$N$1)+(Q65*$Q$1)+(T65*$T$1),"") -> 3115 | Y65: =IF(E65<>"",IF(X65<(AE65*$AE$1),(AE65*$AE$1),X65),"") -> 3680 | AD65: =SUMPRODUCT(Z65:AB65,$Z$1:$AB$1) -> 0 | AE65: 8 | AF65: 3.5 | AG65: =Table3[[#This Row],[Active hours (Other than drilling)]]*$AF$1 -> 1610 | AH65: 0.5 | AJ65: {=SUM(Table3[[#This Row],[Inactive Hours (Other than client standby)]:[Standby Total Hours]]*$AI62)} -> 0 | AM65: =IF(ISBLANK(AE65),"",SUM(AE65:AF65,AH65:AI65,AK65:AL65)) -> 12 | AN65: =(AF65*$AF$1)+(AH65*$AH$1)+(AI65*$AI$1) -> 1790 | AO65: 786.12 | AP65: =AO65-H65 -> 396.12 | AQ65: =SUM(Y65,AN65,AP65,H65)+AD65 -> 6256.12 | AR65: 6256.12 | AS65: =SUM($AQ$6:AQ65) -> 360279.8 | AT65: =_xlfn.TEXTJOIN(,TRUE,"0",MONTH(C65)) -> 08 | AU65: =DAY(C65) -> 4 | AV65: =LEFT(D65,1) -> N
A66: MET | B66: 1 | C66: =C64+1 -> 45874.21 | D66: DS 5am | E66: SF25_DMET017 | G66: 3 | H66: =IF(ISBLANK(G66),"",G66*$H$1) -> 390 | I66: 17.8 | J66: 50.1 | K66: =IF(ISBLANK(I66),0,J66-I66) -> 32.3 | N66: =IF(ISBLANK(L66),,M66-L66) -> 0 | Q66: =IF(ISBLANK(O66),,P66-O66) -> 0 | T66: =IF(ISBLANK(R66),,S66-R66) -> 0 | U66: =SUM(K66,Q66) -> 32.3 | V66: =SUM(N66,T66) -> 0 | W66: =IFERROR(K66+N66+Q66+T66,"") -> 32.3 | X66: =IFERROR((K66*$K$1)+(N66*$N$1)+(Q66*$Q$1)+(T66*$T$1),"") -> 5652.5 | Y66: =IF(E66<>"",IF(X66<(AE66*$AE$1),(AE66*$AE$1),X66),"") -> 5652.5 | Z66: 1 | AA66: 1 | AB66: 1 | AC66: 13170 | AD66: =SUMPRODUCT(Z66:AB66,$Z$1:$AB$1) -> 750 | AE66: 10.75 | AF66: 0.75 | AG66: =Table3[[#This Row],[Active hours (Other than drilling)]]*$AF$1 -> 345 | AH66: 0.5 | AJ66: {=SUM(Table3[[#This Row],[Inactive Hours (Other than client standby)]:[Standby Total Hours]]*$AI63)} -> 0 | AM66: =IF(ISBLANK(AE66),"",SUM(AE66:AF66,AH66:AI66,AK66:AL66)) -> 12 | AN66: =(AF66*$AF$1)+(AH66*$AH$1)+(AI66*$AI$1) -> 525 | AO66: 390 | AP66: =AO66-H66 -> 0 | AQ66: =SUM(Y66,AN66,AP66,H66)+AD66 -> 7317.5 | AR66: 7317.5 | AS66: =SUM($AQ$6:AQ66) -> 367597.3 | AT66: =_xlfn.TEXTJOIN(,TRUE,"0",MONTH(C66)) -> 08 | AU66: =DAY(C66) -> 5 | AV66: =LEFT(D66,1) -> D
A67: MET | C67: =C65+1 -> 45874.71 | D67: NS 5pm | E67: SF25_DMET019 | G67: 3 | H67: =IF(ISBLANK(G67),"",G67*$H$1) -> 390 | I67: 0 | J67: 5.7 | K67: =IF(ISBLANK(I67),0,J67-I67) -> 5.7 | N67: =IF(ISBLANK(L67),,M67-L67) -> 0 | Q67: =IF(ISBLANK(O67),,P67-O67) -> 0 | T67: =IF(ISBLANK(R67),,S67-R67) -> 0 | U67: =SUM(K67,Q67) -> 5.7 | V67: =SUM(N67,T67) -> 0 | W67: =IFERROR(K67+N67+Q67+T67,"") -> 5.7 | X67: =IFERROR((K67*$K$1)+(N67*$N$1)+(Q67*$Q$1)+(T67*$T$1),"") -> 997.5 | Y67: =IF(E67<>"",IF(X67<(AE67*$AE$1),(AE67*$AE$1),X67),"") -> 997.5 | AD67: =SUMPRODUCT(Z67:AB67,$Z$1:$AB$1) -> 0 | AE67: 2 | AF67: 6.5 | AG67: =Table3[[#This Row],[Active hours (Other than drilling)]]*$AF$1 -> 2990 | AH67: 1.5 | AJ67: {=SUM(Table3[[#This Row],[Inactive Hours (Other than client standby)]:[Standby Total Hours]]*$AI64)} -> 1.5 | AK67: 2 | AM67: =IF(ISBLANK(AE67),"",SUM(AE67:AF67,AH67:AI67,AK67:AL67)) -> 12 | AN67: =(AF67*$AF$1)+(AH67*$AH$1)+(AI67*$AI$1) -> 3530 | AO67: 390 | AP67: =AO67-H67 -> 0 | AQ67: =SUM(Y67,AN67,AP67,H67)+AD67 -> 4917.5 | AR67: 4917.5 | AS67: =SUM($AQ$6:AQ67) -> 372514.8 | AT67: =_xlfn.TEXTJOIN(,TRUE,"0",MONTH(C67)) -> 08 | AU67: =DAY(C67) -> 5 | AV67: =LEFT(D67,1) -> N
A68: MET | C68: =C66+1 -> 45875.21 | D68: DS 5am | E68: SF25_DMET019 | G68: 3 | H68: =IF(ISBLANK(G68),"",G68*$H$1) -> 390 | I68: 5.7 | J68: 8.4 | K68: =IF(ISBLANK(I68),0,J68-I68) -> 2.7 | N68: =IF(ISBLANK(L68),,M68-L68) -> 0 | Q68: =IF(ISBLANK(O68),,P68-O68) -> 0 | T68: =IF(ISBLANK(R68),,S68-R68) -> 0 | U68: =SUM(K68,Q68) -> 2.7 | V68: =SUM(N68,T68) -> 0 | W68: =IFERROR(K68+N68+Q68+T68,"") -> 2.7 | X68: =IFERROR((K68*$K$1)+(N68*$N$1)+(Q68*$Q$1)+(T68*$T$1),"") -> 472.5 | Y68: =IF(E68<>"",IF(X68<(AE68*$AE$1),(AE68*$AE$1),X68),"") -> 575 | Z68: 1 | AA68: 1 | AB68: 1 | AC68: 13170 | AD68: =SUMPRODUCT(Z68:AB68,$Z$1:$AB$1) -> 750 | AE68: 1.25 | AF68: 1.25 | AG68: =Table3[[#This Row],[Active hours (Other than drilling)]]*$AF$1 -> 575 | AH68: 0.5 | AI68: 1 | AJ68: {=SUM(Table3[[#This Row],[Inactive Hours (Other than client standby)]:[Standby Total Hours]]*$AI65)} -> 0 | AK68: 8 | AM68: =IF(ISBLANK(AE68),"",SUM(AE68:AF68,AH68:AI68,AK68:AL68)) -> 12 | AN68: =(AF68*$AF$1)+(AH68*$AH$1)+(AI68*$AI$1) -> 1115 | AO68: 786.12 | AP68: =AO68-H68 -> 396.12 | AQ68: =SUM(Y68,AN68,AP68,H68)+AD68 -> 3226.12 | AR68: 3226.12 | AS68: =SUM($AQ$6:AQ68) -> 375740.92 | AT68: =_xlfn.TEXTJOIN(,TRUE,"0",MONTH(C68)) -> 08 | AU68: =DAY(C68) -> 6 | AV68: =LEFT(D68,1) -> D
A69: MET | C69: =C67+1 -> 45875.71 | D69: NS 5pm | E69: SF25_DMET019 | G69: 3 | H69: =IF(ISBLANK(G69),"",G69*$H$1) -> 390 | I69: 8.4 | J69: 39.7 | K69: =IF(ISBLANK(I69),0,J69-I69) -> 31.3 | N69: =IF(ISBLANK(L69),,M69-L69) -> 0 | Q69: =IF(ISBLANK(O69),,P69-O69) -> 0 | T69: =IF(ISBLANK(R69),,S69-R69) -> 0 | U69: =SUM(K69,Q69) -> 31.3 | V69: =SUM(N69,T69) -> 0 | W69: =IFERROR(K69+N69+Q69+T69,"") -> 31.3 | X69: =IFERROR((K69*$K$1)+(N69*$N$1)+(Q69*$Q$1)+(T69*$T$1),"") -> 5477.5 | Y69: =IF(E69<>"",IF(X69<(AE69*$AE$1),(AE69*$AE$1),X69),"") -> 5477.5 | AD69: =SUMPRODUCT(Z69:AB69,$Z$1:$AB$1) -> 0 | AE69: 11 | AF69: 0.5 | AG69: =Table3[[#This Row],[Active hours (Other than drilling)]]*$AF$1 -> 230 | AH69: 0.5 | AJ69: {=SUM(Table3[[#This Row],[Inactive Hours (Other than client standby)]:[Standby Total Hours]]*$AI66)} -> 0 | AM69: =IF(ISBLANK(AE69),"",SUM(AE69:AF69,AH69:AI69,AK69:AL69)) -> 12 | AN69: =(AF69*$AF$1)+(AH69*$AH$1)+(AI69*$AI$1) -> 410 | AO69: 390 | AP69: =AO69-H69 -> 0 | AQ69: =SUM(Y69,AN69,AP69,H69)+AD69 -> 6277.5 | AR69: 6277.5 | AS69: =SUM($AQ$6:AQ69) -> 382018.42 | AT69: =_xlfn.TEXTJOIN(,TRUE,"0",MONTH(C69)) -> 08 | AU69: =DAY(C69) -> 6 | AV69: =LEFT(D69,1) -> N
A70: MET | B70: 1 | C70: =C68+1 -> 45876.21 | D70: DS 5am | E70: SF25_DMET019 | F70: SF25_DDRD001 | G70: 3 | H70: =IF(ISBLANK(G70),"",G70*$H$1) -> 390 | I70: 39.7 | J70: 50.4 | K70: =IF(ISBLANK(I70),0,J70-I70) -> 10.7 | N70: =IF(ISBLANK(L70),,M70-L70) -> 0 | Q70: =IF(ISBLANK(O70),,P70-O70) -> 0 | T70: =IF(ISBLANK(R70),,S70-R70) -> 0 | U70: =SUM(K70,Q70) -> 10.7 | V70: =SUM(N70,T70) -> 0 | W70: =IFERROR(K70+N70+Q70+T70,"") -> 10.7 | X70: =IFERROR((K70*$K$1)+(N70*$N$1)+(Q70*$Q$1)+(T70*$T$1),"") -> 1872.5 | Y70: =IF(E70<>"",IF(X70<(AE70*$AE$1),(AE70*$AE$1),X70),"") -> 1872.5 | Z70: 1 | AA70: 1 | AB70: 1 | AC70: 13170 | AD70: =SUMPRODUCT(Z70:AB70,$Z$1:$AB$1) -> 750 | AE70: 4 | AF70: 7.5 | AG70: =Table3[[#This Row],[Active hours (Other than drilling)]]*$AF$1 -> 3450 | AH70: 0.5 | AJ70: {=SUM(Table3[[#This Row],[Inactive Hours (Other than client standby)]:[Standby Total Hours]]*$AI67)} -> 0 | AM70: =IF(ISBLANK(AE70),"",SUM(AE70:AF70,AH70:AI70,AK70:AL70)) -> 12 | AN70: =(AF70*$AF$1)+(AH70*$AH$1)+(AI70*$AI$1) -> 3630 | AO70: 390 | AP70: =AO70-H70 -> 0 | AQ70: =SUM(Y70,AN70,AP70,H70)+AD70 -> 6642.5 | AS70: =SUM($AQ$6:AQ70) -> 388660.92 | AT70: =_xlfn.TEXTJOIN(,TRUE,"0",MONTH(C70)) -> 08 | AU70: =DAY(C70) -> 7 | AV70: =LEFT(D70,1) -> D
A71: DDRD | C71: =C69+1 -> 45876.71 | D71: NS 5pm | E71: SF25_DDRD001 | G71: 3 | H71: =IF(ISBLANK(G71),"",G71*$H$1) -> 390 | I71: 0 | J71: 0 | K71: =IF(ISBLANK(I71),0,J71-I71) -> 0 | N71: =IF(ISBLANK(L71),,M71-L71) -> 0 | Q71: =IF(ISBLANK(O71),,P71-O71) -> 0 | T71: =IF(ISBLANK(R71),,S71-R71) -> 0 | U71: =SUM(K71,Q71) -> 0 | V71: =SUM(N71,T71) -> 0 | W71: =IFERROR(K71+N71+Q71+T71,"") -> 0 | X71: =IFERROR((K71*$K$1)+(N71*$N$1)+(Q71*$Q$1)+(T71*$T$1),"") -> 0 | Y71: =IF(E71<>"",IF(X71<(AE71*$AE$1),(AE71*$AE$1),X71),"") -> 0 | AD71: =SUMPRODUCT(Z71:AB71,$Z$1:$AB$1) -> 0 | AE71: 0 | AF71: 11.5 | AG71: =Table3[[#This Row],[Active hours (Other than drilling)]]*$AF$1 -> 5290 | AH71: 0.5 | AJ71: {=SUM(Table3[[#This Row],[Inactive Hours (Other than client standby)]:[Standby Total Hours]]*$AI68)} -> 0.5 | AM71: =IF(ISBLANK(AE71),"",SUM(AE71:AF71,AH71:AI71,AK71:AL71)) -> 12 | AN71: =(AF71*$AF$1)+(AH71*$AH$1)+(AI71*$AI$1) -> 5470 | AO71: 390 | AP71: =AO71-H71 -> 0 | AQ71: =SUM(Y71,AN71,AP71,H71)+AD71 -> 5860 | AS71: =SUM($AQ$6:AQ71) -> 394520.92 | AT71: =_xlfn.TEXTJOIN(,TRUE,"0",MONTH(C71)) -> 08 | AU71: =DAY(C71) -> 7 | AV71: =LEFT(D71,1) -> N
A72: DDRD | C72: =C70+1 -> 45877.21 | D72: DS 5am | E72: SF25_DDRD001 | G72: 3 | H72: =IF(ISBLANK(G72),"",G72*$H$1) -> 390 | K72: =IF(ISBLANK(I72),0,J72-I72) -> 0 | L72: 0 | M72: 5 | N72: =IF(ISBLANK(L72),,M72-L72) -> 5 | Q72: =IF(ISBLANK(O72),,P72-O72) -> 0 | T72: =IF(ISBLANK(R72),,S72-R72) -> 0 | U72: =SUM(K72,Q72) -> 0 | V72: =SUM(N72,T72) -> 5 | W72: =IFERROR(K72+N72+Q72+T72,"") -> 5 | X72: =IFERROR((K72*$K$1)+(N72*$N$1)+(Q72*$Q$1)+(T72*$T$1),"") -> 675 | Y72: =IF(E72<>"",IF(X72<(AE72*$AE$1),(AE72*$AE$1),X72),"") -> 920 | Z72: 1 | AA72: 1 | AB72: 1 | AC72: 13170 | AD72: =SUMPRODUCT(Z72:AB72,$Z$1:$AB$1) -> 750 | AE72: 2 | AF72: 0 | AG72: =Table3[[#This Row],[Active hours (Other than drilling)]]*$AF$1 -> 0 | AH72: 0.5 | AI72: 9.5 | AJ72: {=SUM(Table3[[#This Row],[Inactive Hours (Other than client standby)]:[Standby Total Hours]]*$AI69)} -> 0 | AM72: =IF(ISBLANK(AE72),"",SUM(AE72:AF72,AH72:AI72,AK72:AL72)) -> 12 | AN72: =(AF72*$AF$1)+(AH72*$AH$1)+(AI72*$AI$1) -> 3600 | AO72: 5458 | AP72: =AO72-H72 -> 5068 | AQ72: =SUM(Y72,AN72,AP72,H72)+AD72 -> 10728 | AR72: 10728 | AS72: =SUM($AQ$6:AQ72) -> 405248.92 | AT72: =_xlfn.TEXTJOIN(,TRUE,"0",MONTH(C72)) -> 08 | AU72: =DAY(C72) -> 8 | AV72: =LEFT(D72,1) -> D
A73: DDRD | C73: =C71+1 -> 45877.71 | D73: NS 5pm | E73: SF25_DDRD001 | G73: 3 | H73: =IF(ISBLANK(G73),"",G73*$H$1) -> 390 | K73: =IF(ISBLANK(I73),0,J73-I73) -> 0 | L73: 5 | M73: 22 | N73: =IF(ISBLANK(L73),,M73-L73) -> 17 | Q73: =IF(ISBLANK(O73),,P73-O73) -> 0 | T73: =IF(ISBLANK(R73),,S73-R73) -> 0 | U73: =SUM(K73,Q73) -> 0 | V73: =SUM(N73,T73) -> 17 | W73: =IFERROR(K73+N73+Q73+T73,"") -> 17 | X73: =IFERROR((K73*$K$1)+(N73*$N$1)+(Q73*$Q$1)+(T73*$T$1),"") -> 2295 | Y73: =IF(E73<>"",IF(X73<(AE73*$AE$1),(AE73*$AE$1),X73),"") -> 4025 | AD73: =SUMPRODUCT(Z73:AB73,$Z$1:$AB$1) -> 0 | AE73: 8.75 | AF73: 2.75 | AG73: =Table3[[#This Row],[Active hours (Other than drilling)]]*$AF$1 -> 1265 | AH73: 0.5 | AJ73: {=SUM(Table3[[#This Row],[Inactive Hours (Other than client standby)]:[Standby Total Hours]]*$AI70)} -> 0 | AM73: =IF(ISBLANK(AE73),"",SUM(AE73:AF73,AH73:AI73,AK73:AL73)) -> 12 | AN73: =(AF73*$AF$1)+(AH73*$AH$1)+(AI73*$AI$1) -> 1445 | AO73: 738.56 | AP73: =AO73-H73 -> 348.56 | AQ73: =SUM(Y73,AN73,AP73,H73)+AD73 -> 6208.56 | AR73: 6208.56 | AS73: =SUM($AQ$6:AQ73) -> 411457.48 | AT73: =_xlfn.TEXTJOIN(,TRUE,"0",MONTH(C73)) -> 08 | AU73: =DAY(C73) -> 8 | AV73: =LEFT(D73,1) -> N
A74: DDRD | C74: =C72+1 -> 45878.21 | D74: DS 5am | E74: SF25_DDRD001 | G74: 3 | H74: =IF(ISBLANK(G74),"",G74*$H$1) -> 390 | K74: =IF(ISBLANK(I74),0,J74-I74) -> 0 | L74: 22 | M74: 57.8 | N74: =IF(ISBLANK(L74),,M74-L74) -> 35.8 | Q74: =IF(ISBLANK(O74),,P74-O74) -> 0 | T74: =IF(ISBLANK(R74),,S74-R74) -> 0 | U74: =SUM(K74,Q74) -> 0 | V74: =SUM(N74,T74) -> 35.8 | W74: =IFERROR(K74+N74+Q74+T74,"") -> 35.8 | X74: =IFERROR((K74*$K$1)+(N74*$N$1)+(Q74*$Q$1)+(T74*$T$1),"") -> 4833 | Y74: =IF(E74<>"",IF(X74<(AE74*$AE$1),(AE74*$AE$1),X74),"") -> 5060 | Z74: 1 | AA74: 1 | AB74: 1 | AC74: 13170 | AD74: =SUMPRODUCT(Z74:AB74,$Z$1:$AB$1) -> 750 | AE74: 11 | AF74: 0.5 | AG74: =Table3[[#This Row],[Active hours (Other than drilling)]]*$AF$1 -> 230 | AH74: 0.5 | AJ74: {=SUM(Table3[[#This Row],[Inactive Hours (Other than client standby)]:[Standby Total Hours]]*$AI71)} -> 0 | AM74: =IF(ISBLANK(AE74),"",SUM(AE74:AF74,AH74:AI74,AK74:AL74)) -> 12 | AN74: =(AF74*$AF$1)+(AH74*$AH$1)+(AI74*$AI$1) -> 410 | AO74: 390 | AP74: =AO74-H74 -> 0 | AQ74: =SUM(Y74,AN74,AP74,H74)+AD74 -> 6610 | AR74: 6610 | AS74: =SUM($AQ$6:AQ74) -> 418067.48 | AT74: =_xlfn.TEXTJOIN(,TRUE,"0",MONTH(C74)) -> 08 | AU74: =DAY(C74) -> 9 | AV74: =LEFT(D74,1) -> D
A75: DDRD | C75: =C73+1 -> 45878.71 | D75: NS 5pm | E75: SF25_DDRD001 | G75: 3 | H75: =IF(ISBLANK(G75),"",G75*$H$1) -> 390 | K75: =IF(ISBLANK(I75),0,J75-I75) -> 0 | L75: 57.8 | M75: 84.6 | N75: =IF(ISBLANK(L75),,M75-L75) -> 26.8 | Q75: =IF(ISBLANK(O75),,P75-O75) -> 0 | T75: =IF(ISBLANK(R75),,S75-R75) -> 0 | U75: =SUM(K75,Q75) -> 0 | V75: =SUM(N75,T75) -> 26.8 | W75: =IFERROR(K75+N75+Q75+T75,"") -> 26.8 | X75: =IFERROR((K75*$K$1)+(N75*$N$1)+(Q75*$Q$1)+(T75*$T$1),"") -> 3618 | Y75: =IF(E75<>"",IF(X75<(AE75*$AE$1),(AE75*$AE$1),X75),"") -> 3618 | AD75: =SUMPRODUCT(Z75:AB75,$Z$1:$AB$1) -> 0 | AE75: 7 | AF75: 0.25 | AG75: =Table3[[#This Row],[Active hours (Other than drilling)]]*$AF$1 -> 115 | AH75: 0.5 | AI75: 4.25 | AJ75: {=SUM(Table3[[#This Row],[Inactive Hours (Other than client standby)]:[Standby Total Hours]]*$AI72)} -> 45.125 | AM75: =IF(ISBLANK(AE75),"",SUM(AE75:AF75,AH75:AI75,AK75:AL75)) -> 12 | AN75: =(AF75*$AF$1)+(AH75*$AH$1)+(AI75*$AI$1) -> 1825 | AO75: 527.5 | AP75: =AO75-H75 -> 137.5 | AQ75: =SUM(Y75,AN75,AP75,H75)+AD75 -> 5970.5 | AR75: 5970.5 | AS75: =SUM($AQ$6:AQ75) -> 424037.98 | AT75: =_xlfn.TEXTJOIN(,TRUE,"0",MONTH(C75)) -> 08 | AU75: =DAY(C75) -> 9 | AV75: =LEFT(D75,1) -> N
A76: DDRD | B76: 1 | C76: =C74+1 -> 45879.21 | D76: DS 5am | E76: SF25_DDRD001 | F76: SF25_DDGT001 | G76: 3 | H76: =IF(ISBLANK(G76),"",G76*$H$1) -> 390 | K76: =IF(ISBLANK(I76),0,J76-I76) -> 0 | N76: =IF(ISBLANK(L76),,M76-L76) -> 0 | Q76: =IF(ISBLANK(O76),,P76-O76) -> 0 | T76: =IF(ISBLANK(R76),,S76-R76) -> 0 | U76: =SUM(K76,Q76) -> 0 | V76: =SUM(N76,T76) -> 0 | W76: =IFERROR(K76+N76+Q76+T76,"") -> 0 | X76: =IFERROR((K76*$K$1)+(N76*$N$1)+(Q76*$Q$1)+(T76*$T$1),"") -> 0 | Y76: =IF(E76<>"",IF(X76<(AE76*$AE$1),(AE76*$AE$1),X76),"") -> 0 | AD76: =SUMPRODUCT(Z76:AB76,$Z$1:$AB$1) -> 0 | AG76: =Table3[[#This Row],[Active hours (Other than drilling)]]*$AF$1 -> 0 | AJ76: {=SUM(Table3[[#This Row],[Inactive Hours (Other than client standby)]:[Standby Total Hours]]*$AI73)} -> 0 | AM76: =IF(ISBLANK(AE76),"",SUM(AE76:AF76,AH76:AI76,AK76:AL76)) | AN76: =(AF76*$AF$1)+(AH76*$AH$1)+(AI76*$AI$1) -> 0 | AQ76: =SUM(Y76,AN76,AP76,H76)+AD76 -> 390 | AS76: =SUM($AQ$6:AQ76) -> 424427.98 | AT76: =_xlfn.TEXTJOIN(,TRUE,"0",MONTH(C76)) -> 08 | AU76: =DAY(C76) -> 10 | AV76: =LEFT(D76,1) -> D
A77: =IFERROR(IF(FIND("MET",E77),"MET",IF(FIND("GT",E77),"GT",)),"") | C77: =C75+1 -> 45879.71 | D77: NS 5pm | H77: =IF(ISBLANK(G77),"",G77*$H$1) | K77: =IF(ISBLANK(I77),0,J77-I77) -> 0 | N77: =IF(ISBLANK(L77),,M77-L77) -> 0 | Q77: =IF(ISBLANK(O77),,P77-O77) -> 0 | T77: =IF(ISBLANK(R77),,S77-R77) -> 0 | U77: =SUM(K77,Q77) -> 0 | V77: =SUM(N77,T77) -> 0 | W77: =IFERROR(K77+N77+Q77+T77,"") -> 0 | X77: =IFERROR((K77*$K$1)+(N77*$N$1)+(Q77*$Q$1)+(T77*$T$1),"") -> 0 | Y77: =IF(E77<>"",IF(X77<(AE77*$AE$1),(AE77*$AE$1),X77),"") | AD77: =SUMPRODUCT(Z77:AB77,$Z$1:$AB$1) -> 0 | AG77: =Table3[[#This Row],[Active hours (Other than drilling)]]*$AF$1 -> 0 | AJ77: {=SUM(Table3[[#This Row],[Inactive Hours (Other than client standby)]:[Standby Total Hours]]*$AI74)} -> 0 | AM77: =IF(ISBLANK(AE77),"",SUM(AE77:AF77,AH77:AI77,AK77:AL77)) | AN77: =(AF77*$AF$1)+(AH77*$AH$1)+(AI77*$AI$1) -> 0 | AQ77: =SUM(Y77,AN77,AP77,H77)+AD77 -> 0 | AS77: =SUM($AQ$6:AQ77) -> 424427.98 | AT77: =_xlfn.TEXTJOIN(,TRUE,"0",MONTH(C77)) -> 08 | AU77: =DAY(C77) -> 10 | AV77: =LEFT(D77,1) -> N
A78: =IFERROR(IF(FIND("MET",E78),"MET",IF(FIND("GT",E78),"GT",)),"") | C78: =C76+1 -> 45880.21 | D78: DS 5am | H78: =IF(ISBLANK(G78),"",G78*$H$1) | K78: =IF(ISBLANK(I78),0,J78-I78) -> 0 | N78: =IF(ISBLANK(L78),,M78-L78) -> 0 | Q78: =IF(ISBLANK(O78),,P78-O78) -> 0 | T78: =IF(ISBLANK(R78),,S78-R78) -> 0 | U78: =SUM(K78,Q78) -> 0 | V78: =SUM(N78,T78) -> 0 | W78: =IFERROR(K78+N78+Q78+T78,"") -> 0 | X78: =IFERROR((K78*$K$1)+(N78*$N$1)+(Q78*$Q$1)+(T78*$T$1),"") -> 0 | Y78: =IF(E78<>"",IF(X78<(AE78*$AE$1),(AE78*$AE$1),X78),"") | AD78: =SUMPRODUCT(Z78:AB78,$Z$1:$AB$1) -> 0 | AG78: =Table3[[#This Row],[Active hours (Other than drilling)]]*$AF$1 -> 0 | AJ78: {=SUM(Table3[[#This Row],[Inactive Hours (Other than client standby)]:[Standby Total Hours]]*$AI75)} -> 0 | AM78: =IF(ISBLANK(AE78),"",SUM(AE78:AF78,AH78:AI78,AK78:AL78)) | AN78: =(AF78*$AF$1)+(AH78*$AH$1)+(AI78*$AI$1) -> 0 | AQ78: =SUM(Y78,AN78,AP78,H78)+AD78 -> 0 | AS78: =SUM($AQ$6:AQ78) -> 424427.98 | AT78: =_xlfn.TEXTJOIN(,TRUE,"0",MONTH(C78)) -> 08 | AU78: =DAY(C78) -> 11 | AV78: =LEFT(D78,1) -> D
A79: =IFERROR(IF(FIND("MET",E79),"MET",IF(FIND("GT",E79),"GT",)),"") | C79: =C77+1 -> 45880.71 | D79: NS 5pm | H79: =IF(ISBLANK(G79),"",G79*$H$1) | K79: =IF(ISBLANK(I79),0,J79-I79) -> 0 | N79: =IF(ISBLANK(L79),,M79-L79) -> 0 | Q79: =IF(ISBLANK(O79),,P79-O79) -> 0 | T79: =IF(ISBLANK(R79),,S79-R79) -> 0 | U79: =SUM(K79,Q79) -> 0 | V79: =SUM(N79,T79) -> 0 | W79: =IFERROR(K79+N79+Q79+T79,"") -> 0 | X79: =IFERROR((K79*$K$1)+(N79*$N$1)+(Q79*$Q$1)+(T79*$T$1),"") -> 0 | Y79: =IF(E79<>"",IF(X79<(AE79*$AE$1),(AE79*$AE$1),X79),"") | AD79: =SUMPRODUCT(Z79:AB79,$Z$1:$AB$1) -> 0 | AG79: =Table3[[#This Row],[Active hours (Other than drilling)]]*$AF$1 -> 0 | AJ79: {=SUM(Table3[[#This Row],[Inactive Hours (Other than client standby)]:[Standby Total Hours]]*$AI76)} -> 0 | AM79: =IF(ISBLANK(AE79),"",SUM(AE79:AF79,AH79:AI79,AK79:AL79)) | AN79: =(AF79*$AF$1)+(AH79*$AH$1)+(AI79*$AI$1) -> 0 | AQ79: =SUM(Y79,AN79,AP79,H79)+AD79 -> 0 | AS79: =SUM($AQ$6:AQ79) -> 424427.98 | AT79: =_xlfn.TEXTJOIN(,TRUE,"0",MONTH(C79)) -> 08 | AU79: =DAY(C79) -> 11 | AV79: =LEFT(D79,1) -> N
A80: =IFERROR(IF(FIND("MET",E80),"MET",IF(FIND("GT",E80),"GT",)),"") | C80: =C78+1 -> 45881.21 | D80: DS 5am | H80: =IF(ISBLANK(G80),"",G80*$H$1) | K80: =IF(ISBLANK(I80),0,J80-I80) -> 0 | N80: =IF(ISBLANK(L80),,M80-L80) -> 0 | Q80: =IF(ISBLANK(O80),,P80-O80) -> 0 | T80: =IF(ISBLANK(R80),,S80-R80) -> 0 | U80: =SUM(K80,Q80) -> 0 | V80: =SUM(N80,T80) -> 0 | W80: =IFERROR(K80+N80+Q80+T80,"") -> 0 | X80: =IFERROR((K80*$K$1)+(N80*$N$1)+(Q80*$Q$1)+(T80*$T$1),"") -> 0 | Y80: =IF(E80<>"",IF(X80<(AE80*$AE$1),(AE80*$AE$1),X80),"") | AD80: =SUMPRODUCT(Z80:AB80,$Z$1:$AB$1) -> 0 | AG80: =Table3[[#This Row],[Active hours (Other than drilling)]]*$AF$1 -> 0 | AJ80: {=SUM(Table3[[#This Row],[Inactive Hours (Other than client standby)]:[Standby Total Hours]]*$AI77)} -> 0 | AM80: =IF(ISBLANK(AE80),"",SUM(AE80:AF80,AH80:AI80,AK80:AL80)) | AN80: =(AF80*$AF$1)+(AH80*$AH$1)+(AI80*$AI$1) -> 0 | AQ80: =SUM(Y80,AN80,AP80,H80)+AD80 -> 0 | AS80: =SUM($AQ$6:AQ80) -> 424427.98 | AT80: =_xlfn.TEXTJOIN(,TRUE,"0",MONTH(C80)) -> 08 | AU80: =DAY(C80) -> 12 | AV80: =LEFT(D80,1) -> D
A81: =IFERROR(IF(FIND("MET",E81),"MET",IF(FIND("GT",E81),"GT",)),"") | C81: =C79+1 -> 45881.71 | D81: NS 5pm | H81: =IF(ISBLANK(G81),"",G81*$H$1) | K81: =IF(ISBLANK(I81),0,J81-I81) -> 0 | N81: =IF(ISBLANK(L81),,M81-L81) -> 0 | Q81: =IF(ISBLANK(O81),,P81-O81) -> 0 | T81: =IF(ISBLANK(R81),,S81-R81) -> 0 | U81: =SUM(K81,Q81) -> 0 | V81: =SUM(N81,T81) -> 0 | W81: =IFERROR(K81+N81+Q81+T81,"") -> 0 | X81: =IFERROR((K81*$K$1)+(N81*$N$1)+(Q81*$Q$1)+(T81*$T$1),"") -> 0 | Y81: =IF(E81<>"",IF(X81<(AE81*$AE$1),(AE81*$AE$1),X81),"") | AD81: =SUMPRODUCT(Z81:AB81,$Z$1:$AB$1) -> 0 | AG81: =Table3[[#This Row],[Active hours (Other than drilling)]]*$AF$1 -> 0 | AJ81: {=SUM(Table3[[#This Row],[Inactive Hours (Other than client standby)]:[Standby Total Hours]]*$AI78)} -> 0 | AM81: =IF(ISBLANK(AE81),"",SUM(AE81:AF81,AH81:AI81,AK81:AL81)) | AN81: =(AF81*$AF$1)+(AH81*$AH$1)+(AI81*$AI$1) -> 0 | AQ81: =SUM(Y81,AN81,AP81,H81)+AD81 -> 0 | AS81: =SUM($AQ$6:AQ81) -> 424427.98 | AT81: =_xlfn.TEXTJOIN(,TRUE,"0",MONTH(C81)) -> 08 | AU81: =DAY(C81) -> 12 | AV81: =LEFT(D81,1) -> N
A82: =IFERROR(IF(FIND("MET",E82),"MET",IF(FIND("GT",E82),"GT",)),"") | C82: =C80+1 -> 45882.21 | D82: DS 5am | H82: =IF(ISBLANK(G82),"",G82*$H$1) | K82: =IF(ISBLANK(I82),0,J82-I82) -> 0 | N82: =IF(ISBLANK(L82),,M82-L82) -> 0 | Q82: =IF(ISBLANK(O82),,P82-O82) -> 0 | T82: =IF(ISBLANK(R82),,S82-R82) -> 0 | U82: =SUM(K82,Q82) -> 0 | V82: =SUM(N82,T82) -> 0 | W82: =IFERROR(K82+N82+Q82+T82,"") -> 0 | X82: =IFERROR((K82*$K$1)+(N82*$N$1)+(Q82*$Q$1)+(T82*$T$1),"") -> 0 | Y82: =IF(E82<>"",IF(X82<(AE82*$AE$1),(AE82*$AE$1),X82),"") | AD82: =SUMPRODUCT(Z82:AB82,$Z$1:$AB$1) -> 0 | AG82: =Table3[[#This Row],[Active hours (Other than drilling)]]*$AF$1 -> 0 | AJ82: {=SUM(Table3[[#This Row],[Inactive Hours (Other than client standby)]:[Standby Total Hours]]*$AI79)} -> 0 | AM82: =IF(ISBLANK(AE82),"",SUM(AE82:AF82,AH82:AI82,AK82:AL82)) | AN82: =(AF82*$AF$1)+(AH82*$AH$1)+(AI82*$AI$1) -> 0 | AQ82: =SUM(Y82,AN82,AP82,H82)+AD82 -> 0 | AS82: =SUM($AQ$6:AQ82) -> 424427.98 | AT82: =_xlfn.TEXTJOIN(,TRUE,"0",MONTH(C82)) -> 08 | AU82: =DAY(C82) -> 13 | AV82: =LEFT(D82,1) -> D
A83: =IFERROR(IF(FIND("MET",E83),"MET",IF(FIND("GT",E83),"GT",)),"") | C83: =C81+1 -> 45882.71 | D83: NS 5pm | H83: =IF(ISBLANK(G83),"",G83*$H$1) | K83: =IF(ISBLANK(I83),0,J83-I83) -> 0 | N83: =IF(ISBLANK(L83),,M83-L83) -> 0 | Q83: =IF(ISBLANK(O83),,P83-O83) -> 0 | T83: =IF(ISBLANK(R83),,S83-R83) -> 0 | U83: =SUM(K83,Q83) -> 0 | V83: =SUM(N83,T83) -> 0 | W83: =IFERROR(K83+N83+Q83+T83,"") -> 0 | X83: =IFERROR((K83*$K$1)+(N83*$N$1)+(Q83*$Q$1)+(T83*$T$1),"") -> 0 | Y83: =IF(E83<>"",IF(X83<(AE83*$AE$1),(AE83*$AE$1),X83),"") | AD83: =SUMPRODUCT(Z83:AB83,$Z$1:$AB$1) -> 0 | AG83: =Table3[[#This Row],[Active hours (Other than drilling)]]*$AF$1 -> 0 | AJ83: {=SUM(Table3[[#This Row],[Inactive Hours (Other than client standby)]:[Standby Total Hours]]*$AI80)} -> 0 | AM83: =IF(ISBLANK(AE83),"",SUM(AE83:AF83,AH83:AI83,AK83:AL83)) | AN83: =(AF83*$AF$1)+(AH83*$AH$1)+(AI83*$AI$1) -> 0 | AQ83: =SUM(Y83,AN83,AP83,H83)+AD83 -> 0 | AS83: =SUM($AQ$6:AQ83) -> 424427.98 | AT83: =_xlfn.TEXTJOIN(,TRUE,"0",MONTH(C83)) -> 08 | AU83: =DAY(C83) -> 13 | AV83: =LEFT(D83,1) -> N
A84: =IFERROR(IF(FIND("MET",E84),"MET",IF(FIND("GT",E84),"GT",)),"") | C84: =C82+1 -> 45883.21 | D84: DS 5am | H84: =IF(ISBLANK(G84),"",G84*$H$1) | K84: =IF(ISBLANK(I84),0,J84-I84) -> 0 | N84: =IF(ISBLANK(L84),,M84-L84) -> 0 | Q84: =IF(ISBLANK(O84),,P84-O84) -> 0 | T84: =IF(ISBLANK(R84),,S84-R84) -> 0 | U84: =SUM(K84,Q84) -> 0 | V84: =SUM(N84,T84) -> 0 | W84: =IFERROR(K84+N84+Q84+T84,"") -> 0 | X84: =IFERROR((K84*$K$1)+(N84*$N$1)+(Q84*$Q$1)+(T84*$T$1),"") -> 0 | Y84: =IF(E84<>"",IF(X84<(AE84*$AE$1),(AE84*$AE$1),X84),"") | AD84: =SUMPRODUCT(Z84:AB84,$Z$1:$AB$1) -> 0 | AG84: =Table3[[#This Row],[Active hours (Other than drilling)]]*$AF$1 -> 0 | AJ84: {=SUM(Table3[[#This Row],[Inactive Hours (Other than client standby)]:[Standby Total Hours]]*$AI81)} -> 0 | AM84: =IF(ISBLANK(AE84),"",SUM(AE84:AF84,AH84:AI84,AK84:AL84)) | AN84: =(AF84*$AF$1)+(AH84*$AH$1)+(AI84*$AI$1) -> 0 | AQ84: =SUM(Y84,AN84,AP84,H84)+AD84 -> 0 | AS84: =SUM($AQ$6:AQ84) -> 424427.98 | AT84: =_xlfn.TEXTJOIN(,TRUE,"0",MONTH(C84)) -> 08 | AU84: =DAY(C84) -> 14 | AV84: =LEFT(D84,1) -> D
A85: =IFERROR(IF(FIND("MET",E85),"MET",IF(FIND("GT",E85),"GT",)),"") | C85: =C83+1 -> 45883.71 | D85: NS 5pm | H85: =IF(ISBLANK(G85),"",G85*$H$1) | K85: =IF(ISBLANK(I85),0,J85-I85) -> 0 | N85: =IF(ISBLANK(L85),,M85-L85) -> 0 | Q85: =IF(ISBLANK(O85),,P85-O85) -> 0 | T85: =IF(ISBLANK(R85),,S85-R85) -> 0 | U85: =SUM(K85,Q85) -> 0 | V85: =SUM(N85,T85) -> 0 | W85: =IFERROR(K85+N85+Q85+T85,"") -> 0 | X85: =IFERROR((K85*$K$1)+(N85*$N$1)+(Q85*$Q$1)+(T85*$T$1),"") -> 0 | Y85: =IF(E85<>"",IF(X85<(AE85*$AE$1),(AE85*$AE$1),X85),"") | AD85: =SUMPRODUCT(Z85:AB85,$Z$1:$AB$1) -> 0 | AG85: =Table3[[#This Row],[Active hours (Other than drilling)]]*$AF$1 -> 0 | AJ85: {=SUM(Table3[[#This Row],[Inactive Hours (Other than client standby)]:[Standby Total Hours]]*$AI82)} -> 0 | AM85: =IF(ISBLANK(AE85),"",SUM(AE85:AF85,AH85:AI85,AK85:AL85)) | AN85: =(AF85*$AF$1)+(AH85*$AH$1)+(AI85*$AI$1) -> 0 | AQ85: =SUM(Y85,AN85,AP85,H85)+AD85 -> 0 | AS85: =SUM($AQ$6:AQ85) -> 424427.98 | AT85: =_xlfn.TEXTJOIN(,TRUE,"0",MONTH(C85)) -> 08 | AU85: =DAY(C85) -> 14 | AV85: =LEFT(D85,1) -> N
A86: =IFERROR(IF(FIND("MET",E86),"MET",IF(FIND("GT",E86),"GT",)),"") | C86: =C84+1 -> 45884.21 | D86: DS 5am | H86: =IF(ISBLANK(G86),"",G86*$H$1) | K86: =IF(ISBLANK(I86),0,J86-I86) -> 0 | N86: =IF(ISBLANK(L86),,M86-L86) -> 0 | Q86: =IF(ISBLANK(O86),,P86-O86) -> 0 | T86: =IF(ISBLANK(R86),,S86-R86) -> 0 | U86: =SUM(K86,Q86) -> 0 | V86: =SUM(N86,T86) -> 0 | W86: =IFERROR(K86+N86+Q86+T86,"") -> 0 | X86: =IFERROR((K86*$K$1)+(N86*$N$1)+(Q86*$Q$1)+(T86*$T$1),"") -> 0 | Y86: =IF(E86<>"",IF(X86<(AE86*$AE$1),(AE86*$AE$1),X86),"") | AD86: =SUMPRODUCT(Z86:AB86,$Z$1:$AB$1) -> 0 | AG86: =Table3[[#This Row],[Active hours (Other than drilling)]]*$AF$1 -> 0 | AJ86: {=SUM(Table3[[#This Row],[Inactive Hours (Other than client standby)]:[Standby Total Hours]]*$AI83)} -> 0 | AM86: =IF(ISBLANK(AE86),"",SUM(AE86:AF86,AH86:AI86,AK86:AL86)) | AN86: =(AF86*$AF$1)+(AH86*$AH$1)+(AI86*$AI$1) -> 0 | AQ86: =SUM(Y86,AN86,AP86,H86)+AD86 -> 0 | AS86: =SUM($AQ$6:AQ86) -> 424427.98 | AT86: =_xlfn.TEXTJOIN(,TRUE,"0",MONTH(C86)) -> 08 | AU86: =DAY(C86) -> 15 | AV86: =LEFT(D86,1) -> D
A87: =IFERROR(IF(FIND("MET",E87),"MET",IF(FIND("GT",E87),"GT",)),"") | C87: =C85+1 -> 45884.71 | D87: NS 5pm | H87: =IF(ISBLANK(G87),"",G87*$H$1) | K87: =IF(ISBLANK(I87),0,J87-I87) -> 0 | N87: =IF(ISBLANK(L87),,M87-L87) -> 0 | Q87: =IF(ISBLANK(O87),,P87-O87) -> 0 | T87: =IF(ISBLANK(R87),,S87-R87) -> 0 | U87: =SUM(K87,Q87) -> 0 | V87: =SUM(N87,T87) -> 0 | W87: =IFERROR(K87+N87+Q87+T87,"") -> 0 | X87: =IFERROR((K87*$K$1)+(N87*$N$1)+(Q87*$Q$1)+(T87*$T$1),"") -> 0 | Y87: =IF(E87<>"",IF(X87<(AE87*$AE$1),(AE87*$AE$1),X87),"") | AD87: =SUMPRODUCT(Z87:AB87,$Z$1:$AB$1) -> 0 | AG87: =Table3[[#This Row],[Active hours (Other than drilling)]]*$AF$1 -> 0 | AJ87: {=SUM(Table3[[#This Row],[Inactive Hours (Other than client standby)]:[Standby Total Hours]]*$AI84)} -> 0 | AM87: =IF(ISBLANK(AE87),"",SUM(AE87:AF87,AH87:AI87,AK87:AL87)) | AN87: =(AF87*$AF$1)+(AH87*$AH$1)+(AI87*$AI$1) -> 0 | AQ87: =SUM(Y87,AN87,AP87,H87)+AD87 -> 0 | AS87: =SUM($AQ$6:AQ87) -> 424427.98 | AT87: =_xlfn.TEXTJOIN(,TRUE,"0",MONTH(C87)) -> 08 | AU87: =DAY(C87) -> 15 | AV87: =LEFT(D87,1) -> N
A88: =IFERROR(IF(FIND("MET",E88),"MET",IF(FIND("GT",E88),"GT",)),"") | C88: =C86+1 -> 45885.21 | D88: DS 5am | H88: =IF(ISBLANK(G88),"",G88*$H$1) | K88: =IF(ISBLANK(I88),0,J88-I88) -> 0 | N88: =IF(ISBLANK(L88),,M88-L88) -> 0 | Q88: =IF(ISBLANK(O88),,P88-O88) -> 0 | T88: =IF(ISBLANK(R88),,S88-R88) -> 0 | U88: =SUM(K88,Q88) -> 0 | V88: =SUM(N88,T88) -> 0 | W88: =IFERROR(K88+N88+Q88+T88,"") -> 0 | X88: =IFERROR((K88*$K$1)+(N88*$N$1)+(Q88*$Q$1)+(T88*$T$1),"") -> 0 | Y88: =IF(E88<>"",IF(X88<(AE88*$AE$1),(AE88*$AE$1),X88),"") | AD88: =SUMPRODUCT(Z88:AB88,$Z$1:$AB$1) -> 0 | AG88: =Table3[[#This Row],[Active hours (Other than drilling)]]*$AF$1 -> 0 | AJ88: {=SUM(Table3[[#This Row],[Inactive Hours (Other than client standby)]:[Standby Total Hours]]*$AI85)} -> 0 | AM88: =IF(ISBLANK(AE88),"",SUM(AE88:AF88,AH88:AI88,AK88:AL88)) | AN88: =(AF88*$AF$1)+(AH88*$AH$1)+(AI88*$AI$1) -> 0 | AQ88: =SUM(Y88,AN88,AP88,H88)+AD88 -> 0 | AS88: =SUM($AQ$6:AQ88) -> 424427.98 | AT88: =_xlfn.TEXTJOIN(,TRUE,"0",MONTH(C88)) -> 08 | AU88: =DAY(C88) -> 16 | AV88: =LEFT(D88,1) -> D
... A188: =IFERROR(IF(FIND("MET",E188),"MET",IF(FIND("GT",E188),"GT",)),"") | C188: =C186+1 -> 45935.21 | D188: DS 5am | H188: =IF(ISBLANK(G188),"",G188*$H$1) | K188: =IF(ISBLANK(I188),0,J188-I188) -> 0 | N188: =IF(ISBLANK(L188),,M188-L188) -> 0 | Q188: =IF(ISBLANK(O188),,P188-O188) -> 0 | T188: =IF(ISBLANK(R188),,S188-R188) -> 0 | U188: =SUM(K188,Q188) -> 0 | V188: =SUM(N188,T188) -> 0 | W188: =IFERROR(K188+N188+Q188+T188,"") -> 0 | X188: =IFERROR((K188*$K$1)+(N188*$N$1)+(Q188*$Q$1)+(T188*$T$1),"") -> 0 | Y188: =IF(E188<>"",IF(X188<(AE188*$AE$1),(AE188*$AE$1),X188),"") | AD188: =SUMPRODUCT(Z188:AB188,$Z$1:$AB$1) -> 0 | AG188: =Table3[[#This Row],[Active hours (Other than drilling)]]*$AF$1 -> 0 | AJ188: {=SUM(Table3[[#This Row],[Inactive Hours (Other than client standby)]:[Standby Total Hours]]*$AI185)} -> 0 | AM188: =IF(ISBLANK(AE188),"",SUM(AE188:AF188,AH188:AI188,AK188:AL188)) | AN188: =(AF188*$AF$1)+(AH188*$AH$1)+(AI188*$AI$1) -> 0 | AQ188: =SUM(Y188,AN188,AP188,H188)+AD188 -> 0 | AS188: =SUM($AQ$6:AQ188) -> 424427.98 | AT188: =_xlfn.TEXTJOIN(,TRUE,"0",MONTH(C188)) -> 010 | AU188: =DAY(C188) -> 5 | AV188: =LEFT(D188,1) -> D
A189: =IFERROR(IF(FIND("MET",E189),"MET",IF(FIND("GT",E189),"GT",)),"") | C189: =C187+1 -> 45935.71 | D189: NS 5pm | U189: =SUM(K189,Q189) -> 0 | V189: =SUM(N189,T189) -> 0 | W189: =IFERROR(K189+N189+Q189+T189,"") -> 0 | X189: =IFERROR((K189*$K$1)+(N189*$N$1)+(Q189*$Q$1)+(T189*$T$1),"") -> 0 | Y189: =IF(E189<>"",IF(X189<(AE189*$AE$1),(AE189*$AE$1),X189),"") | AD189: =SUMPRODUCT(Z189:AB189,$Z$1:$AB$1) -> 0
A190: =IFERROR(IF(FIND("MET",E190),"MET",IF(FIND("GT",E190),"GT",)),"") | C190: =C188+1 -> 45936.21 | D190: DS 5am | U190: =SUM(K190,Q190) -> 0 | V190: =SUM(N190,T190) -> 0 | W190: =IFERROR(K190+N190+Q190+T190,"") -> 0 | X190: =IFERROR((K190*$K$1)+(N190*$N$1)+(Q190*$Q$1)+(T190*$T$1),"") -> 0 | Y190: =IF(E190<>"",IF(X190<(AE190*$AE$1),(AE190*$AE$1),X190),"") | AD190: =SUMPRODUCT(Z190:AB190,$Z$1:$AB$1) -> 0
A191: =IFERROR(IF(FIND("MET",E191),"MET",IF(FIND("GT",E191),"GT",)),"") | C191: =C189+1 -> 45936.71 | D191: NS 5pm | U191: =SUM(K191,Q191) -> 0 | V191: =SUM(N191,T191) -> 0 | W191: =IFERROR(K191+N191+Q191+T191,"") -> 0 | X191: =IFERROR((K191*$K$1)+(N191*$N$1)+(Q191*$Q$1)+(T191*$T$1),"") -> 0 | Y191: =IF(E191<>"",IF(X191<(AE191*$AE$1),(AE191*$AE$1),X191),"") | AD191: =SUMPRODUCT(Z191:AB191,$Z$1:$AB$1) -> 0
A192: =IFERROR(IF(FIND("MET",E192),"MET",IF(FIND("GT",E192),"GT",)),"") | C192: =C190+1 -> 45937.21 | D192: DS 5am | U192: =SUM(K192,Q192) -> 0 | V192: =SUM(N192,T192) -> 0 | W192: =IFERROR(K192+N192+Q192+T192,"") -> 0 | X192: =IFERROR((K192*$K$1)+(N192*$N$1)+(Q192*$Q$1)+(T192*$T$1),"") -> 0 | Y192: =IF(E192<>"",IF(X192<(AE192*$AE$1),(AE192*$AE$1),X192),"") | AD192: =SUMPRODUCT(Z192:AB192,$Z$1:$AB$1) -> 0
A193: =IFERROR(IF(FIND("MET",E193),"MET",IF(FIND("GT",E193),"GT",)),"") | C193: =C191+1 -> 45937.71 | D193: NS 5pm | U193: =SUM(K193,Q193) -> 0 | V193: =SUM(N193,T193) -> 0 | W193: =IFERROR(K193+N193+Q193+T193,"") -> 0 | X193: =IFERROR((K193*$K$1)+(N193*$N$1)+(Q193*$Q$1)+(T193*$T$1),"") -> 0 | Y193: =IF(E193<>"",IF(X193<(AE193*$AE$1),(AE193*$AE$1),X193),"") | AD193: =SUMPRODUCT(Z193:AB193,$Z$1:$AB$1) -> 0
A194: =IFERROR(IF(FIND("MET",E194),"MET",IF(FIND("GT",E194),"GT",)),"") | C194: =C192+1 -> 45938.21 | D194: DS 5am | U194: =SUM(K194,Q194) -> 0 | V194: =SUM(N194,T194) -> 0 | W194: =IFERROR(K194+N194+Q194+T194,"") -> 0 | X194: =IFERROR((K194*$K$1)+(N194*$N$1)+(Q194*$Q$1)+(T194*$T$1),"") -> 0 | Y194: =IF(E194<>"",IF(X194<(AE194*$AE$1),(AE194*$AE$1),X194),"") | AD194: =SUMPRODUCT(Z194:AB194,$Z$1:$AB$1) -> 0
A195: =IFERROR(IF(FIND("MET",E195),"MET",IF(FIND("GT",E195),"GT",)),"") | C195: =C193+1 -> 45938.71 | D195: NS 5pm | U195: =SUM(K195,Q195) -> 0 | V195: =SUM(N195,T195) -> 0 | W195: =IFERROR(K195+N195+Q195+T195,"") -> 0 | X195: =IFERROR((K195*$K$1)+(N195*$N$1)+(Q195*$Q$1)+(T195*$T$1),"") -> 0 | Y195: =IF(E195<>"",IF(X195<(AE195*$AE$1),(AE195*$AE$1),X195),"") | AD195: =SUMPRODUCT(Z195:AB195,$Z$1:$AB$1) -> 0
A196: =IFERROR(IF(FIND("MET",E196),"MET",IF(FIND("GT",E196),"GT",)),"") | C196: =C194+1 -> 45939.21 | D196: DS 5am | U196: =SUM(K196,Q196) -> 0 | V196: =SUM(N196,T196) -> 0 | W196: =IFERROR(K196+N196+Q196+T196,"") -> 0 | X196: =IFERROR((K196*$K$1)+(N196*$N$1)+(Q196*$Q$1)+(T196*$T$1),"") -> 0 | Y196: =IF(E196<>"",IF(X196<(AE196*$AE$1),(AE196*$AE$1),X196),"") | AD196: =SUMPRODUCT(Z196:AB196,$Z$1:$AB$1) -> 0
A197: =IFERROR(IF(FIND("MET",E197),"MET",IF(FIND("GT",E197),"GT",)),"") | C197: =C195+1 -> 45939.71 | D197: NS 5pm | U197: =SUM(K197,Q197) -> 0 | V197: =SUM(N197,T197) -> 0 | W197: =IFERROR(K197+N197+Q197+T197,"") -> 0 | X197: =IFERROR((K197*$K$1)+(N197*$N$1)+(Q197*$Q$1)+(T197*$T$1),"") -> 0 | Y197: =IF(E197<>"",IF(X197<(AE197*$AE$1),(AE197*$AE$1),X197),"") | AD197: =SUMPRODUCT(Z197:AB197,$Z$1:$AB$1) -> 0
A198: =IFERROR(IF(FIND("MET",E198),"MET",IF(FIND("GT",E198),"GT",)),"") | C198: =C196+1 -> 45940.21 | D198: DS 5am | U198: =SUM(K198,Q198) -> 0 | V198: =SUM(N198,T198) -> 0 | W198: =IFERROR(K198+N198+Q198+T198,"") -> 0 | X198: =IFERROR((K198*$K$1)+(N198*$N$1)+(Q198*$Q$1)+(T198*$T$1),"") -> 0 | Y198: =IF(E198<>"",IF(X198<(AE198*$AE$1),(AE198*$AE$1),X198),"") | AD198: =SUMPRODUCT(Z198:AB198,$Z$1:$AB$1) -> 0
A199: =IFERROR(IF(FIND("MET",E199),"MET",IF(FIND("GT",E199),"GT",)),"") | C199: =C197+1 -> 45940.71 | D199: NS 5pm | U199: =SUM(K199,Q199) -> 0 | V199: =SUM(N199,T199) -> 0 | W199: =IFERROR(K199+N199+Q199+T199,"") -> 0 | X199: =IFERROR((K199*$K$1)+(N199*$N$1)+(Q199*$Q$1)+(T199*$T$1),"") -> 0 | Y199: =IF(E199<>"",IF(X199<(AE199*$AE$1),(AE199*$AE$1),X199),"") | AD199: =SUMPRODUCT(Z199:AB199,$Z$1:$AB$1) -> 0
...

Sheet DDH1 RIG 38
F1: Holes Completed: | G1: {=SUM(--(_xlfn.UNIQUE(_xlfn._xlws.FILTER(_xlfn.VSTACK(F6:F300, G6:G300), ISTEXT(_xlfn.VSTACK(F6:F300, G6:G300))))<>""))} -> 25 | I1: Accom | J1: {=SUM(IFERROR(J6:J500,""))} -> 43680 | L1: Sum PQ | M1: =SUM(M6:M234,S6:S234) -> 759.1 | O1: Sum HQ | P1: =SUM(P6:P234,V6:V234) -> 1473.6 | X1: Drilling Cost | Y1: {=SUM(IFERROR(Y6:Y500,""))} -> 382495.5 | AC1: Tool Cost | AD1: {=SUM(IFERROR(AD6:AD500,""))} -> 37625 | AO1: Total Activity Costs | AP1: {=SUM(IFERROR(AP6:AP500,""))} -> 190655 | AQ1: Total Consumable Costs | AR1: {=SUM(IFERROR(AR6:AR500,""))} -> 47998.76 | AS1: {=SUM(IFERROR(AS6:AS500,""))} -> 702454.26
C2: RIG 38 | I2: Rate | J2: 130 | K2: Hole 1 | M2: 175 | P2: 135 | Q2: Hole 2 | S2: 175 | V2: 135 | Z2: 175 | AA2: 155 | AB2: 420 | AE2: 460 | AF2: 460 | AH2: 360 | AI2: 360
F3: Hole 1 | G3: Hole 2 | K3: PQ3 | N3: HQ3 | Q3: PQ3 | T3: HQ3 | Y3: Slow Pen rate Normalised | AK3: 0 | AL3: 0 | AY3: =AVERAGEIF(C:C,"MET",AY12:AY240) -> 379.88878 | AZ3: =AVERAGEIF(C$6:C$1048576,"GT",AY12:AY240) -> 421.04955
B4: Purpose | C4: Hole Type | D4: Date | E4: Shift | F4: Hole ID | G4: Hole ID | H4: Driller Name | I4: Personel (incl driller) | J4: Accom Cost | K4: Depth From | L4: Depth To | M4: Length | N4: Depth From | O4: Depth To | P4: Length | Q4: Depth From | R4: Depth To | S4: Length | T4: Depth From | U4: Depth To | V4: Length | W4: Total Length | X4: Drilling Cost | Y4: Charged Drilling Cost | Z4: PQ Ori Tool | AA4: HQ Ori Tool | AB4: Gyro Tool | AC4: Tool ID | AD4: Tool Hire Cost | AE4: Drill Time | AF4: Active hours (Other than drilling) | AG4: Comment (IF less than 10hours EXPLAIN) | AH4: Inactive Hours (Other than client standby) | AI4: Standby Total Hours | AJ4: Comment (IF more than 2 hours EXPLAIN) | AK4: Uncharged Hours | AL4: Maintenance | AM4: Comments | AN4: Total Daily Hours | AO4: Comments (IF not 12hrs EXPLAIN) | AP4: Total Activity Hours Cost | AQ4: ***Insert Total Consumable Costs*** | AR4: Total Consumables Cost (-accom) | AS4: Total Costs | AT4: Plod Cost (Comparison) | AV4: =IFERROR(AVERAGE(AV8:AV147),"") -> 0.21377417 | AW4: Cummulative Cost | AX4: EOM Cummulative Cost | AY4: All in Cost Per Metre | AZ4: PLOD LINK | BA4: Comments | BB4: Stem | BC4: Year | BD4: Month | BE4: Day | BF4: Shift Shorthand
C5: Index | D5: 1 | E5: 2 | F5: 3 | G5: 4 | H5: 5 | I5: 6 | J5: 7 | K5: 8 | L5: 9 | M5: 10 | N5: 11 | O5: 12 | P5: 13 | Q5: 14 | R5: 15 | S5: 16 | T5: 17 | U5: 18 | V5: 19 | X5: 20 | Y5: 21 | AA5: 22 | AB5: 23 | AC5: 24 | AE5: 25 | AF5: 26 | AG5: 27 | AH5: 28 | AI5: 29 | AJ5: 30 | AK5: 31 | AL5: 32 | AN5: 33 | AO5: 34 | AP5: 35 | AR5: 36 | AS5: 37 | AW5: 38 | AX5: 39 | AY5: 40 | AZ5: 41 | BA5: 42 | BB5: 43 | BC5: 44 | BD5: 45 | BE5: 46 | BF5: 47 | BG5: 48 | BH5: 49 | BI5: 50 | BJ5: 51 | BK5: 52 | BL5: 53 | BM5: 54 | BN5: 55 | BO5: 56 | BP5: 57 | BQ5: 58 | BR5: 59 | BS5: 60 | BT5: 61 | BU5: 62 | BV5: 63 | BW5: 64 | BX5: 65 | BY5: 66 | BZ5: 67 | CA5: 68 | CB5: 69 | CC5: 70 | CD5: 71
A6: =VLOOKUP(F6,'Tenement Lookup'!A:BH,60,FALSE) -> #N/A | B6: =IFERROR(IF(FIND("MET",E6),"MET",IF(FIND("GT",E6),"GT",)),"") | C6: =IFERROR(IF(FIND("MET",F6),"MET",IF(FIND("GT",F6),"GT",)),"") | D6: =45843.21 -> 45843.21 | E6: DS 5am | J6: =IF(ISBLANK(I6),"",I6*$J$2) | M6: =IF(ISBLANK(K6),"",L6-K6) | P6: =IF(ISBLANK(N6),,O6-N6) -> 0 | S6: =IF(ISBLANK(Q6),,R6-Q6) -> 0 | V6: =IF(ISBLANK(T6),,U6-T6) -> 0 | W6: =IFERROR(M6+P6+S6+V6,"") | X6: =IFERROR((M6*$M$2)+(P6*$P$2)+(S6*$S$2)+(V6*$V$2),"") | Y6: =IF(F6<>"",IF(X6<(AE6*$AE$2),(AE6*$AE$2),X6),"") | AA6: 1 | AB6: 1 | AE6: 0 | AF6: 0 | AH6: 3.5 | AJ6: Unpacking rig after mobilisation | AK6: 8.5 | AN6: =IF(ISBLANK(AE6),"",SUM(AE6:AF6,AH6:AL6)) -> 12 | AP6: =(AF6*$AF$2)+(AH6*$AH$2)+(AI6*$AI$2) -> 1260 | AS6: =SUM(Y6,AP6,AR6,J6)+AD6 -> 1260 | AU6: =SUM(AR6,AD6,Y6,J6) -> 0 | AW6: =SUM($AS6:AS$8) -> 3780 | AX6: =IF(AS6=0,"",SUMIFS($AS6:AS$8, $BH6:BH$8, BH6)) -> 3780 | AZ6: =IF(D6<TODAY(),HYPERLINK(BG6,"LINK"),"") -> LINK | BA6: Mobilising from timber creek to doon doon road house, unload caravans and the road train at the road house, move gear to site, unload lay down at site, site inspections, travel back to doon doon for accommodation. | BB6: https://www.coreplan.io/app/ddh1-drilling/speewah-mining-speewah-fluorite-project-wa/plods/1663- | BC6: =RIGHT(YEAR(D6),2) -> 25 | BD6: =IF(LEN(MONTH(D8))=1,_xlfn.TEXTJOIN(,,"0",MONTH(D8)),MONTH(D8)) -> 07 | BE6: =IF(LEN(DAY(D8))=1,_xlfn.TEXTJOIN(,,"0",DAY(D8)),DAY(D8)) -> 06 | BF6: =LEFT(E6,1) -> D | BG6: =CONCATENATE(BB6,BC6,BD6,BE6,BF6) -> https://www.coreplan.io/app/ddh1-drilling/speewah-mining-speewah-fluorite-project-wa/plods/1663-250706D | BH6: =TEXT(D6, "yyyy-mm") -> 2025-07
A7: =VLOOKUP(F7,'Tenement Lookup'!A:BH,60,FALSE) -> #N/A | B7: =IFERROR(IF(FIND("MET",E7),"MET",IF(FIND("GT",E7),"GT",)),"") | C7: =IFERROR(IF(FIND("MET",F7),"MET",IF(FIND("GT",F7),"GT",)),"") | D7: =45843 -> 45843 | E7: NS 5pm | J7: =IF(ISBLANK(I7),"",I7*$J$2) | M7: =IF(ISBLANK(K7),"",L7-K7) | P7: =IF(ISBLANK(N7),,O7-N7) -> 0 | S7: =IF(ISBLANK(Q7),,R7-Q7) -> 0 | V7: =IF(ISBLANK(T7),,U7-T7) -> 0 | W7: =IFERROR(M7+P7+S7+V7,"") | X7: =IFERROR((M7*$M$2)+(P7*$P$2)+(S7*$S$2)+(V7*$V$2),"") | Y7: =IF(F7<>"",IF(X7<(AE7*$AE$2),(AE7*$AE$2),X7),"") | AE7: 0 | AF7: 0 | AH7: 3.5 | AJ7: Unpacking rig after mobilisation | AK7: 7.5 | AN7: =IF(ISBLANK(AE7),"",SUM(AE7:AF7,AH7:AL7)) -> 11 | AP7: =(AF7*$AF$2)+(AH7*$AH$2)+(AI7*$AI$2) -> 1260 | AS7: =SUM(Y7,AP7,AR7,J7)+AD7 -> 1260 | AU7: =SUM(AR7,AD7,Y7,J7) -> 0 | AW7: =SUM($AS7:AS$8) -> 2520 | AX7: =IF(AS7=0,"",SUMIFS($AS7:AS$8, $BH7:BH$8, BH7)) -> 2520 | AZ7: =IF(D7<TODAY(),HYPERLINK(BG7,"LINK"),"") -> LINK | BA7: Mobilising from timber creek to doon doon road house, unload caravans and the road train at the road house, move gear to site, unload lay down at site, site inspections, travel back to doon doon for accommodation. | BB7: https://www.coreplan.io/app/ddh1-drilling/speewah-mining-speewah-fluorite-project-wa/plods/1663- | BC7: =RIGHT(YEAR(D7),2) -> 25 | BD7: =IF(LEN(MONTH(D9))=1,_xlfn.TEXTJOIN(,,"0",MONTH(D9)),MONTH(D9)) -> 07 | BE7: =IF(LEN(DAY(D9))=1,_xlfn.TEXTJOIN(,,"0",DAY(D9)),DAY(D9)) -> 06 | BF7: =LEFT(E7,1) -> N | BG7: =CONCATENATE(BB7,BC7,BD7,BE7,BF7) -> https://www.coreplan.io/app/ddh1-drilling/speewah-mining-speewah-fluorite-project-wa/plods/1663-250706N | BH7: =TEXT(D7, "yyyy-mm") -> 2025-07
A8: =VLOOKUP(F8,'Tenement Lookup'!A:BH,60,FALSE) -> #N/A | C8: =IFERROR(IF(FIND("MET",F8),"MET",IF(FIND("GT",F8),"GT",)),"") | D8: =45843.21+1 -> 45844.21 | E8: DS 5am | J8: =IF(ISBLANK(I8),"",I8*$J$2) | M8: =IF(ISBLANK(K8),"",L8-K8) | P8: =IF(ISBLANK(N8),,O8-N8) -> 0 | S8: =IF(ISBLANK(Q8),,R8-Q8) -> 0 | V8: =IF(ISBLANK(T8),,U8-T8) -> 0 | W8: =IFERROR(M8+P8+S8+V8,"") | X8: =IFERROR((M8*$M$2)+(P8*$P$2)+(S8*$S$2)+(V8*$V$2),"") | Y8: =IF(F8<>"",IF(X8<(AE8*$AE$2),(AE8*$AE$2),X8),"") | AA8: 1 | AB8: 1 | AE8: 0 | AF8: 0 | AH8: 3.5 | AJ8: Unpacking rig after mobilisation | AK8: 8.5 | AN8: =IF(ISBLANK(AE8),"",SUM(AE8:AF8,AH8:AL8)) -> 12 | AP8: =(AF8*$AF$2)+(AH8*$AH$2)+(AI8*$AI$2) -> 1260 | AS8: =SUM(Y8,AP8,AR8,J8)+AD8 -> 1260 | AT8: 1260 | AU8: =SUM(AR8,AD8,Y8,J8) -> 0 | AW8: =SUM($AS$8:AS8) -> 1260 | AX8: =IF(AS8=0,"",SUMIFS($AS$8:AS8, $BH$8:BH8, BH8)) -> 1260 | AZ8: =IF(D8<TODAY(),HYPERLINK(BG8,"LINK"),"") -> LINK | BA8: Mobilising from timber creek to doon doon road house, unload caravans and the road train at the road house, move gear to site, unload lay down at site, site inspections, travel back to doon doon for accommodation. | BB8: https://www.coreplan.io/app/ddh1-drilling/speewah-mining-speewah-fluorite-project-wa/plods/1663- | BC8: =RIGHT(YEAR(D8),2) -> 25 | BD8: =IF(LEN(MONTH(D10))=1,_xlfn.TEXTJOIN(,,"0",MONTH(D10)),MONTH(D10)) -> 07 | BE8: =IF(LEN(DAY(D10))=1,_xlfn.TEXTJOIN(,,"0",DAY(D10)),DAY(D10)) -> 07 | BF8: =LEFT(E8,1) -> D | BG8: =CONCATENATE(BB8,BC8,BD8,BE8,BF8) -> https://www.coreplan.io/app/ddh1-drilling/speewah-mining-speewah-fluorite-project-wa/plods/1663-250707D | BH8: =TEXT(D8, "yyyy-mm") -> 2025-07 | BJ8: MET | BK8: GT | BM8: {=_xlfn.UNIQUE(_xlfn._xlws.FILTER(C6:C100, C6:C100<>""))} -> MET | BN8: {=_xlfn.LET( _xlpm.idx, I6, _xlpm.rowMatch, C6:C100 = _xlpm.idx, _xlpm.dTexts, _xlfn._xlws.FILTER(F6:F100, _xlpm.rowMatch), _xlpm.eTexts, _xlfn._xlws.FILTER(G6:G100, _xlpm.rowMatch), _xlpm.combined, _xlfn.VSTACK(_xlpm.dTexts, _xlpm.eTexts), _xlpm.validTexts, _xlfn._xlws.FILTER(_xlpm.combined, ISTEXT(_xlpm.combined)), COUNTA(_xlfn.UNIQUE(_xlpm.validTexts)) )} -> 1
A9: =VLOOKUP(F9,'Tenement Lookup'!A:BH,60,FALSE) -> #N/A | C9: =IFERROR(IF(FIND("MET",F9),"MET",IF(FIND("GT",F9),"GT",)),"") | D9: =45843.71+1 -> 45844.71 | E9: NS 5pm | J9: =IF(ISBLANK(I9),"",I9*$J$2) | M9: =IF(ISBLANK(K9),"",L9-K9) | P9: =IF(ISBLANK(N9),,O9-N9) -> 0 | S9: =IF(ISBLANK(Q9),,R9-Q9) -> 0 | V9: =IF(ISBLANK(T9),,U9-T9) -> 0 | W9: =IFERROR(M9+P9+S9+V9,"") | X9: =IFERROR((M9*$M$2)+(P9*$P$2)+(S9*$S$2)+(V9*$V$2),"") | Y9: =IF(F9<>"",IF(X9<(AE9*$AE$2),(AE9*$AE$2),X9),"") | AN9: =IF(ISBLANK(AE9),"",SUM(AE9:AF9,AH9:AL9)) | AP9: =(AF9*$AF$2)+(AH9*$AH$2)+(AI9*$AI$2) -> 0 | AS9: =SUM(Y9,AP9,AR9,J9)+AD9 -> 0 | AT9: 0 | AU9: =SUM(AR9,AD9,Y9,J9) -> 0 | AW9: =SUM($AS$8:AS9) -> 1260 | AX9: =IF(AS9=0,"",SUMIFS($AS$8:AS9, $BH$8:BH9, BH9)) | AY9: =IF(AND(D9>TODAY(),ISBLANK(H9)),"",IF(ISBLANK(AE9),"no drilling completed",AS9/(W9))) -> no drilling completed | AZ9: =IF(D9<TODAY(),HYPERLINK(BG9,"LINK"),"") -> LINK | BA9: No NS | BB9: https://www.coreplan.io/app/ddh1-drilling/speewah-mining-speewah-fluorite-project-wa/plods/1663- | BC9: =RIGHT(YEAR(D9),2) -> 25 | BD9: =IF(LEN(MONTH(D11))=1,_xlfn.TEXTJOIN(,,"0",MONTH(D11)),MONTH(D11)) -> 07 | BE9: =IF(LEN(DAY(D11))=1,_xlfn.TEXTJOIN(,,"0",DAY(D11)),DAY(D11)) -> 07 | BF9: =LEFT(E9,1) -> N | BG9: =CONCATENATE(BB9,BC9,BD9,BE9,BF9) -> https://www.coreplan.io/app/ddh1-drilling/speewah-mining-speewah-fluorite-project-wa/plods/1663-250707N | BH9: =TEXT(D9, "yyyy-mm") -> 2025-07 | BJ9: =AVERAGEIF(C:C,"MET",AY:AY) -> 396.73876 | BK9: =AVERAGEIF(C:C,"GT",AY:AY) -> 426.62994 | BM9: GT | BN9: {=_xlfn.LET( _xlpm.idx, I7, _xlpm.rowMatch, C7:C101 = _xlpm.idx, _xlpm.dTexts, _xlfn._xlws.FILTER(F7:F101, _xlpm.rowMatch), _xlpm.eTexts, _xlfn._xlws.FILTER(G7:G101, _xlpm.rowMatch), _xlpm.combined, _xlfn.VSTACK(_xlpm.dTexts, _xlpm.eTexts), _xlpm.validTexts, _xlfn._xlws.FILTER(_xlpm.combined, ISTEXT(_xlpm.combined)), COUNTA(_xlfn.UNIQUE(_xlpm.validTexts)) )} -> 1
A10: =VLOOKUP(F10,'Tenement Lookup'!A:BH,60,FALSE) -> M 80/269 | B10: =VLOOKUP(F10,Purpose!$A$2:$B$334,2,FALSE) -> Met | C10: MET | D10: =D8+1 -> 45845.21 | E10: DS 5am | F10: SF25_DMET023 | H10: Melville, Dean | I10: 6 | J10: =IF(ISBLANK(I10),"",I10*$J$2) -> 780 | K10: 0 | L10: 0 | M10: =IF(ISBLANK(K10),"",L10-K10) -> 0 | P10: =IF(ISBLANK(N10),,O10-N10) -> 0 | S10: =IF(ISBLANK(Q10),,R10-Q10) -> 0 | V10: =IF(ISBLANK(T10),,U10-T10) -> 0 | W10: =IFERROR(M10+P10+S10+V10,"") -> 0 | X10: =IFERROR((M10*$M$2)+(P10*$P$2)+(S10*$S$2)+(V10*$V$2),"") -> 0 | Y10: =IF(F10<>"",IF(X10<(AE10*$AE$2),(AE10*$AE$2),X10),"") -> 0 | AA10: 1 | AB10: 1 | AC10: 13170 | AD10: =SUMPRODUCT(Z10:AB10,$Z$2:$AB$2) -> 575 | AE10: 0 | AF10: 8.25 | AH10: 2 | AK10: 1.75 | AN10: =IF(ISBLANK(AE10),"",SUM(AE10:AF10,AH10:AL10)) -> 12 | AP10: =(AF10*$AF$2)+(AH10*$AH$2)+(AI10*$AI$2) -> 4515 | AR10: 761 | AS10: =SUM(Y10,AP10,AR10,J10)+AD10 -> 6631 | AT10: 6631 | AU10: =SUM(AR10,AD10,Y10,J10) -> 2116 | AV10: =IFERROR((AS10-AU10)/AS10,"") -> 0.68089278 | AW10: =SUM($AS$8:AS10) -> 7891 | AX10: =IF(AS10=0,"",SUMIFS($AS$8:AS10, $BH$8:BH10, BH10)) -> 7891 | AZ10: =IF(D10<TODAY(),HYPERLINK(BG10,"LINK"),"") -> LINK | BA10: travel to site from doon doon, unload trucks at laydown, brad meikle/ carl jonas travel to kununurra to pick up bed vans, pack gear for rig, move rig and gear onto drill pad, set up rig on azi, mast shot survey, start setting up drill site, run poly to drill pad, start filling sumps. | BB10: https://www.coreplan.io/app/ddh1-drilling/speewah-mining-speewah-fluorite-project-wa/plods/1663- | BC10: =RIGHT(YEAR(D10),2) -> 25 | BD10: =IF(LEN(MONTH(D12))=1,_xlfn.TEXTJOIN(,,"0",MONTH(D12)),MONTH(D12)) -> 07 | BE10: =IF(LEN(DAY(D12))=1,_xlfn.TEXTJOIN(,,"0",DAY(D12)),DAY(D12)) -> 08 | BF10: =LEFT(E10,1) -> D | BG10: =CONCATENATE(BB10,BC10,BD10,BE10,BF10) -> https://www.coreplan.io/app/ddh1-drilling/speewah-mining-speewah-fluorite-project-wa/plods/1663-250708D | BH10: =TEXT(D10, "yyyy-mm") -> 2025-07 | BM10: DDRD | BN10: {=_xlfn.LET( _xlpm.idx, I8, _xlpm.rowMatch, C8:C102 = _xlpm.idx, _xlpm.dTexts, _xlfn._xlws.FILTER(F8:F102, _xlpm.rowMatch), _xlpm.eTexts, _xlfn._xlws.FILTER(G8:G102, _xlpm.rowMatch), _xlpm.combined, _xlfn.VSTACK(_xlpm.dTexts, _xlpm.eTexts), _xlpm.validTexts, _xlfn._xlws.FILTER(_xlpm.combined, ISTEXT(_xlpm.combined)), COUNTA(_xlfn.UNIQUE(_xlpm.validTexts)) )} -> 1
A11: =VLOOKUP(F11,'Tenement Lookup'!A:BH,60,FALSE) -> #N/A | D11: =D9+1 -> 45845.71 | E11: NS 5pm | J11: =IF(ISBLANK(I11),"",I11*$J$2) | M11: =IF(ISBLANK(K11),"",L11-K11) | P11: =IF(ISBLANK(N11),,O11-N11) -> 0 | S11: =IF(ISBLANK(Q11),,R11-Q11) -> 0 | V11: =IF(ISBLANK(T11),,U11-T11) -> 0 | W11: =IFERROR(M11+P11+S11+V11,"") | X11: =IFERROR((M11*$M$2)+(P11*$P$2)+(S11*$S$2)+(V11*$V$2),"") | Y11: =IF(F11<>"",IF(X11<(AE11*$AE$2),(AE11*$AE$2),X11),"") | AD11: =SUMPRODUCT(Z11:AB11,$Z$2:$AB$2) -> 0 | AN11: =IF(ISBLANK(AE11),"",SUM(AE11:AF11,AH11:AL11)) | AP11: =(AF11*$AF$2)+(AH11*$AH$2)+(AI11*$AI$2) -> 0 | AS11: =SUM(Y11,AP11,AR11,J11)+AD11 -> 0 | AT11: 0 | AU11: =SUM(AR11,AD11,Y11,J11) -> 0 | AV11: =IFERROR((AS11-AU11)/AS11,"") | AW11: =SUM($AS$8:AS11) -> 7891 | AX11: =IF(AS11=0,"",SUMIFS($AS$8:AS11, $BH$8:BH11, BH11)) | AY11: =IF(AND(D11>TODAY(),ISBLANK(H11)),"",IF(ISBLANK(AE11),"no drilling completed",AS11/(W11))) -> no drilling completed | AZ11: =IF(D11<TODAY(),HYPERLINK(BG11,"LINK"),"") -> LINK | BB11: https://www.coreplan.io/app/ddh1-drilling/speewah-mining-speewah-fluorite-project-wa/plods/1663- | BC11: =RIGHT(YEAR(D11),2) -> 25 | BD11: =IF(LEN(MONTH(D13))=1,_xlfn.TEXTJOIN(,,"0",MONTH(D13)),MONTH(D13)) -> 07 | BE11: =IF(LEN(DAY(D13))=1,_xlfn.TEXTJOIN(,,"0",DAY(D13)),DAY(D13)) -> 08 | BF11: =LEFT(E11,1) -> N | BG11: =CONCATENATE(BB11,BC11,BD11,BE11,BF11) -> https://www.coreplan.io/app/ddh1-drilling/speewah-mining-speewah-fluorite-project-wa/plods/1663-250708N | BH11: =TEXT(D11, "yyyy-mm") -> 2025-07
A12: =VLOOKUP(F12,'Tenement Lookup'!A:BH,60,FALSE) -> M 80/269 | B12: =VLOOKUP(F12,Purpose!$A$2:$B$334,2,FALSE) -> Met | C12: MET | D12: =D10+1 -> 45846.21 | E12: DS 5am | F12: SF25_DMET023 | H12: Melville, Dean | I12: 3 | J12: =IF(ISBLANK(I12),"",I12*$J$2) -> 390 | K12: 0 | L12: 11 | M12: =IF(ISBLANK(K12),"",L12-K12) -> 11 | P12: =IF(ISBLANK(N12),,O12-N12) -> 0 | S12: =IF(ISBLANK(Q12),,R12-Q12) -> 0 | V12: =IF(ISBLANK(T12),,U12-T12) -> 0 | W12: =IFERROR(M12+P12+S12+V12,"") -> 11 | X12: =IFERROR((M12*$M$2)+(P12*$P$2)+(S12*$S$2)+(V12*$V$2),"") -> 1925 | Y12: =IF(F12<>"",IF(X12<(AE12*$AE$2),(AE12*$AE$2),X12),"") -> 1955 | AA12: 1 | AB12: 1 | AC12: 13170 | AD12: =SUMPRODUCT(Z12:AB12,$Z$2:$AB$2) -> 575 | AE12: 4.25 | AF12: 7 | AH12: 0.75 | AN12: =IF(ISBLANK(AE12),"",SUM(AE12:AF12,AH12:AL12)) -> 12 | AP12: =(AF12*$AF$2)+(AH12*$AH$2)+(AI12*$AI$2) -> 3490 | AR12: =1076.34-390 -> 686.34 | AS12: =SUM(Y12,AP12,AR12,J12)+AD12 -> 7096.34 | AT12: 7096.34 | AU12: =SUM(AR12,AD12,Y12,J12) -> 3606.34 | AV12: =IFERROR((AS12-AU12)/AS12,"") -> 0.49180282 | AW12: =SUM($AS$8:AS12) -> 14987.34 | AX12: =IF(AS12=0,"",SUMIFS($AS$8:AS12, $BH$8:BH12, BH12)) -> 14987.34 | AY12: =IF(AND(D12>TODAY(),ISBLANK(H12)),"",IF(ISBLANK(AE12),"no drilling completed",AS12/(W12))) -> 645.12182 | AZ12: =IF(D12<TODAY(),HYPERLINK(BG12,"LINK"),"") -> LINK | BB12: https://www.coreplan.io/app/ddh1-drilling/speewah-mining-speewah-fluorite-project-wa/plods/1663- | BC12: =RIGHT(YEAR(D12),2) -> 25 | BD12: =IF(LEN(MONTH(D14))=1,_xlfn.TEXTJOIN(,,"0",MONTH(D14)),MONTH(D14)) -> 07 | BE12: =IF(LEN(DAY(D14))=1,_xlfn.TEXTJOIN(,,"0",DAY(D14)),DAY(D14)) -> 09 | BF12: =LEFT(E12,1) -> D | BG12: =CONCATENATE(BB12,BC12,BD12,BE12,BF12) -> https://www.coreplan.io/app/ddh1-drilling/speewah-mining-speewah-fluorite-project-wa/plods/1663-250709D | BH12: =TEXT(D12, "yyyy-mm") -> 2025-07
A13: =VLOOKUP(F13,'Tenement Lookup'!A:BH,60,FALSE) -> M 80/269 | B13: =VLOOKUP(F13,Purpose!$A$2:$B$334,2,FALSE) -> Met | C13: MET | D13: =D11+1 -> 45846.71 | E13: NS 5pm | F13: SF25_DMET023 | H13: Zeke Shackelton | I13: 3 | J13: =IF(ISBLANK(I13),"",I13*$J$2) -> 390 | K13: 11 | L13: 26.6 | M13: =IF(ISBLANK(K13),"",L13-K13) -> 15.6 | P13: =IF(ISBLANK(N13),,O13-N13) -> 0 | S13: =IF(ISBLANK(Q13),,R13-Q13) -> 0 | V13: =IF(ISBLANK(T13),,U13-T13) -> 0 | W13: =IFERROR(M13+P13+S13+V13,"") -> 15.6 | X13: =IFERROR((M13*$M$2)+(P13*$P$2)+(S13*$S$2)+(V13*$V$2),"") -> 2730 | Y13: =IF(F13<>"",IF(X13<(AE13*$AE$2),(AE13*$AE$2),X13),"") -> 3335 | AD13: =SUMPRODUCT(Z13:AB13,$Z$2:$AB$2) -> 0 | AE13: 7.25 | AF13: 1.5 | AH13: 0.25 | AK13: 3 | AN13: =IF(ISBLANK(AE13),"",SUM(AE13:AF13,AH13:AL13)) -> 12 | AP13: =(AF13*$AF$2)+(AH13*$AH$2)+(AI13*$AI$2) -> 780 | AR13: 117.93 | AS13: =SUM(Y13,AP13,AR13,J13)+AD13 -> 4622.93 | AT13: 4622.93 | AU13: =SUM(AR13,AD13,Y13,J13) -> 3842.93 | AV13: =IFERROR((AS13-AU13)/AS13,"") -> 0.16872416 | AW13: =SUM($AS$8:AS13) -> 19610.27 | AX13: =IF(AS13=0,"",SUMIFS($AS$8:AS13, $BH$8:BH13, BH13)) -> 19610.27 | AY13: =IF(AND(D13>TODAY(),ISBLANK(H13)),"",IF(ISBLANK(AE13),"no drilling completed",AS13/(W13))) -> 296.34167 | AZ13: =IF(D13<TODAY(),HYPERLINK(BG13,"LINK"),"") -> LINK | BB13: https://www.coreplan.io/app/ddh1-drilling/speewah-mining-speewah-fluorite-project-wa/plods/1663- | BC13: =RIGHT(YEAR(D13),2) -> 25 | BD13: =IF(LEN(MONTH(D15))=1,_xlfn.TEXTJOIN(,,"0",MONTH(D15)),MONTH(D15)) -> 07 | BE13: =IF(LEN(DAY(D15))=1,_xlfn.TEXTJOIN(,,"0",DAY(D15)),DAY(D15)) -> 09 | BF13: =LEFT(E13,1) -> N | BG13: =CONCATENATE(BB13,BC13,BD13,BE13,BF13) -> https://www.coreplan.io/app/ddh1-drilling/speewah-mining-speewah-fluorite-project-wa/plods/1663-250709N | BH13: =TEXT(D13, "yyyy-mm") -> 2025-07
A14: =VLOOKUP(F14,'Tenement Lookup'!A:BH,60,FALSE) -> M 80/269 | B14: =VLOOKUP(F14,Purpose!$A$2:$B$334,2,FALSE) -> Met | C14: MET | D14: =D12+1 -> 45847.21 | E14: DS 5am | F14: SF25_DMET023 | H14: Matthew Sing | I14: 3 | J14: =IF(ISBLANK(I14),"",I14*$J$2) -> 390 | K14: 26.6 | L14: 33.7 | M14: =IF(ISBLANK(K14),"",L14-K14) -> 7.1 | P14: =IF(ISBLANK(N14),,O14-N14) -> 0 | S14: =IF(ISBLANK(Q14),,R14-Q14) -> 0 | V14: =IF(ISBLANK(T14),,U14-T14) -> 0 | W14: =IFERROR(M14+P14+S14+V14,"") -> 7.1 | X14: =IFERROR((M14*$M$2)+(P14*$P$2)+(S14*$S$2)+(V14*$V$2),"") -> 1242.5 | Y14: =IF(F14<>"",IF(X14<(AE14*$AE$2),(AE14*$AE$2),X14),"") -> 1380 | AA14: 1 | AB14: 1 | AC14: 13170 | AD14: =SUMPRODUCT(Z14:AB14,$Z$2:$AB$2) -> 575 | AE14: 3 | AF14: 0.25 | AH14: 0.25 | AK14: 8.5 | AN14: =IF(ISBLANK(AE14),"",SUM(AE14:AF14,AH14:AL14)) -> 12 | AP14: =(AF14*$AF$2)+(AH14*$AH$2)+(AI14*$AI$2) -> 205 | AR14: 0 | AS14: =SUM(Y14,AP14,AR14,J14)+AD14 -> 2550 | AT14: 2550 | AU14: =SUM(AR14,AD14,Y14,J14) -> 2345 | AV14: =IFERROR((AS14-AU14)/AS14,"") -> 0.080392157 | AW14: =SUM($AS$8:AS14) -> 22160.27 | AX14: =IF(AS14=0,"",SUMIFS($AS$8:AS14, $BH$8:BH14, BH14)) -> 22160.27 | AY14: =IF(AND(D14>TODAY(),ISBLANK(H14)),"",IF(ISBLANK(AE14),"no drilling completed",AS14/(W14))) -> 359.15493 | AZ14: =IF(D14<TODAY(),HYPERLINK(BG14,"LINK"),"") -> LINK | BA14: Crew change, Pre-shift meeting, Pre-start all equipment, continue to dill PQ3 through broken ground, condition hole | BB14: https://www.coreplan.io/app/ddh1-drilling/speewah-mining-speewah-fluorite-project-wa/plods/1663- | BC14: =RIGHT(YEAR(D14),2) -> 25 | BD14: =IF(LEN(MONTH(D16))=1,_xlfn.TEXTJOIN(,,"0",MONTH(D16)),MONTH(D16)) -> 07 | BE14: =IF(LEN(DAY(D16))=1,_xlfn.TEXTJOIN(,,"0",DAY(D16)),DAY(D16)) -> 10 | BF14: =LEFT(E14,1) -> D | BG14: =CONCATENATE(BB14,BC14,BD14,BE14,BF14) -> https://www.coreplan.io/app/ddh1-drilling/speewah-mining-speewah-fluorite-project-wa/plods/1663-250710D | BH14: =TEXT(D14, "yyyy-mm") -> 2025-07
A15: =VLOOKUP(F15,'Tenement Lookup'!A:BH,60,FALSE) -> M 80/269 | B15: =VLOOKUP(F15,Purpose!$A$2:$B$334,2,FALSE) -> Met | C15: MET | D15: =D13+1 -> 45847.71 | E15: NS 5pm | F15: SF25_DMET023 | H15: Ben Payton | I15: 3 | J15: =IF(ISBLANK(I15),"",I15*$J$2) -> 390 | K15: 33.7 | L15: 63.7 | M15: =IF(ISBLANK(K15),"",L15-K15) -> 30 | P15: =IF(ISBLANK(N15),,O15-N15) -> 0 | S15: =IF(ISBLANK(Q15),,R15-Q15) -> 0 | V15: =IF(ISBLANK(T15),,U15-T15) -> 0 | W15: =IFERROR(M15+P15+S15+V15,"") -> 30 | X15: =IFERROR((M15*$M$2)+(P15*$P$2)+(S15*$S$2)+(V15*$V$2),"") -> 5250 | Y15: =IF(F15<>"",IF(X15<(AE15*$AE$2),(AE15*$AE$2),X15),"") -> 5250 | AD15: =SUMPRODUCT(Z15:AB15,$Z$2:$AB$2) -> 0 | AE15: 10.75 | AF15: 0.75 | AH15: 0.5 | AN15: =IF(ISBLANK(AE15),"",SUM(AE15:AF15,AH15:AL15)) -> 12 | AP15: =(AF15*$AF$2)+(AH15*$AH$2)+(AI15*$AI$2) -> 525 | AR15: 117.93 | AS15: =SUM(Y15,AP15,AR15,J15)+AD15 -> 6282.93 | AT15: 6282.93 | AU15: =SUM(AR15,AD15,Y15,J15) -> 5757.93 | AV15: =IFERROR((AS15-AU15)/AS15,"") -> 0.08355974 | AW15: =SUM($AS$8:AS15) -> 28443.2 | AX15: =IF(AS15=0,"",SUMIFS($AS$8:AS15, $BH$8:BH15, BH15)) -> 28443.2 | AY15: =IF(AND(D15>TODAY(),ISBLANK(H15)),"",IF(ISBLANK(AE15),"no drilling completed",AS15/(W15))) -> 209.431 | AZ15: =IF(D15<TODAY(),HYPERLINK(BG15,"LINK"),"") -> LINK | BB15: https://www.coreplan.io/app/ddh1-drilling/speewah-mining-speewah-fluorite-project-wa/plods/1663- | BC15: =RIGHT(YEAR(D15),2) -> 25 | BD15: =IF(LEN(MONTH(D17))=1,_xlfn.TEXTJOIN(,,"0",MONTH(D17)),MONTH(D17)) -> 07 | BE15: =IF(LEN(DAY(D17))=1,_xlfn.TEXTJOIN(,,"0",DAY(D17)),DAY(D17)) -> 10 | BF15: =LEFT(E15,1) -> N | BG15: =CONCATENATE(BB15,BC15,BD15,BE15,BF15) -> https://www.coreplan.io/app/ddh1-drilling/speewah-mining-speewah-fluorite-project-wa/plods/1663-250710N | BH15: =TEXT(D15, "yyyy-mm") -> 2025-07
A16: =VLOOKUP(F16,'Tenement Lookup'!A:BH,60,FALSE) -> M 80/269 | B16: =VLOOKUP(F16,Purpose!$A$2:$B$334,2,FALSE) -> Met | C16: MET | D16: =D14+1 -> 45848.21 | E16: DS 5am | F16: SF25_DMET023 | H16: Matthew Sing | I16: 3 | J16: =IF(ISBLANK(I16),"",I16*$J$2) -> 390 | K16: 63.7 | L16: 84.1 | M16: =IF(ISBLANK(K16),"",L16-K16) -> 20.4 | P16: =IF(ISBLANK(N16),,O16-N16) -> 0 | S16: =IF(ISBLANK(Q16),,R16-Q16) -> 0 | V16: =IF(ISBLANK(T16),,U16-T16) -> 0 | W16: =IFERROR(M16+P16+S16+V16,"") -> 20.4 | X16: =IFERROR((M16*$M$2)+(P16*$P$2)+(S16*$S$2)+(V16*$V$2),"") -> 3570 | Y16: =IF(F16<>"",IF(X16<(AE16*$AE$2),(AE16*$AE$2),X16),"") -> 5060 | AA16: 1 | AB16: 1 | AC16: 13170 | AD16: =SUMPRODUCT(Z16:AB16,$Z$2:$AB$2) -> 575 | AE16: 11 | AF16: 0.5 | AH16: 0.5 | AN16: =IF(ISBLANK(AE16),"",SUM(AE16:AF16,AH16:AL16)) -> 12 | AP16: =(AF16*$AF$2)+(AH16*$AH$2)+(AI16*$AI$2) -> 410 | AR16: =817.99-390 -> 427.99 | AS16: =SUM(Y16,AP16,AR16,J16)+AD16 -> 6862.99 | AT16: 6862.99 | AU16: =SUM(AR16,AD16,Y16,J16) -> 6452.99 | AV16: =IFERROR((AS16-AU16)/AS16,"") -> 0.059740725 | AW16: =SUM($AS$8:AS16) -> 35306.19 | AX16: =IF(AS16=0,"",SUMIFS($AS$8:AS16, $BH$8:BH16, BH16)) -> 35306.19 | AY16: =IF(AND(D16>TODAY(),ISBLANK(H16)),"",IF(ISBLANK(AE16),"no drilling completed",AS16/(W16))) -> 336.42108 | AZ16: =IF(D16<TODAY(),HYPERLINK(BG16,"LINK"),"") -> LINK | BB16: https://www.coreplan.io/app/ddh1-drilling/speewah-mining-speewah-fluorite-project-wa/plods/1663- | BC16: =RIGHT(YEAR(D16),2) -> 25 | BD16: =IF(LEN(MONTH(D18))=1,_xlfn.TEXTJOIN(,,"0",MONTH(D18)),MONTH(D18)) -> 07 | BE16: =IF(LEN(DAY(D18))=1,_xlfn.TEXTJOIN(,,"0",DAY(D18)),DAY(D18)) -> 11 | BF16: =LEFT(E16,1) -> D | BG16: =CONCATENATE(BB16,BC16,BD16,BE16,BF16) -> https://www.coreplan.io/app/ddh1-drilling/speewah-mining-speewah-fluorite-project-wa/plods/1663-250711D | BH16: =TEXT(D16, "yyyy-mm") -> 2025-07
A17: =VLOOKUP(F17,'Tenement Lookup'!A:BH,60,FALSE) -> M 80/269 | B17: =VLOOKUP(F17,Purpose!$A$2:$B$334,2,FALSE) -> Met | C17: MET | D17: =D15+1 -> 45848.71 | E17: NS 5pm | F17: SF25_DMET023 | H17: Ben Payton | I17: 3 | J17: =IF(ISBLANK(I17),"",I17*$J$2) -> 390 | K17: 84.1 | L17: 99.7 | M17: =IF(ISBLANK(K17),"",L17-K17) -> 15.6 | P17: =IF(ISBLANK(N17),,O17-N17) -> 0 | S17: =IF(ISBLANK(Q17),,R17-Q17) -> 0 | V17: =IF(ISBLANK(T17),,U17-T17) -> 0 | W17: =IFERROR(M17+P17+S17+V17,"") -> 15.6 | X17: =IFERROR((M17*$M$2)+(P17*$P$2)+(S17*$S$2)+(V17*$V$2),"") -> 2730 | Y17: =IF(F17<>"",IF(X17<(AE17*$AE$2),(AE17*$AE$2),X17),"") -> 3105 | AD17: =SUMPRODUCT(Z17:AB17,$Z$2:$AB$2) -> 0 | AE17: 6.75 | AF17: 4.75 | AG17: Change bit - dropped PVC casing down hole. | AH17: 0.5 | AN17: =IF(ISBLANK(AE17),"",SUM(AE17:AF17,AH17:AL17)) -> 12 | AP17: =(AF17*$AF$2)+(AH17*$AH$2)+(AI17*$AI$2) -> 2365 | AR17: =1166.68-390 -> 776.68 | AS17: =SUM(Y17,AP17,AR17,J17)+AD17 -> 6636.68 | AT17: 6636.68 | AU17: =SUM(AR17,AD17,Y17,J17) -> 4271.68 | AV17: =IFERROR((AS17-AU17)/AS17,"") -> 0.35635288 | AW17: =SUM($AS$8:AS17) -> 41942.87 | AX17: =IF(AS17=0,"",SUMIFS($AS$8:AS17, $BH$8:BH17, BH17)) -> 41942.87 | AY17: =IF(AND(D17>TODAY(),ISBLANK(H17)),"",IF(ISBLANK(AE17),"no drilling completed",AS17/(W17))) -> 425.42821 | AZ17: =IF(D17<TODAY(),HYPERLINK(BG17,"LINK"),"") -> LINK | BB17: https://www.coreplan.io/app/ddh1-drilling/speewah-mining-speewah-fluorite-project-wa/plods/1663- | BC17: =RIGHT(YEAR(D17),2) -> 25 | BD17: =IF(LEN(MONTH(D19))=1,_xlfn.TEXTJOIN(,,"0",MONTH(D19)),MONTH(D19)) -> 07 | BE17: =IF(LEN(DAY(D19))=1,_xlfn.TEXTJOIN(,,"0",DAY(D19)),DAY(D19)) -> 11 | BF17: =LEFT(E17,1) -> N | BG17: =CONCATENATE(BB17,BC17,BD17,BE17,BF17) -> https://www.coreplan.io/app/ddh1-drilling/speewah-mining-speewah-fluorite-project-wa/plods/1663-250711N | BH17: =TEXT(D17, "yyyy-mm") -> 2025-07
A18: =VLOOKUP(F18,'Tenement Lookup'!A:BH,60,FALSE) -> M 80/269 | B18: =VLOOKUP(F18,Purpose!$A$2:$B$334,2,FALSE) -> Met | C18: MET | D18: =D16+1 -> 45849.21 | E18: DS 5am | F18: SF25_DMET023 | H18: Matthew Sing | I18: 3 | J18: =IF(ISBLANK(I18),"",I18*$J$2) -> 390 | K18: 99.7 | L18: 118.7 | M18: =IF(ISBLANK(K18),"",L18-K18) -> 19 | P18: =IF(ISBLANK(N18),,O18-N18) -> 0 | S18: =IF(ISBLANK(Q18),,R18-Q18) -> 0 | V18: =IF(ISBLANK(T18),,U18-T18) -> 0 | W18: =IFERROR(M18+P18+S18+V18,"") -> 19 | X18: =IFERROR((M18*$M$2)+(P18*$P$2)+(S18*$S$2)+(V18*$V$2),"") -> 3325 | Y18: =IF(F18<>"",IF(X18<(AE18*$AE$2),(AE18*$AE$2),X18),"") -> 3910 | AA18: 1 | AB18: 1 | AC18: 13170 | AD18: =SUMPRODUCT(Z18:AB18,$Z$2:$AB$2) -> 575 | AE18: 8.5 | AF18: 3 | AG18: Move hole | AH18: 0.5 | AN18: =IF(ISBLANK(AE18),"",SUM(AE18:AF18,AH18:AL18)) -> 12 | AP18: =(AF18*$AF$2)+(AH18*$AH$2)+(AI18*$AI$2) -> 1560 | AS18: =SUM(Y18,AP18,AR18,J18)+AD18 -> 6435 | AT18: 6435 | AU18: =SUM(AR18,AD18,Y18,J18) -> 4875 | AV18: =IFERROR((AS18-AU18)/AS18,"") -> 0.24242424 | AW18: =SUM($AS$8:AS18) -> 48377.87 | AX18: =IF(AS18=0,"",SUMIFS($AS$8:AS18, $BH$8:BH18, BH18)) -> 48377.87 | AY18: =IF(AND(D18>TODAY(),ISBLANK(H18)),"",IF(ISBLANK(AE18),"no drilling completed",AS18/(W18))) -> 338.68421 | AZ18: =IF(D18<TODAY(),HYPERLINK(BG18,"LINK"),"") -> LINK | BB18: https://www.coreplan.io/app/ddh1-drilling/speewah-mining-speewah-fluorite-project-wa/plods/1663- | BC18: =RIGHT(YEAR(D18),2) -> 25 | BD18: =IF(LEN(MONTH(D20))=1,_xlfn.TEXTJOIN(,,"0",MONTH(D20)),MONTH(D20)) -> 07 | BE18: =IF(LEN(DAY(D20))=1,_xlfn.TEXTJOIN(,,"0",DAY(D20)),DAY(D20)) -> 12 | BF18: =LEFT(E18,1) -> D | BG18: =CONCATENATE(BB18,BC18,BD18,BE18,BF18) -> https://www.coreplan.io/app/ddh1-drilling/speewah-mining-speewah-fluorite-project-wa/plods/1663-250712D | BH18: =TEXT(D18, "yyyy-mm") -> 2025-07
A19: =VLOOKUP(F19,'Tenement Lookup'!A:BH,60,FALSE) -> M 80/269 | B19: =VLOOKUP(F19,Purpose!$A$2:$B$334,2,FALSE) -> Met | C19: MET | D19: =D17+1 -> 45849.71 | E19: NS 5pm | F19: SF25_DMET022 | H19: Ben Payton | I19: 3 | J19: =IF(ISBLANK(I19),"",I19*$J$2) -> 390 | K19: 0 | L19: 16.5 | M19: =IF(ISBLANK(K19),"",L19-K19) -> 16.5 | P19: =IF(ISBLANK(N19),,O19-N19) -> 0 | S19: =IF(ISBLANK(Q19),,R19-Q19) -> 0 | V19: =IF(ISBLANK(T19),,U19-T19) -> 0 | W19: =IFERROR(M19+P19+S19+V19,"") -> 16.5 | X19: =IFERROR((M19*$M$2)+(P19*$P$2)+(S19*$S$2)+(V19*$V$2),"") -> 2887.5 | Y19: =IF(F19<>"",IF(X19<(AE19*$AE$2),(AE19*$AE$2),X19),"") -> 3335 | AD19: =SUMPRODUCT(Z19:AB19,$Z$2:$AB$2) -> 0 | AE19: 7.25 | AF19: 4.25 | AG19: Setting up pad | AH19: 0.5 | AN19: =IF(ISBLANK(AE19),"",SUM(AE19:AF19,AH19:AL19)) -> 12 | AP19: =(AF19*$AF$2)+(AH19*$AH$2)+(AI19*$AI$2) -> 2135 | AR19: =786.12-390 -> 396.12 | AS19: =SUM(Y19,AP19,AR19,J19)+AD19 -> 6256.12 | AT19: 6256.12 | AU19: =SUM(AR19,AD19,Y19,J19) -> 4121.12 | AV19: =IFERROR((AS19-AU19)/AS19,"") -> 0.34126583 | AW19: =SUM($AS$8:AS19) -> 54633.99 | AX19: =IF(AS19=0,"",SUMIFS($AS$8:AS19, $BH$8:BH19, BH19)) -> 54633.99 | AY19: =IF(AND(D19>TODAY(),ISBLANK(H19)),"",IF(ISBLANK(AE19),"no drilling completed",AS19/(W19))) -> 379.15879 | AZ19: =IF(D19<TODAY(),HYPERLINK(BG19,"LINK"),"") -> LINK | BB19: https://www.coreplan.io/app/ddh1-drilling/speewah-mining-speewah-fluorite-project-wa/plods/1663- | BC19: =RIGHT(YEAR(D19),2) -> 25 | BD19: =IF(LEN(MONTH(D21))=1,_xlfn.TEXTJOIN(,,"0",MONTH(D21)),MONTH(D21)) -> 07 | BE19: =IF(LEN(DAY(D21))=1,_xlfn.TEXTJOIN(,,"0",DAY(D21)),DAY(D21)) -> 12 | BF19: =LEFT(E19,1) -> N | BG19: =CONCATENATE(BB19,BC19,BD19,BE19,BF19) -> https://www.coreplan.io/app/ddh1-drilling/speewah-mining-speewah-fluorite-project-wa/plods/1663-250712N | BH19: =TEXT(D19, "yyyy-mm") -> 2025-07
A20: =VLOOKUP(F20,'Tenement Lookup'!A:BH,60,FALSE) -> M 80/269 | B20: =VLOOKUP(F20,Purpose!$A$2:$B$334,2,FALSE) -> Met | C20: MET | D20: =D18+1 -> 45850.21 | E20: DS 5am | F20: SF25_DMET022 | H20: Matthew Sing | I20: 3 | J20: =IF(ISBLANK(I20),"",I20*$J$2) -> 390 | K20: 16.5 | L20: 39.4 | M20: =IF(ISBLANK(K20),"",L20-K20) -> 22.9 | P20: =IF(ISBLANK(N20),,O20-N20) -> 0 | S20: =IF(ISBLANK(Q20),,R20-Q20) -> 0 | V20: =IF(ISBLANK(T20),,U20-T20) -> 0 | W20: =IFERROR(M20+P20+S20+V20,"") -> 22.9 | X20: =IFERROR((M20*$M$2)+(P20*$P$2)+(S20*$S$2)+(V20*$V$2),"") -> 4007.5 | Y20: =IF(F20<>"",IF(X20<(AE20*$AE$2),(AE20*$AE$2),X20),"") -> 4945 | AA20: 1 | AB20: 1 | AC20: 13170 | AD20: =SUMPRODUCT(Z20:AB20,$Z$2:$AB$2) -> 575 | AE20: 10.75 | AF20: 0.25 | AH20: 0.5 | AK20: 0.5 | AN20: =IF(ISBLANK(AE20),"",SUM(AE20:AF20,AH20:AL20)) -> 12 | AP20: =(AF20*$AF$2)+(AH20*$AH$2)+(AI20*$AI$2) -> 295 | AR20: 151.79 | AS20: =SUM(Y20,AP20,AR20,J20)+AD20 -> 6356.79 | AT20: 6356.79 | AU20: =SUM(AR20,AD20,Y20,J20) -> 6061.79 | AV20: =IFERROR((AS20-AU20)/AS20,"") -> 0.04640707 | AW20: =SUM($AS$8:AS20) -> 60990.78 | AX20: =IF(AS20=0,"",SUMIFS($AS$8:AS20, $BH$8:BH20, BH20)) -> 60990.78 | AY20: =IF(AND(D20>TODAY(),ISBLANK(H20)),"",IF(ISBLANK(AE20),"no drilling completed",AS20/(W20))) -> 277.58908 | AZ20: =IF(D20<TODAY(),HYPERLINK(BG20,"LINK"),"") -> LINK | BB20: https://www.coreplan.io/app/ddh1-drilling/speewah-mining-speewah-fluorite-project-wa/plods/1663- | BC20: =RIGHT(YEAR(D20),2) -> 25 | BD20: =IF(LEN(MONTH(D22))=1,_xlfn.TEXTJOIN(,,"0",MONTH(D22)),MONTH(D22)) -> 07 | BE20: =IF(LEN(DAY(D22))=1,_xlfn.TEXTJOIN(,,"0",DAY(D22)),DAY(D22)) -> 13 | BF20: =LEFT(E20,1) -> D | BG20: =CONCATENATE(BB20,BC20,BD20,BE20,BF20) -> https://www.coreplan.io/app/ddh1-drilling/speewah-mining-speewah-fluorite-project-wa/plods/1663-250713D | BH20: =TEXT(D20, "yyyy-mm") -> 2025-07
A21: =VLOOKUP(F21,'Tenement Lookup'!A:BH,60,FALSE) -> M 80/269 | B21: =VLOOKUP(F21,Purpose!$A$2:$B$334,2,FALSE) -> Met | C21: MET | D21: =D19+1 -> 45850.71 | E21: NS 5pm | F21: SF25_DMET022 | H21: Ben Payton | I21: 3 | J21: =IF(ISBLANK(I21),"",I21*$J$2) -> 390 | K21: 39.4 | L21: 60.6 | M21: =IF(ISBLANK(K21),"",L21-K21) -> 21.2 | P21: =IF(ISBLANK(N21),,O21-N21) -> 0 | S21: =IF(ISBLANK(Q21),,R21-Q21) -> 0 | V21: =IF(ISBLANK(T21),,U21-T21) -> 0 | W21: =IFERROR(M21+P21+S21+V21,"") -> 21.2 | X21: =IFERROR((M21*$M$2)+(P21*$P$2)+(S21*$S$2)+(V21*$V$2),"") -> 3710 | Y21: =IF(F21<>"",IF(X21<(AE21*$AE$2),(AE21*$AE$2),X21),"") -> 3910 | AD21: =SUMPRODUCT(Z21:AB21,$Z$2:$AB$2) -> 0 | AE21: 8.5 | AF21: 2.5 | AH21: 0.5 | AK21: 0.5 | AN21: =IF(ISBLANK(AE21),"",SUM(AE21:AF21,AH21:AL21)) -> 12 | AP21: =(AF21*$AF$2)+(AH21*$AH$2)+(AI21*$AI$2) -> 1330 | AR21: 117.93 | AS21: =SUM(Y21,AP21,AR21,J21)+AD21 -> 5747.93 | AT21: 5747.93 | AU21: =SUM(AR21,AD21,Y21,J21) -> 4417.93 | AV21: =IFERROR((AS21-AU21)/AS21,"") -> 0.23138765 | AW21: =SUM($AS$8:AS21) -> 66738.71 | AX21: =IF(AS21=0,"",SUMIFS($AS$8:AS21, $BH$8:BH21, BH21)) -> 66738.71 | AY21: =IF(AND(D21>TODAY(),ISBLANK(H21)),"",IF(ISBLANK(AE21),"no drilling completed",AS21/(W21))) -> 271.12877 | AZ21: =IF(D21<TODAY(),HYPERLINK(BG21,"LINK"),"") -> LINK | BB21: https://www.coreplan.io/app/ddh1-drilling/speewah-mining-speewah-fluorite-project-wa/plods/1663- | BC21: =RIGHT(YEAR(D21),2) -> 25 | BD21: =IF(LEN(MONTH(D23))=1,_xlfn.TEXTJOIN(,,"0",MONTH(D23)),MONTH(D23)) -> 07 | BE21: =IF(LEN(DAY(D23))=1,_xlfn.TEXTJOIN(,,"0",DAY(D23)),DAY(D23)) -> 13 | BF21: =LEFT(E21,1) -> N | BG21: =CONCATENATE(BB21,BC21,BD21,BE21,BF21) -> https://www.coreplan.io/app/ddh1-drilling/speewah-mining-speewah-fluorite-project-wa/plods/1663-250713N | BH21: =TEXT(D21, "yyyy-mm") -> 2025-07
A22: =VLOOKUP(F22,'Tenement Lookup'!A:BH,60,FALSE) -> M 80/269 | B22: =VLOOKUP(F22,Purpose!$A$2:$B$334,2,FALSE) -> Met | C22: MET | D22: =D20+1 -> 45851.21 | E22: DS 5am | F22: SF25_DMET022 | H22: Matthew Sing | I22: 3 | J22: =IF(ISBLANK(I22),"",I22*$J$2) -> 390 | K22: 60.6 | L22: 73.8 | M22: =IF(ISBLANK(K22),"",L22-K22) -> 13.2 | P22: =IF(ISBLANK(N22),,O22-N22) -> 0 | S22: =IF(ISBLANK(Q22),,R22-Q22) -> 0 | V22: =IF(ISBLANK(T22),,U22-T22) -> 0 | W22: =IFERROR(M22+P22+S22+V22,"") -> 13.2 | X22: =IFERROR((M22*$M$2)+(P22*$P$2)+(S22*$S$2)+(V22*$V$2),"") -> 2310 | Y22: =IF(F22<>"",IF(X22<(AE22*$AE$2),(AE22*$AE$2),X22),"") -> 4025 | AA22: 1 | AB22: 1 | AC22: 13170 | AD22: =SUMPRODUCT(Z22:AB22,$Z$2:$AB$2) -> 575 | AE22: 8.75 | AF22: 2.75 | AH22: 0.5 | AN22: =IF(ISBLANK(AE22),"",SUM(AE22:AF22,AH22:AL22)) -> 12 | AP22: =(AF22*$AF$2)+(AH22*$AH$2)+(AI22*$AI$2) -> 1445 | AR22: 53.23 | AS22: =SUM(Y22,AP22,AR22,J22)+AD22 -> 6488.23 | AT22: 6488.23 | AU22: =SUM(AR22,AD22,Y22,J22) -> 5043.23 | AV22: =IFERROR((AS22-AU22)/AS22,"") -> 0.22271097 | AW22: =SUM($AS$8:AS22) -> 73226.94 | AX22: =IF(AS22=0,"",SUMIFS($AS$8:AS22, $BH$8:BH22, BH22)) -> 73226.94 | AY22: =IF(AND(D22>TODAY(),ISBLANK(H22)),"",IF(ISBLANK(AE22),"no drilling completed",AS22/(W22))) -> 491.53258 | AZ22: =IF(D22<TODAY(),HYPERLINK(BG22,"LINK"),"") -> LINK | BB22: https://www.coreplan.io/app/ddh1-drilling/speewah-mining-speewah-fluorite-project-wa/plods/1663- | BC22: =RIGHT(YEAR(D22),2) -> 25 | BD22: =IF(LEN(MONTH(D24))=1,_xlfn.TEXTJOIN(,,"0",MONTH(D24)),MONTH(D24)) -> 07 | BE22: =IF(LEN(DAY(D24))=1,_xlfn.TEXTJOIN(,,"0",DAY(D24)),DAY(D24)) -> 14 | BF22: =LEFT(E22,1) -> D | BG22: =CONCATENATE(BB22,BC22,BD22,BE22,BF22) -> https://www.coreplan.io/app/ddh1-drilling/speewah-mining-speewah-fluorite-project-wa/plods/1663-250714D | BH22: =TEXT(D22, "yyyy-mm") -> 2025-07
A23: =VLOOKUP(F23,'Tenement Lookup'!A:BH,60,FALSE) -> M 80/269 | B23: =VLOOKUP(F23,Purpose!$A$2:$B$334,2,FALSE) -> Met | C23: MET | D23: =D21+1 -> 45851.71 | E23: NS 5pm | F23: SF25_DMET022 | H23: Ben Payton | I23: 3 | J23: =IF(ISBLANK(I23),"",I23*$J$2) -> 390 | K23: 73.8 | L23: 101.1 | M23: =IF(ISBLANK(K23),"",L23-K23) -> 27.3 | P23: =IF(ISBLANK(N23),,O23-N23) -> 0 | S23: =IF(ISBLANK(Q23),,R23-Q23) -> 0 | V23: =IF(ISBLANK(T23),,U23-T23) -> 0 | W23: =IFERROR(M23+P23+S23+V23,"") -> 27.3 | X23: =IFERROR((M23*$M$2)+(P23*$P$2)+(S23*$S$2)+(V23*$V$2),"") -> 4777.5 | Y23: =IF(F23<>"",IF(X23<(AE23*$AE$2),(AE23*$AE$2),X23),"") -> 5060 | AD23: =SUMPRODUCT(Z23:AB23,$Z$2:$AB$2) -> 0 | AE23: 11 | AF23: 0.5 | AH23: 0.5 | AN23: =IF(ISBLANK(AE23),"",SUM(AE23:AF23,AH23:AL23)) -> 12 | AP23: =(AF23*$AF$2)+(AH23*$AH$2)+(AI23*$AI$2) -> 410 | AR23: 117.93 | AS23: =SUM(Y23,AP23,AR23,J23)+AD23 -> 5977.93 | AT23: 5977.93 | AU23: =SUM(AR23,AD23,Y23,J23) -> 5567.93 | AV23: =IFERROR((AS23-AU23)/AS23,"") -> 0.068585614 | AW23: =SUM($AS$8:AS23) -> 79204.87 | AX23: =IF(AS23=0,"",SUMIFS($AS$8:AS23, $BH$8:BH23, BH23)) -> 79204.87 | AY23: =IF(AND(D23>TODAY(),ISBLANK(H23)),"",IF(ISBLANK(AE23),"no drilling completed",AS23/(W23))) -> 218.97179 | AZ23: =IF(D23<TODAY(),HYPERLINK(BG23,"LINK"),"") -> LINK | BB23: https://www.coreplan.io/app/ddh1-drilling/speewah-mining-speewah-fluorite-project-wa/plods/1663- | BC23: =RIGHT(YEAR(D23),2) -> 25 | BD23: =IF(LEN(MONTH(D25))=1,_xlfn.TEXTJOIN(,,"0",MONTH(D25)),MONTH(D25)) -> 07 | BE23: =IF(LEN(DAY(D25))=1,_xlfn.TEXTJOIN(,,"0",DAY(D25)),DAY(D25)) -> 14 | BF23: =LEFT(E23,1) -> N | BG23: =CONCATENATE(BB23,BC23,BD23,BE23,BF23) -> https://www.coreplan.io/app/ddh1-drilling/speewah-mining-speewah-fluorite-project-wa/plods/1663-250714N | BH23: =TEXT(D23, "yyyy-mm") -> 2025-07
A24: =VLOOKUP(F24,'Tenement Lookup'!A:BH,60,FALSE) -> M 80/269 | B24: =VLOOKUP(F24,Purpose!$A$2:$B$334,2,FALSE) -> Met | C24: MET | D24: =D22+1 -> 45852.21 | E24: DS 5am | F24: SF25_DMET022 | H24: Matthew Sing | I24: 3 | J24: =IF(ISBLANK(I24),"",I24*$J$2) -> 390 | K24: 101.1 | L24: 120.7 | M24: =IF(ISBLANK(K24),"",L24-K24) -> 19.6 | P24: =IF(ISBLANK(N24),,O24-N24) -> 0 | S24: =IF(ISBLANK(Q24),,R24-Q24) -> 0 | V24: =IF(ISBLANK(T24),,U24-T24) -> 0 | W24: =IFERROR(M24+P24+S24+V24,"") -> 19.6 | X24: =IFERROR((M24*$M$2)+(P24*$P$2)+(S24*$S$2)+(V24*$V$2),"") -> 3430 | Y24: =IF(F24<>"",IF(X24<(AE24*$AE$2),(AE24*$AE$2),X24),"") -> 3680 | AA24: 1 | AB24: 1 | AC24: 13170 | AD24: =SUMPRODUCT(Z24:AB24,$Z$2:$AB$2) -> 575 | AE24: 8 | AF24: 3.5 | AG24: rig move | AH24: 0.5 | AN24: =IF(ISBLANK(AE24),"",SUM(AE24:AF24,AH24:AL24)) -> 12 | AP24: =(AF24*$AF$2)+(AH24*$AH$2)+(AI24*$AI$2) -> 1790 | AS24: =SUM(Y24,AP24,AR24,J24)+AD24 -> 6435 | AT24: 6435 | AU24: =SUM(AR24,AD24,Y24,J24) -> 4645 | AV24: =IFERROR((AS24-AU24)/AS24,"") -> 0.27816628 | AW24: =SUM($AS$8:AS24) -> 85639.87 | AX24: =IF(AS24=0,"",SUMIFS($AS$8:AS24, $BH$8:BH24, BH24)) -> 85639.87 | AY24: =IF(AND(D24>TODAY(),ISBLANK(H24)),"",IF(ISBLANK(AE24),"no drilling completed",AS24/(W24))) -> 328.31633 | AZ24: =IF(D24<TODAY(),HYPERLINK(BG24,"LINK"),"") -> LINK | BA24: Pre-shift meeting, Pre-start all equipment, continue to drill PQ3, survey @ 108m and 117m, drill to EOH @ 120.7m, move equipment to bring in ST and pull out barrel, mast down, pack up site and move equipment to next hole, mast up and take mast shot, start setting up site | BB24: https://www.coreplan.io/app/ddh1-drilling/speewah-mining-speewah-fluorite-project-wa/plods/1663- | BC24: =RIGHT(YEAR(D24),2) -> 25 | BD24: =IF(LEN(MONTH(D26))=1,_xlfn.TEXTJOIN(,,"0",MONTH(D26)),MONTH(D26)) -> 07 | BE24: =IF(LEN(DAY(D26))=1,_xlfn.TEXTJOIN(,,"0",DAY(D26)),DAY(D26)) -> 15 | BF24: =LEFT(E24,1) -> D | BG24: =CONCATENATE(BB24,BC24,BD24,BE24,BF24) -> https://www.coreplan.io/app/ddh1-drilling/speewah-mining-speewah-fluorite-project-wa/plods/1663-250715D | BH24: =TEXT(D24, "yyyy-mm") -> 2025-07
A25: =VLOOKUP(F25,'Tenement Lookup'!A:BH,60,FALSE) -> M 80/269 | B25: =VLOOKUP(F25,Purpose!$A$2:$B$334,2,FALSE) -> Met | C25: MET | D25: =D23+1 -> 45852.71 | E25: NS 5pm | F25: SF25_DMET021 | H25: Ben Payton | I25: 3 | J25: =IF(ISBLANK(I25),"",I25*$J$2) -> 390 | K25: 0 | L25: 20.5 | M25: =IF(ISBLANK(K25),"",L25-K25) -> 20.5 | P25: =IF(ISBLANK(N25),,O25-N25) -> 0 | S25: =IF(ISBLANK(Q25),,R25-Q25) -> 0 | V25: =IF(ISBLANK(T25),,U25-T25) -> 0 | W25: =IFERROR(M25+P25+S25+V25,"") -> 20.5 | X25: =IFERROR((M25*$M$2)+(P25*$P$2)+(S25*$S$2)+(V25*$V$2),"") -> 3587.5 | Y25: =IF(F25<>"",IF(X25<(AE25*$AE$2),(AE25*$AE$2),X25),"") -> 3795 | AD25: =SUMPRODUCT(Z25:AB25,$Z$2:$AB$2) -> 0 | AE25: 8.25 | AF25: 3.25 | AH25: 0.5 | AN25: =IF(ISBLANK(AE25),"",SUM(AE25:AF25,AH25:AL25)) -> 12 | AP25: =(AF25*$AF$2)+(AH25*$AH$2)+(AI25*$AI$2) -> 1675 | AR25: 235.86 | AS25: =SUM(Y25,AP25,AR25,J25)+AD25 -> 6095.86 | AT25: 6095.86 | AU25: =SUM(AR25,AD25,Y25,J25) -> 4420.86 | AV25: =IFERROR((AS25-AU25)/AS25,"") -> 0.27477665 | AW25: =SUM($AS$8:AS25) -> 91735.73 | AX25: =IF(AS25=0,"",SUMIFS($AS$8:AS25, $BH$8:BH25, BH25)) -> 91735.73 | AY25: =IF(AND(D25>TODAY(),ISBLANK(H25)),"",IF(ISBLANK(AE25),"no drilling completed",AS25/(W25))) -> 297.35902 | AZ25: =IF(D25<TODAY(),HYPERLINK(BG25,"LINK"),"") -> LINK | BA25: Pre-shift meeting / Pre-start all equipment / Set up site / Drill PQ3 from surface / Ream 6.0m of PWT casing in hole as ground too hard from surface for Rock roller & PVC / Flush Hole clean / Drill on PQ3 DR38, RT38, LP10, ST25, LT95, DDH1 DL219 | BB25: https://www.coreplan.io/app/ddh1-drilling/speewah-mining-speewah-fluorite-project-wa/plods/1663- | BC25: =RIGHT(YEAR(D25),2) -> 25 | BD25: =IF(LEN(MONTH(D27))=1,_xlfn.TEXTJOIN(,,"0",MONTH(D27)),MONTH(D27)) -> 07 | BE25: =IF(LEN(DAY(D27))=1,_xlfn.TEXTJOIN(,,"0",DAY(D27)),DAY(D27)) -> 15 | BF25: =LEFT(E25,1) -> N | BG25: =CONCATENATE(BB25,BC25,BD25,BE25,BF25) -> https://www.coreplan.io/app/ddh1-drilling/speewah-mining-speewah-fluorite-project-wa/plods/1663-250715N | BH25: =TEXT(D25, "yyyy-mm") -> 2025-07
A26: =VLOOKUP(F26,'Tenement Lookup'!A:BH,60,FALSE) -> M 80/269 | B26: =VLOOKUP(F26,Purpose!$A$2:$B$334,2,FALSE) -> Met | C26: MET | D26: =D24+1 -> 45853.21 | E26: DS 5am | F26: SF25_DMET021 | H26: Matthew Sing | I26: 3 | J26: =IF(ISBLANK(I26),"",I26*$J$2) -> 390 | K26: 20.5 | L26: 50.5 | M26: =IF(ISBLANK(K26),"",L26-K26) -> 30 | P26: =IF(ISBLANK(N26),,O26-N26) -> 0 | S26: =IF(ISBLANK(Q26),,R26-Q26) -> 0 | V26: =IF(ISBLANK(T26),,U26-T26) -> 0 | W26: =IFERROR(M26+P26+S26+V26,"") -> 30 | X26: =IFERROR((M26*$M$2)+(P26*$P$2)+(S26*$S$2)+(V26*$V$2),"") -> 5250 | Y26: =IF(F26<>"",IF(X26<(AE26*$AE$2),(AE26*$AE$2),X26),"") -> 5250 | AA26: 1 | AB26: 1 | AC26: 13170 | AD26: =SUMPRODUCT(Z26:AB26,$Z$2:$AB$2) -> 575 | AE26: 10.5 | AF26: 1 | AH26: 0.5 | AN26: =IF(ISBLANK(AE26),"",SUM(AE26:AF26,AH26:AL26)) -> 12 | AP26: =(AF26*$AF$2)+(AH26*$AH$2)+(AI26*$AI$2) -> 640 | AR26: 879.56 | AS26: =SUM(Y26,AP26,AR26,J26)+AD26 -> 7734.56 | AT26: 7734.56 | AU26: =SUM(AR26,AD26,Y26,J26) -> 7094.56 | AV26: =IFERROR((AS26-AU26)/AS26,"") -> 0.082745496 | AW26: =SUM($AS$8:AS26) -> 99470.29 | AX26: =IF(AS26=0,"",SUMIFS($AS$8:AS26, $BH$8:BH26, BH26)) -> 99470.29 | AY26: =IF(AND(D26>TODAY(),ISBLANK(H26)),"",IF(ISBLANK(AE26),"no drilling completed",AS26/(W26))) -> 257.81867 | AZ26: =IF(D26<TODAY(),HYPERLINK(BG26,"LINK"),"") -> LINK | BA26: Continue to drill PQ3, survey @ 18m & 36m, pull out and run in softer bit, condition hole throughout shift | BB26: https://www.coreplan.io/app/ddh1-drilling/speewah-mining-speewah-fluorite-project-wa/plods/1663- | BC26: =RIGHT(YEAR(D26),2) -> 25 | BD26: =IF(LEN(MONTH(D28))=1,_xlfn.TEXTJOIN(,,"0",MONTH(D28)),MONTH(D28)) -> 07 | BE26: =IF(LEN(DAY(D28))=1,_xlfn.TEXTJOIN(,,"0",DAY(D28)),DAY(D28)) -> 16 | BF26: =LEFT(E26,1) -> D | BG26: =CONCATENATE(BB26,BC26,BD26,BE26,BF26) -> https://www.coreplan.io/app/ddh1-drilling/speewah-mining-speewah-fluorite-project-wa/plods/1663-250716D | BH26: =TEXT(D26, "yyyy-mm") -> 2025-07
A27: =VLOOKUP(F27,'Tenement Lookup'!A:BH,60,FALSE) -> M 80/269 | B27: =VLOOKUP(F27,Purpose!$A$2:$B$334,2,FALSE) -> Met | C27: MET | D27: =D25+1 -> 45853.71 | E27: NS 5pm | F27: SF25_DMET021 | H27: Ben Payton | I27: 3 | J27: =IF(ISBLANK(I27),"",I27*$J$2) -> 390 | K27: 50.5 | L27: 80.6 | M27: =IF(ISBLANK(K27),"",L27-K27) -> 30.1 | P27: =IF(ISBLANK(N27),,O27-N27) -> 0 | S27: =IF(ISBLANK(Q27),,R27-Q27) -> 0 | V27: =IF(ISBLANK(T27),,U27-T27) -> 0 | W27: =IFERROR(M27+P27+S27+V27,"") -> 30.1 | X27: =IFERROR((M27*$M$2)+(P27*$P$2)+(S27*$S$2)+(V27*$V$2),"") -> 5267.5 | Y27: =IF(F27<>"",IF(X27<(AE27*$AE$2),(AE27*$AE$2),X27),"") -> 5267.5 | AD27: =SUMPRODUCT(Z27:AB27,$Z$2:$AB$2) -> 0 | AE27: 10.25 | AF27: 1.25 | AH27: 0.5 | AN27: =IF(ISBLANK(AE27),"",SUM(AE27:AF27,AH27:AL27)) -> 12 | AP27: =(AF27*$AF$2)+(AH27*$AH$2)+(AI27*$AI$2) -> 755 | AR27: 236.49 | AS27: =SUM(Y27,AP27,AR27,J27)+AD27 -> 6648.99 | AT27: 6648.99 | AU27: =SUM(AR27,AD27,Y27,J27) -> 5893.99 | AV27: =IFERROR((AS27-AU27)/AS27,"") -> 0.11355108 | AW27: =SUM($AS$8:AS27) -> 106119.28 | AX27: =IF(AS27=0,"",SUMIFS($AS$8:AS27, $BH$8:BH27, BH27)) -> 106119.28 | AY27: =IF(AND(D27>TODAY(),ISBLANK(H27)),"",IF(ISBLANK(AE27),"no drilling completed",AS27/(W27))) -> 220.89668 | AZ27: =IF(D27<TODAY(),HYPERLINK(BG27,"LINK"),"") -> LINK | BA27: Drill PQ3, 54m & 72m surveys of hole, bit change due to worn bit, run back in, Drill on PQ3 | BB27: https://www.coreplan.io/app/ddh1-drilling/speewah-mining-speewah-fluorite-project-wa/plods/1663- | BC27: =RIGHT(YEAR(D27),2) -> 25 | BD27: =IF(LEN(MONTH(D29))=1,_xlfn.TEXTJOIN(,,"0",MONTH(D29)),MONTH(D29)) -> 07 | BE27: =IF(LEN(DAY(D29))=1,_xlfn.TEXTJOIN(,,"0",DAY(D29)),DAY(D29)) -> 16 | BF27: =LEFT(E27,1) -> N | BG27: =CONCATENATE(BB27,BC27,BD27,BE27,BF27) -> https://www.coreplan.io/app/ddh1-drilling/speewah-mining-speewah-fluorite-project-wa/plods/1663-250716N | BH27: =TEXT(D27, "yyyy-mm") -> 2025-07
